Workbook
Name Param.Startjahr: Parameter!$F$6
Name Param.Startalter: Parameter!$F$8
Name Param.DeportwertStart: Parameter!$F$31
Name Param.SparrateDepotMonatl: Parameter!$F$18
Name Param.SparrateFestgeldMonatl: Parameter!$F$19
Name Param.DeportwertStartPerformAnteil: Parameter!$F$32
Name Param.Teilfreistellung: Parameter!$F$12
Name Param.FireStartjahr: Parameter!$F$9
Name Param.SonstigEinmaligBeschreib1: Parameter!$C$67
Name Param.SonstigEinmaligBeschreib2: Parameter!$C$68
Name Param.SonstigEinmaligBeschreib3: Parameter!$C$69
Name Param.SonstigEinmaligBeschreib4: Parameter!$C$70
Name Param.SonstigEinmaligBeschreib5: Parameter!$C$71
Name Param.SonstigEinmaligBeschreib6: Parameter!$C$72
Name Param.SonstigEinmaligBeschreib7: Parameter!$C$73
Name Param.SonstigEinmaligBeschreib8: Parameter!$C$74
Name Param.SonstigEinmaligBeschreib9: Parameter!$C$75
Name Param.SonstigEinmaligBeschreib10: Parameter!$C$76
Name Param.FestgeldStart: Parameter!$F$44
Name Param.FestgeldZinssatz: Parameter!$F$45
Name Param.SparerPauschbetrag: Parameter!$F$13
Name Param.SonstigEinmaligBetrag1: Parameter!$D$67
Name Param.SonstigEinmaligBetrag2: Parameter!$D$68
Name Param.SonstigEinmaligBetrag3: Parameter!$D$69
Name Param.SonstigEinmaligBetrag4: Parameter!$D$70
Name Param.SonstigEinmaligBetrag5: Parameter!$D$71
Name Param.SonstigEinmaligBetrag6: Parameter!$D$72
Name Param.SonstigEinmaligBetrag7: Parameter!$D$73
Name Param.SonstigEinmaligBetrag8: Parameter!$D$74
Name Param.SonstigEinmaligBetrag9: Parameter!$D$75
Name Param.SonstigEinmaligBetrag10: Parameter!$D$76
Name Param.SonstigEinmaligJahr1: Parameter!$E$67
Name Param.SonstigEinmaligJahr2: Parameter!$E$68
Name Param.SonstigEinmaligJahr3: Parameter!$E$69
Name Param.SonstigEinmaligJahr4: Parameter!$E$70
Name Param.SonstigEinmaligJahr5: Parameter!$E$71
Name Param.SonstigEinmaligJahr6: Parameter!$E$72
Name Param.SonstigEinmaligJahr7: Parameter!$E$73
Name Param.SonstigEinmaligJahr8: Parameter!$E$74
Name Param.SonstigEinmaligJahr9: Parameter!$E$75
Name Param.SonstigEinmaligJahr10: Parameter!$E$76
Name Param.SonstigRegelmJahrBeginn10: Parameter!$G$62
Name Param.SonstigRegelmBeschreib1: Parameter!$C$53
Name Param.SonstigRegelmBeschreib2: Parameter!$C$54
Name Param.SonstigRegelmBeschreib3: Parameter!$C$55
Name Param.SonstigRegelmBeschreib4: Parameter!$C$56
Name Param.SonstigRegelmBeschreib5: Parameter!$C$57
Name Param.SonstigRegelmBeschreib6: Parameter!$C$58
Name Param.SonstigRegelmBeschreib7: Parameter!$C$59
Name Param.SonstigRegelmBeschreib8: Parameter!$C$60
Name Param.SonstigRegelmBeschreib9: Parameter!$C$61
Name Param.SonstigRegelmBeschreib10: Parameter!$C$62
Name Param.SonstigRegelmBetragJaehrl1: Parameter!$E$53
Name Param.SonstigRegelmBetragJaehrl2: Parameter!$E$54
Name Param.SonstigRegelmBetragJaehrl3: Parameter!$E$55
Name Param.SonstigRegelmBetragJaehrl4: Parameter!$E$56
Name Param.SonstigRegelmBetragJaehrl5: Parameter!$E$57
Name Param.SonstigRegelmBetragJaehrl6: Parameter!$E$58
Name Param.SonstigRegelmBetragJaehrl7: Parameter!$E$59
Name Param.SonstigRegelmBetragJaehrl8: Parameter!$E$60

Sheet Parameter
B1: FiRe-Spread - Beta | M1: v0.3.3
H2: =_xlfn.CONCAT(G37:G41)
F3: Graue Felder nicht bearbeiten (werden autom. berechnet)
C4: Grunddaten | H4: Ergebnis
C5: Jahresangaben | H5: In Zahlen
C6: Startjahr der Simulation | F6: 2026 | H6: Vermögen reicht bis ins Jahr: | K6: =IF(MIN(FIRE!BM5:BM100)=0,"bis ans Lebensende (~unendlich)",MIN(FIRE!BM5:BM100)-1) -> 2078 | R6: Ziel dieses Tools
C7: Monat der Vermögenserfassung | F7: 6 | H7: Vermögen reicht bis ins Lebensjahr: | K7: =IF(MIN(FIRE!BM5:BM100)=0,"bis ans Lebensende (~unendlich)",MIN(FIRE!BM5:BM100)-Param.Startjahr+Param.Startalter-1) -> 82 | R7: Errechnet wie lange das Vermögen bei vorgegebenden Sparrate und Entnahme ausreicht und berücksichtigt sonstige regelm. und einmalige Einzahlungen und Ausgaben.
C8: Alter zum Startjahr der Simulation | F8: 30 | H8: =IF(FIRE!BJ1<>"Festgeld positiv","Das Festgeld läuft irgendwann ins negative - Zu hohe einmalige Festgeld-Ausgabe geplant?",IF(_xlfn.CONCAT(G37:G41,N67:N76)<>"","Es besteht ein Fehler in diesem Tabellenblatt - siehe Zeile neben dem Begriff ""[Fehler]"" innerhalb dieses Tabellenblatts.","")) | R8: Depot und Festgeld verschiedene Rendite
C9: FIRE-Startjahr | F9: 2045 | R9: Die Entnahme erfolgt immer aus dem Depot _und_ dem Festgeld. Immer proportional zum jeweiligen Bestand. So leeren sich beide Konten synchron und sollten ungefähr zeitgleich leer sein.
H10: In Worten | R10: Sonstige Lebensereignisse werden berücksichtigt (z.B. Auszahlung von privaten Lebensversicherungen, staatl. Rentenzahlung)
C11: Erwartete Steuern + Inflation | H11: =IF(Param.FireStartjahr=Param.Startjahr,"Wenn du direkt im Startjahr in die Entnahmephase gehst (kein Ansparjahr),","Wenn du mit den angegebenen Parametern bis zum Jahr "&Param.FireStartjahr-1&" jährlich "&TEXT(Param.SparrateGesamtJaehrlich,"#.##0")&"€ einzahlst und im Dezember "&Param.FireStartjahr-1&" aufhörst zu arbeiten/einzuzahlen,")&" steht dir ab Januar "&Param.FireStartjahr&" "&IF(MIN(FIRE!BM5:BM100)=0,"bis ans Lebensende (~unendlich)","bis ins Jahr "&MIN(FIRE!BM5:BM100)-1&" (Alter: "&MIN(FIRE!BM5:BM100)-Param.Startjahr+Param.Startalter-1&")")&" jährlich "&TEXT(Param.EntnahmeBetragStart,"#.##0")&"€ (real) zur Verfügung"&IF(MIN(FIRE!BM5:BM100)=0," (dann gibt es auch noch Restkapital)."," (= Pleite im Alter von "&MIN(FIRE!BM5:BM100)-Param.Startjahr+Param.Startalter&").") -> Wenn du mit den angegebenen Parametern bis zum Jahr 2044 jährlich 7.800€ einzahlst und im Dezember 2044 aufhörst zu arbeiten/einzuzahlen, steht dir ab Januar 2045 bis ins Jahr 2078 (Alter: 82) jährlich 30.000€ (real) zur Verfügung (= Pleite im Alter von 83). | R11: Nachvollziehbare Berechnung mit Möglichkeit zur Meldung/Korrektur von Fehlern (in Online-Tools nicht immer möglich)
C12: Teilfreistellung Depot | F12: 0.3 | R12: Annäherung: Versteuerung den Entnahmen unter Berücksichtigung des Sparer-Pauschbetrag (_keine_ Günstigerprüfung!)
C13: Sparer Pauschbetrag | F13: 1000 | R13: Möglichkeit zur Simulation von der Depotentwicklung in frei wählbaren Rendite-starken/-schwachen Jahren.
C14: KapSt (inkl Soli) | F14: =0.25*1.055 -> 0.26375 | R14: Eine SWR wird nicht berechnet oder berücksichtigt.
C15: Inflationsrate p.a. | F15: 0.025
R16: Anforderungen
C17: Einzahlungen bis Rentenbeginn | R17: keine Makros
C18: Depot - Sparrate monatlich | F18: 500 | R18: Läuft in
C19: Festgeld - Sparrate monatlich | F19: 150 | R19: Planmaker (Softmaker)
C20: Dynamische Anpassung der Sparrate in % (jährl. Erhöhung gilt für Depot und Festgeld) | F20: 0 | R20: LibreCalc (LibreOffice)
C21: Gesamtsparrate - monatlich (im 1. Jahr / wird in Folgejahren u.U.dynamisch erhöht) | F21: =Param.SparrateDepotMonatl+Param.SparrateFestgeldMonatl -> 650 | R21: Wahrscheinlich auch in Excel (MS Office)
C22: Gesamtsparrate - jährlich (im 1. Jahr / wird in Folgejahren u.U. dynamisch erhöht) | F22: =F21*12 -> 7800
R23: Annahmen / Rechnerverhalten
C24: Entnahmeplan ab Rentenbeginn | R24: - Depotentwicklung wird berechnet unter Annahme, dass die Entnahme (während Entnahmephasen) jeweils zum Jahresbeginn erfolgt. Die Einzahlung/Verzinsung (während Ansparphase) erfolgt monatlich.
C25: Jährliche Entnahme (real im heutigen Jahr) | F25: 30000 | R25: - Vereinfachung: Die sonstigen regelm. / einmaligen Einkünfte und Ausgaben werden berücksichtig, wie eine Bewegung zum jeweiligen Jahrebeginn (auch wenn z.B. die regelm. Einkunft "staatl. Rente" monatlich erfolgt).
C26: Jährliche Entnahme (real zum 1. Entnahmejahr) | F26: =F25*(1+F15)^(F9-F6) -> 47959.506 | R26: - Sparer-Freibetrag wird immer zuerst von den Festgelderträgen abgezogen (auch wenn keine Entnahme erfolgt). Wenn die Erträge auf Festgeld kleiner sind als der Sparerpauschbetrag (z.B. 1.000€) wird der Rest des Sparerpauschbetrags von der steuerpflicht der Depoterträge abgezogen.
R27: - Entnahme aus Depot und Festgeld ist immer proportial zum jeweiligen Depot-/Kontowert
R28: - mit "Festgeldkonto" ist ein beliebiges Konto gemeint (egal. ob Giro/Tagesgeld/Festgeldkonto). Es könnte auch ein Depot mit Geldmarkt-ETF (=ohne Teilfreistellung) sein, das relativ konstante Rendite/Zins abwirft.
C29: Vermögen zum Beginn des Startjahres der Simulation
C30: Depot | R30: Nicht berücksichtigt:
C31: Depotwert Start € | F31: 300000 | R31: - keine Günstigerprüfung (https://frugalisten.de/steuern-kapitalertraege-privatier-optimieren/)
C32: Davon Performance (Gewinn vom Gesamtdepotwert) | F32: 120000 | R32: - FiFo-Prinzip beim Verkauf von Wertpapieranteilen wird nicht berücksichtigt
C33: Bisherige Depot-Performance in % | F33: =IFERROR(F32/(F31-F32),0) -> 0.66666667 | R33: - keine Berücksichtigung des Renditereihenfolgerisikos / Sequence of Returns Risk (über "Außergewöhnliche Renditen" kann stark vereinfacht "gespielt"/"simuliert" werden)
C34: Depot-Renditeerwartung jährlich (nominal) | R34: - keine Monte Carlo Simulation
C35: Erwartete "Standard-Rendite" (nominal) | F35: 0.06 | R35: - Vorabpauschale wird nicht berücksichtigt
C36: Optional [!] - Außergewöhnliche Renditen (nominal) | D36: Beginn | E36: Ende | F36: %
C37: Schwache Globalwirtschaft | D37: 2026 | E37: 2028 | F37: 0.03 | G37: =IF(Param.DepotRenditeSpezBeginn1>Param.DepotRenditeSpezEnde1,"[Fehler]","") | R37: Verbesserungspotential
C38: Schleppende Erhohlung | D38: 2030 | E38: 2033 | F38: 0.04 | G38: =IF(AND(Param.DepotRenditeSpezBeginn2&Param.DepotRenditeSpezEnde2<>"",OR(Param.DepotRenditeSpezBeginn2<=Param.DepotRenditeSpezEnde1,Param.DepotRenditeSpezEnde2<Param.DepotRenditeSpezBeginn2)),"[Fehler]","") | R38: Überprüfen ob überall die richtigen Begriffe verwendet wurden (z.B. Performance vs Gewinnanteil, Nominal vs Real, Brutto vs Netto)
C39: Starke Jahre | D39: 2045 | E39: 2047 | F39: 0.07 | G39: =IF(AND(Param.DepotRenditeSpezBeginn3&Param.DepotRenditeSpezEnde3<>"",OR(Param.DepotRenditeSpezBeginn3<=MAX(E37:E38),Param.DepotRenditeSpezEnde3<Param.DepotRenditeSpezBeginn3)),"[Fehler]","") | R39: Überprüfen der Berechnungen
G40: =IF(AND(Param.DepotRenditeSpezBeginn4&Param.DepotRenditeSpezEnde4<>"",OR(Param.DepotRenditeSpezBeginn4<=MAX(E37:E39),Param.DepotRenditeSpezEnde4<Param.DepotRenditeSpezBeginn4)),"[Fehler]","") | R40: Im Speziellen die Berechnung in den folgenden Spalten überprüfen:
G41: =IF(AND(Param.DepotRenditeSpezBeginn5&Param.DepotRenditeSpezEnde5<>"",OR(Param.DepotRenditeSpezBeginn5<=MAX(E37:E40),Param.DepotRenditeSpezEnde5<Param.DepotRenditeSpezBeginn5)),"[Fehler]","") | R41: - Depot - benötigte Entnahme inkl. KapErtrgSteuern
R42: - Depotwert nach Rendite inkl. Einzahlungen
C43: Festgeld (oder vergleichare liquide Anlagen wie Tagesgeld etc.) | R43: - Gewinn nach Entnahme
C44: Festgeld Start € | F44: 100000 | R44: Hinweis anzeigen wenn eine Günstigerprüfung sinnvoll wäre (die jährliche Steuerlast auf die Kapitelerträge aus Depot- & Festgeld-Entnahmen wird bereits berechnet)
C45: Festgeld Zinssatz (nominal) | F45: 0.02 | R45: Kommentare in den Zellen überprüfen / verbessern
R46: Gewinnanteil korrekt berechnet (unter Berücksichtigung der Enzahlung und Entnahme)?
C47: Gesamtvermögen | F47: =F31+F44 -> 400000 | R47: Einmalige Einkünfte auf das Depot einzahlen (statt auf Festgeld) - Entwicklung der Funktion ist bereits gestartet
F48: ="(Depot: "&TEXT(Param.DeportwertStart/Param.Gesamtvermoegen,"0%")&" / Festgeld: "&TEXT(Param.FestgeldStart/Param.Gesamtvermoegen,"0%")&")" -> (Depot: 75% / Festgeld: 25%)
N49: Grafik skalieren. Noch ein "Lebendsende-Jahr" als Feld/Option ergänzen?
B51: sonstige regelm. Einkünfte (z.B. Mieten) und Ausgaben (z.B. KV) - außerhalb der normalen Ansparphase / Entnahmeplans
C52: Beschreibung (erwarteter Betrag im 1. Jahr - "Beginn"-Datum) | D52: Monatl. (netto) | E52: Jährl. | F52: Steigerung p.a. | G52: Beginn | H52: Ende | I52: Kommentar
B53: 1 | C53: Staatl. Rente (erwarteter Betrag im 1. Jahr der Rentenzahlung) | D53: 1500 | E53: =12*D53 -> 18000 | F53: 0.01 | G53: 2063 | H53: 2200 | I53: staatl. Rente bis Lebensende. Erwartung, dass staatl. Rente jährl. 1% steigt
B54: 2 | C54: Krankenversicherung (KV) | D54: -600 | E54: =12*D54 -> -7200 | F54: 0.02 | G54: =F9 -> 2045 | H54: =G53-1 -> 2062
B55: 3 | C55: Mieteinkunft | D55: 300 | E55: =12*D55 -> 3600 | F55: 0.01 | G55: 2028 | H55: 2039 | I55: Verkaufspreis geht als einmalige Einkunft auf das Festgeldkonto
B56: 4 | E56: =12*D56 -> 0
B57: 5 | E57: =12*D57 -> 0
B58: 6 | E58: =12*D58 -> 0
B59: 7 | E59: =12*D59 -> 0
B60: 8 | E60: =12*D60 -> 0
B61: 9 | E61: =12*D61 -> 0
B62: 10 | E62: =12*D62 -> 0
B65: sonstige einmalige Einkünfte (z.B. Auszahlung Lebensvers.) und Ausgaben (z.B. Autokauf) - außerhalb der normalen Ansparphase / Entnahmeplans | N65: Aktuell kann ein einmaliges Ereignis nur auf das Festgeldkonto gehen. Depot funktioniert _noch_ nicht.
C66: Beschreibung | D66: Betrag (netto) | E66: Jahr | F66: Depot / Festg. | G66: Kommentar
B67: 1 | C67: Auszahlung Kapitallebensversicherung (Einmalzahlung) | D67: 74000 | E67: 2056 | F67: Festgeld | N67: =IF(AND(Param.SonstigEinmaligBetrag1<>"",OR(Param.SonstigEinmaligJahr1="",Param.SonstigEinmaligKonto1="")),"[Fehler]",IF(AND(Param.SonstigEinmaligKonto1="Depot",Param.SonstigEinmaligBetrag1<0),"[Fehler] - Wenn ""Depot"", darf der Betrag nicht negativ sein",""))
B68: 2 | C68: Autokauf | D68: -25000 | E68: 2030 | F68: Festgeld | N68: =IF(AND(Param.SonstigEinmaligBetrag2<>"",OR(Param.SonstigEinmaligJahr2="",Param.SonstigEinmaligKonto2="")),"[Fehler]",IF(AND(Param.SonstigEinmaligKonto2="Depot",Param.SonstigEinmaligBetrag2<0),"[Fehler] - Wenn ""Depot"", darf der Betrag nicht negativ sein",""))
B69: 3 | C69: Verkauf Immobilie | D69: 100000 | E69: 2040 | F69: Festgeld | N69: =IF(AND(Param.SonstigEinmaligBetrag3<>"",OR(Param.SonstigEinmaligJahr3="",Param.SonstigEinmaligKonto3="")),"[Fehler]",IF(AND(Param.SonstigEinmaligKonto3="Depot",Param.SonstigEinmaligBetrag3<0),"[Fehler] - Wenn ""Depot"", darf der Betrag nicht negativ sein",""))
B70: 4 | N70: =IF(AND(Param.SonstigEinmaligBetrag4<>"",OR(Param.SonstigEinmaligJahr4="",Param.SonstigEinmaligKonto4="")),"[Fehler]",IF(AND(Param.SonstigEinmaligKonto4="Depot",Param.SonstigEinmaligBetrag4<0),"[Fehler] - Wenn ""Depot"", darf der Betrag nicht negativ sein",""))
B71: 5 | N71: =IF(AND(Param.SonstigEinmaligBetrag5<>"",OR(Param.SonstigEinmaligJahr5="",Param.SonstigEinmaligKonto5="")),"[Fehler]",IF(AND(Param.SonstigEinmaligKonto5="Depot",Param.SonstigEinmaligBetrag5<0),"[Fehler] - Wenn ""Depot"", darf der Betrag nicht negativ sein",""))
B72: 6 | N72: =IF(AND(Param.SonstigEinmaligBetrag6<>"",OR(Param.SonstigEinmaligJahr6="",Param.SonstigEinmaligKonto6="")),"[Fehler]",IF(AND(Param.SonstigEinmaligKonto6="Depot",Param.SonstigEinmaligBetrag6<0),"[Fehler] - Wenn ""Depot"", darf der Betrag nicht negativ sein",""))
B73: 7 | N73: =IF(AND(Param.SonstigEinmaligBetrag7<>"",OR(Param.SonstigEinmaligJahr7="",Param.SonstigEinmaligKonto7="")),"[Fehler]",IF(AND(Param.SonstigEinmaligKonto7="Depot",Param.SonstigEinmaligBetrag7<0),"[Fehler] - Wenn ""Depot"", darf der Betrag nicht negativ sein",""))
B74: 8 | N74: =IF(AND(Param.SonstigEinmaligBetrag8<>"",OR(Param.SonstigEinmaligJahr8="",Param.SonstigEinmaligKonto8="")),"[Fehler]",IF(AND(Param.SonstigEinmaligKonto8="Depot",Param.SonstigEinmaligBetrag8<0),"[Fehler] - Wenn ""Depot"", darf der Betrag nicht negativ sein",""))
B75: 9 | N75: =IF(AND(Param.SonstigEinmaligBetrag9<>"",OR(Param.SonstigEinmaligJahr9="",Param.SonstigEinmaligKonto9="")),"[Fehler]",IF(AND(Param.SonstigEinmaligKonto9="Depot",Param.SonstigEinmaligBetrag9<0),"[Fehler] - Wenn ""Depot"", darf der Betrag nicht negativ sein",""))
B76: 10 | N76: =IF(AND(Param.SonstigEinmaligBetrag10<>"",OR(Param.SonstigEinmaligJahr10="",Param.SonstigEinmaligKonto10="")),"[Fehler]",IF(AND(Param.SonstigEinmaligKonto10="Depot",Param.SonstigEinmaligBetrag10<0),"[Fehler] - Wenn ""Depot"", darf der Betrag nicht negativ sein",""))

Sheet FIRE
U1: ist die Einzahlung korrekt in den Gewinnanteil eingerechnet? | AO1: ="Die _jährliche_ Standard-Rendite von "&Param.DepotRenditeDefault*100&"% entspricht einer _monatlichen_ Rendite von "&ROUND(((1+Param.DepotRenditeDefault)^(1/12)-1)*100,2)&"%." -> Die _jährliche_ Standard-Rendite von 6% entspricht einer _monatlichen_ Rendite von 0,49%. | BJ1: =IF(MIN(BJ5:BJ90)<0,"Festgeld negativ","Festgeld positiv") -> Festgeld positiv | BM1: Vermögen reicht bis:
D2: sonstige regelm. Einkünfte (z.B. Mieten) und Ausgaben (z.B. KV) - außerhalb d. norm. Ansparphase/Entnahmeplans | S2: Depot | AP2: Festgeld | BM2: ="Jahr: "&IF(MIN(BM5:BM100)=0,"unendlich",MIN(BM5:BM100)-1&" (Unzureichend ab: "&MIN(BM5:BM100))&")" -> Jahr: 2078 (Unzureichend ab: 2079) | BR2: macht keinen Sinn, wenn die "gesamte entnahme" negativ ist (z.B. wenn eine hohe Lebensverscherung ausgezahlt wurde)
P3: Vermögensaufteilung | V3: sonstige einmalige Einzahlungen ins Depot - außerhalb d. norm. Ansparphase | AS3: sonstige einmalige Einkünfte (z.B. Auszahlung Lebensvers.) und Ausgaben (z.B. Autokauf) - außerhalb d. norm. Ansparphase/Entnahmeplans | BM3: ="Alter: "&MIN(FIRE!BM5:BM100)-Param.Startjahr+Param.Startalter-1 -> Alter: 82
A4: Jahr | B4: Alter | C4: benötigtes Kapital (real) (zum ausgeben, gemäß Entnahmeplan) | D4: =Param.SonstigRegelmBeschreib1 -> Staatl. Rente (erwarteter Betrag im 1. Jahr der Rentenzahlung) | E4: =Param.SonstigRegelmBeschreib2 -> Krankenversicherung (KV) | F4: =Param.SonstigRegelmBeschreib3 -> Mieteinkunft | G4: =Param.SonstigRegelmBeschreib4 -> 0 | H4: =Param.SonstigRegelmBeschreib5 -> 0 | I4: =Param.SonstigRegelmBeschreib6 -> 0 | J4: =Param.SonstigRegelmBeschreib7 -> 0 | K4: =Param.SonstigRegelmBeschreib8 -> 0 | L4: =Param.SonstigRegelmBeschreib9 -> 0 | M4: =Param.SonstigRegelmBeschreib10 -> 0 | N4: benötigte Entnahme (nach Berücksichtigung der sonst. regelm. Einkünfte/Ausgaben) | O4: Überschuss aus sonstigen Einkünften/Ausgaben (falls Einkünfte höher benötigtes Kapital) | P4: Gesamtvermögen (vor Entnahme) | Q4: % Depot | R4: % Festgeld | S4: Depot Start | T4: Gewinnanteil am Depotwert | U4: Depot - jährl. Einzahlung während Ansparphase | V4: =IF(Param.SonstigEinmaligKonto1="Depot",Param.SonstigEinmaligBeschreib1,"") | W4: =IF(Param.SonstigEinmaligKonto2="Depot",Param.SonstigEinmaligBeschreib2,"") | X4: =IF(Param.SonstigEinmaligKonto3="Depot",Param.SonstigEinmaligBeschreib3,"") | Y4: =IF(Param.SonstigEinmaligKonto4="Depot",Param.SonstigEinmaligBeschreib4,"") | Z4: =IF(Param.SonstigEinmaligKonto5="Depot",Param.SonstigEinmaligBeschreib5,"") | AA4: =IF(Param.SonstigEinmaligKonto6="Depot",Param.SonstigEinmaligBeschreib6,"") | AB4: =IF(Param.SonstigEinmaligKonto7="Depot",Param.SonstigEinmaligBeschreib7,"") | AC4: =IF(Param.SonstigEinmaligKonto8="Depot",Param.SonstigEinmaligBeschreib8,"") | AD4: =IF(Param.SonstigEinmaligKonto9="Depot",Param.SonstigEinmaligBeschreib9,"") | AE4: =IF(Param.SonstigEinmaligKonto10="Depot",Param.SonstigEinmaligBeschreib10,"") | AF4: Verfügbarer Pauschbetrag (nach versteuerung von Festgeldzins) | AG4: Depot - benötigte Entnahme ohne KapErtrgSteuern | AH4: Depot - benötigte Entnahme inkl. KapErtrgSteuern | AI4: Steuer | AJ4: Gewinn nach Entnahme | AK4: Depotwert nach Entnahme | AL4: Depotwert nach Rendite inkl. Einzahlungen | AM4: Gewinn nach Rendite | AN4: Gewinnquote | AO4: Monatlicher Zinssatz (umgerechnet "erwarteter Rendite") | AP4: Festgeld Start | AQ4: Festgeld - Einzahlung während Ansparphase | AR4: Einzahlung aus Überschuss aus regelm. Einkünften | AS4: =IF(Param.SonstigEinmaligKonto1="Festgeld",Param.SonstigEinmaligBeschreib1,"") -> Auszahlung Kapitallebensversicherung (Einmalzahlung) | AT4: =IF(Param.SonstigEinmaligKonto2="Festgeld",Param.SonstigEinmaligBeschreib2,"") -> Autokauf | AU4: =IF(Param.SonstigEinmaligKonto3="Festgeld",Param.SonstigEinmaligBeschreib3,"") -> Verkauf Immobilie | AV4: =IF(Param.SonstigEinmaligKonto4="Festgeld",Param.SonstigEinmaligBeschreib4,"") | AW4: =IF(Param.SonstigEinmaligKonto5="Festgeld",Param.SonstigEinmaligBeschreib5,"") | AX4: =IF(Param.SonstigEinmaligKonto6="Festgeld",Param.SonstigEinmaligBeschreib6,"") | AY4: =IF(Param.SonstigEinmaligKonto7="Festgeld",Param.SonstigEinmaligBeschreib7,"") | AZ4: =IF(Param.SonstigEinmaligKonto8="Festgeld",Param.SonstigEinmaligBeschreib8,"") | BA4: =IF(Param.SonstigEinmaligKonto9="Festgeld",Param.SonstigEinmaligBeschreib9,"") | BB4: =IF(Param.SonstigEinmaligKonto10="Festgeld",Param.SonstigEinmaligBeschreib10,"") | BC4: Festgeld Entnahme für Entnahmeplan (keine "sonstige Einkunft/Ausgabe") | BD4: Rendite % | BE4: Brutto Zinsen | BF4: Genutzter Pauschbetrag | BG4: Nach Pausch. | BH4: Steuer | BI4: Netto Zinsen | BJ4: Festgeld Ende inkl. Zinsen (nach Einzahl. & Entnahme) | BK4: Gesamtverm. € | BL4: Gesamtverm. real € | BM4: Jahr in dem das Gesamtvermögen _nicht_ mehr für die geplante Entnahme reicht | BN4: Gesamte geplante + regelm. Entnahmen (aus Depot & Festgeldkonto) | BO4: sonstige einmalige Einkünft & Ausgaben | BP4: Gesamte Entnahmen | BQ4: Gezahlte Steuern (auf Depot und Festgeld) | BR4: Entnahmerate / Withdrawing rate
A5: =Parameter!F6 -> 2026 | B5: =Param.Startalter -> 30 | C5: =IF(A5<Param.FireStartjahr,0,Param.EntnahmeBetragStart*(1+Param.Inflationsrate)^(A5-Param.Startjahr)) -> 0 | D5: =IF(OR($A5<Param.SonstigRegelmJahrBeginn1,$A5>Param.SonstigRegelmJahrEnd1),0,Param.SonstigRegelmBetragJaehrl1*(1+Param.SonstigRegelmSteig1)^(A5-Param.SonstigRegelmJahrBeginn1)) -> 0 | E5: =IF(OR($A5<Param.SonstigRegelmJahrBeginn2,$A5>Param.SonstigRegelmJahrEnd2),0,Param.SonstigRegelmBetragJaehrl2*(1+Param.SonstigRegelmSteig2)^($A5-Param.SonstigRegelmJahrBeginn2)) -> 0 | F5: =IF(OR($A5<Param.SonstigRegelmJahrBeginn3,$A5>Param.SonstigRegelmJahrEnd3),0,Param.SonstigRegelmBetragJaehrl3*(1+Param.SonstigRegelmSteig3)^($A5-Param.SonstigRegelmJahrBeginn3)) -> 0 | G5: =IF(OR($A5<Param.SonstigRegelmJahrBeginn4,$A5>Param.SonstigRegelmJahrEnd4),0,Param.SonstigRegelmBetragJaehrl4*(1+Param.SonstigRegelmSteig4)^($A5-Param.SonstigRegelmJahrBeginn4)) -> 0 | H5: =IF(OR($A5<Param.SonstigRegelmJahrBeginn5,$A5>Param.SonstigRegelmJahrEnd5),0,Param.SonstigRegelmBetragJaehrl5*(1+Param.SonstigRegelmSteig5)^($A5-Param.SonstigRegelmJahrBeginn5)) -> 0 | I5: =IF(OR($A5<Param.SonstigRegelmJahrBeginn6,$A5>Param.SonstigRegelmJahrEnd6),0,Param.SonstigRegelmBetragJaehrl6*(1+Param.SonstigRegelmSteig6)^($A5-Param.SonstigRegelmJahrBeginn6)) -> 0 | J5: =IF(OR($A5<Param.SonstigRegelmJahrBeginn7,$A5>Param.SonstigRegelmJahrEnd7),0,Param.SonstigRegelmBetragJaehrl7*(1+Param.SonstigRegelmSteig7)^($A5-Param.SonstigRegelmJahrBeginn7)) -> 0 | K5: =IF(OR($A5<Param.SonstigRegelmJahrBeginn8,$A5>Param.SonstigRegelmJahrEnd8),0,Param.SonstigRegelmBetragJaehrl8*(1+Param.SonstigRegelmSteig8)^($A5-Param.SonstigRegelmJahrBeginn8)) -> 0 | L5: =IF(OR($A5<Param.SonstigRegelmJahrBeginn9,$A5>Param.SonstigRegelmJahrEnd9),0,Param.SonstigRegelmBetragJaehrl9*(1+Param.SonstigRegelmSteig9)^($A5-Param.SonstigRegelmJahrBeginn9)) -> 0 | M5: =IF(OR($A5<Param.SonstigRegelmJahrBeginn10,$A5>Param.SonstigRegelmJahrEnd10),0,Param.SonstigRegelmBetragJaehrl10*(1+Param.SonstigRegelmSteig10)^($A5-Param.SonstigRegelmJahrBeginn10)) -> 0 | N5: =MAX(0,C5-SUM(D5:M5)) -> 0 | O5: =IF(N5<=0,SUM(D5:M5)-C5,0) -> 0 | P5: =S5+AP5 -> 400000 | Q5: =IF(P5>0,S5/P5,0) -> 0.75 | R5: =IF(P5>0,AP5/P5,0) -> 0.25 | S5: =Param.DeportwertStart -> 300000 | T5: =Param.DeportwertStartPerformAnteil -> 120000 | U5: =IF(A5<Param.FireStartjahr,Param.SparrateDepotMonatl*(13-Param.StartmonatVermoegensstand)*(1+Param.SparrateDynamikJaehrl)^($A5-Param.Startjahr),0) -> 3500 | V5: =IF(AND(Param.SonstigEinmaligKonto1="Depot",$A5=Param.SonstigEinmaligJahr1),Param.SonstigEinmaligBetrag1,0) -> 0 | W5: =IF(AND(Param.SonstigEinmaligKonto2="Depot",$A5=Param.SonstigEinmaligJahr2),Param.SonstigEinmaligBetrag2,0) -> 0 | X5: =IF(AND(Param.SonstigEinmaligKonto3="Depot",$A5=Param.SonstigEinmaligJahr3),Param.SonstigEinmaligBetrag3,0) -> 0 | Y5: =IF(AND(Param.SonstigEinmaligKonto4="Depot",$A5=Param.SonstigEinmaligJahr4),Param.SonstigEinmaligBetrag4,0) -> 0 | Z5: =IF(AND(Param.SonstigEinmaligKonto5="Depot",$A5=Param.SonstigEinmaligJahr5),Param.SonstigEinmaligBetrag5,0) -> 0 | AA5: =IF(AND(Param.SonstigEinmaligKonto6="Depot",$A5=Param.SonstigEinmaligJahr6),Param.SonstigEinmaligBetrag6,0) -> 0 | AB5: =IF(AND(Param.SonstigEinmaligKonto7="Depot",$A5=Param.SonstigEinmaligJahr7),Param.SonstigEinmaligBetrag7,0) -> 0 | AC5: =IF(AND(Param.SonstigEinmaligKonto8="Depot",$A5=Param.SonstigEinmaligJahr8),Param.SonstigEinmaligBetrag8,0) -> 0 | AD5: =IF(AND(Param.SonstigEinmaligKonto9="Depot",$A5=Param.SonstigEinmaligJahr9),Param.SonstigEinmaligBetrag9,0) -> 0 | AE5: =IF(AND(Param.SonstigEinmaligKonto10="Depot",$A5=Param.SonstigEinmaligJahr10),Param.SonstigEinmaligBetrag10,0) -> 0 | AF5: =Param.SparerPauschbetrag-BF5 -> 0 | AG5: =IF(AND(A5>=Param.FireStartjahr,S5>0),MIN(N5*Q5,S5),0) -> 0 | AH5: =IF(AG5<=0,0,IF(S5<=0,0,AG5/(1-MAX(0,((T5/S5)*(1-Param.Teilfreistellung)-MIN(AF5,AG5)/AG5)*Param.KapSt)))) -> 0 | AI5: =AH5-AG5 -> 0 | AJ5: =T5-AH5*(T5/S5) -> 120000 | AK5: =S5-AH5 -> 300000 | AL5: =FV(AO5,(13-Param.StartmonatVermoegensstand),-(U5/(13-Param.StartmonatVermoegensstand)),-AK5,0) -> 308743.65 | AM5: =AJ5+AL5-AK5-U5 -> 125243.65 | AN5: =AM5/AL5 -> 0.40565579 | AO5: =(1+IF(AND(A5>=Param.DepotRenditeSpezBeginn1,A5<=Param.DepotRenditeSpezEnde1),Param.DepotRenditeSpezProz1,IF(AND(A5>=Param.DepotRenditeSpezBeginn2,A5<=Param.DepotRenditeSpezEnde2),Param.DepotRenditeSpezProz2,IF(AND(A5>=Param.DepotRenditeSpezBeginn3,A5<=Param.DepotRenditeSpezEnde3),Param.DepotRenditeSpezProz3,IF(AND(A5>=Param.DepotRenditeSpezBeginn4,A5<=Param.DepotRenditeSpezEnde4),Param.DepotRenditeSpezProz4,IF(AND(A5>=Param.DepotRenditeSpezBeginn5,A5<=Param.DepotRenditeSpezEnde5),Param.DepotRenditeSpezProz5,Param.DepotRenditeDefault))))))^(1/12)-1 -> 0.0024662698 | AP5: =Param.FestgeldStart -> 100000 | AQ5: =IF(A5<Param.FireStartjahr,Param.SparrateFestgeldMonatl*(13-Param.StartmonatVermoegensstand)*(1+Param.SparrateDynamikJaehrl)^($A5-Param.Startjahr),0) -> 1050 | AR5: =O5 -> 0 | AS5: =IF(AND(Param.SonstigEinmaligKonto1="Festgeld",$A5=Param.SonstigEinmaligJahr1),Param.SonstigEinmaligBetrag1,0) -> 0 | AT5: =IF(AND(Param.SonstigEinmaligKonto2="Festgeld",$A5=Param.SonstigEinmaligJahr2),Param.SonstigEinmaligBetrag2,0) -> 0 | AU5: =IF(AND(Param.SonstigEinmaligKonto3="Festgeld",$A5=Param.SonstigEinmaligJahr3),Param.SonstigEinmaligBetrag3,0) -> 0 | AV5: =IF(AND(Param.SonstigEinmaligKonto4="Festgeld",$A5=Param.SonstigEinmaligJahr4),Param.SonstigEinmaligBetrag4,0) -> 0 | AW5: =IF(AND(Param.SonstigEinmaligKonto5="Festgeld",$A5=Param.SonstigEinmaligJahr5),Param.SonstigEinmaligBetrag5,0) -> 0 | AX5: =IF(AND(Param.SonstigEinmaligKonto6="Festgeld",$A5=Param.SonstigEinmaligJahr6),Param.SonstigEinmaligBetrag6,0) -> 0 | AY5: =IF(AND(Param.SonstigEinmaligKonto7="Festgeld",$A5=Param.SonstigEinmaligJahr7),Param.SonstigEinmaligBetrag7,0) -> 0 | AZ5: =IF(AND(Param.SonstigEinmaligKonto8="Festgeld",$A5=Param.SonstigEinmaligJahr8),Param.SonstigEinmaligBetrag8,0) -> 0 | BA5: =IF(AND(Param.SonstigEinmaligKonto9="Festgeld",$A5=Param.SonstigEinmaligJahr9),Param.SonstigEinmaligBetrag9,0) -> 0 | BB5: =IF(AND(Param.SonstigEinmaligKonto10="Festgeld",$A5=Param.SonstigEinmaligJahr10),Param.SonstigEinmaligBetrag10,0) -> 0 | BC5: =IF(AND(A5>=Param.FireStartjahr,AP5>0),MIN(N5*R5,AP5),0) -> 0 | BD5: =Param.FestgeldZinssatz -> 0.02 | BE5: =(AP5+SUM(AQ5:BB5)-BC5)*BD5*(13-Param.StartmonatVermoegensstand)/12 -> 1178.9167 | BF5: =IF(BE5>Param.SparerPauschbetrag,Param.SparerPauschbetrag,BE5) -> 1000 | BG5: =BE5-BF5 -> 178.91667 | BH5: =BG5*Param.KapSt -> 47.189271 | BI5: =BE5-BH5 -> 1131.7274 | BJ5: =AP5+SUM(AQ5:BB5)-BC5+BI5 -> 102181.73 | BK5: =AL5+BJ5 -> 410925.37 | BL5: =BK5/(1+Param.Inflationsrate)^(A5-Param.Startjahr) -> 410925.37 | BM5: =IF(BK5<N5,A5,"") | BN5: =AH5+BC5 -> 0 | BO5: =SUM(AR5:BB5) -> 0 | BP5: =BN5+(-1*BO5) -> 0 | BQ5: =AI5+BH5 -> 47.189271 | BR5: =IF(BK5>0,BP5/BK5,0) -> 0
A6: =A5+1 -> 2027 | B6: =B5+(2-1) -> 31 | C6: =IF(A6<Param.FireStartjahr,0,Param.EntnahmeBetragStart*(1+Param.Inflationsrate)^(A6-Param.Startjahr)) -> 0 | D6: =IF(OR($A6<Param.SonstigRegelmJahrBeginn1,$A6>Param.SonstigRegelmJahrEnd1),0,Param.SonstigRegelmBetragJaehrl1*(1+Param.SonstigRegelmSteig1)^(A6-Param.SonstigRegelmJahrBeginn1)) -> 0 | E6: =IF(OR($A6<Param.SonstigRegelmJahrBeginn2,$A6>Param.SonstigRegelmJahrEnd2),0,Param.SonstigRegelmBetragJaehrl2*(1+Param.SonstigRegelmSteig2)^($A6-Param.SonstigRegelmJahrBeginn2)) -> 0 | F6: =IF(OR($A6<Param.SonstigRegelmJahrBeginn3,$A6>Param.SonstigRegelmJahrEnd3),0,Param.SonstigRegelmBetragJaehrl3*(1+Param.SonstigRegelmSteig3)^($A6-Param.SonstigRegelmJahrBeginn3)) -> 0 | G6: =IF(OR($A6<Param.SonstigRegelmJahrBeginn4,$A6>Param.SonstigRegelmJahrEnd4),0,Param.SonstigRegelmBetragJaehrl4*(1+Param.SonstigRegelmSteig4)^($A6-Param.SonstigRegelmJahrBeginn4)) -> 0 | H6: =IF(OR($A6<Param.SonstigRegelmJahrBeginn5,$A6>Param.SonstigRegelmJahrEnd5),0,Param.SonstigRegelmBetragJaehrl5*(1+Param.SonstigRegelmSteig5)^($A6-Param.SonstigRegelmJahrBeginn5)) -> 0 | I6: =IF(OR($A6<Param.SonstigRegelmJahrBeginn6,$A6>Param.SonstigRegelmJahrEnd6),0,Param.SonstigRegelmBetragJaehrl6*(1+Param.SonstigRegelmSteig6)^($A6-Param.SonstigRegelmJahrBeginn6)) -> 0 | J6: =IF(OR($A6<Param.SonstigRegelmJahrBeginn7,$A6>Param.SonstigRegelmJahrEnd7),0,Param.SonstigRegelmBetragJaehrl7*(1+Param.SonstigRegelmSteig7)^($A6-Param.SonstigRegelmJahrBeginn7)) -> 0 | K6: =IF(OR($A6<Param.SonstigRegelmJahrBeginn8,$A6>Param.SonstigRegelmJahrEnd8),0,Param.SonstigRegelmBetragJaehrl8*(1+Param.SonstigRegelmSteig8)^($A6-Param.SonstigRegelmJahrBeginn8)) -> 0 | L6: =IF(OR($A6<Param.SonstigRegelmJahrBeginn9,$A6>Param.SonstigRegelmJahrEnd9),0,Param.SonstigRegelmBetragJaehrl9*(1+Param.SonstigRegelmSteig9)^($A6-Param.SonstigRegelmJahrBeginn9)) -> 0 | M6: =IF(OR($A6<Param.SonstigRegelmJahrBeginn10,$A6>Param.SonstigRegelmJahrEnd10),0,Param.SonstigRegelmBetragJaehrl10*(1+Param.SonstigRegelmSteig10)^($A6-Param.SonstigRegelmJahrBeginn10)) -> 0 | N6: =MAX(0,C6-SUM(D6:M6)) -> 0 | O6: =IF(N6<=0,SUM(D6:M6)-C6,0) -> 0 | P6: =S6+AP6 -> 410925.37 | Q6: =IF(P6>0,S6/P6,0) -> 0.75133751 | R6: =IF(P6>0,AP6/P6,0) -> 0.24866249 | S6: =AL5 -> 308743.65 | T6: =AM5 -> 125243.65 | U6: =IF(A6<Param.FireStartjahr,Param.SparrateDepotMonatl*12*(1+Param.SparrateDynamikJaehrl)^($A6-Param.Startjahr),0) -> 6000 | V6: =IF(AND(Param.SonstigEinmaligKonto1="Depot",$A6=Param.SonstigEinmaligJahr1),Param.SonstigEinmaligBetrag1,0) -> 0 | W6: =IF(AND(Param.SonstigEinmaligKonto2="Depot",$A6=Param.SonstigEinmaligJahr2),Param.SonstigEinmaligBetrag2,0) -> 0 | X6: =IF(AND(Param.SonstigEinmaligKonto3="Depot",$A6=Param.SonstigEinmaligJahr3),Param.SonstigEinmaligBetrag3,0) -> 0 | Y6: =IF(AND(Param.SonstigEinmaligKonto4="Depot",$A6=Param.SonstigEinmaligJahr4),Param.SonstigEinmaligBetrag4,0) -> 0 | Z6: =IF(AND(Param.SonstigEinmaligKonto5="Depot",$A6=Param.SonstigEinmaligJahr5),Param.SonstigEinmaligBetrag5,0) -> 0 | AA6: =IF(AND(Param.SonstigEinmaligKonto6="Depot",$A6=Param.SonstigEinmaligJahr6),Param.SonstigEinmaligBetrag6,0) -> 0 | AB6: =IF(AND(Param.SonstigEinmaligKonto7="Depot",$A6=Param.SonstigEinmaligJahr7),Param.SonstigEinmaligBetrag7,0) -> 0 | AC6: =IF(AND(Param.SonstigEinmaligKonto8="Depot",$A6=Param.SonstigEinmaligJahr8),Param.SonstigEinmaligBetrag8,0) -> 0 | AD6: =IF(AND(Param.SonstigEinmaligKonto9="Depot",$A6=Param.SonstigEinmaligJahr9),Param.SonstigEinmaligBetrag9,0) -> 0 | AE6: =IF(AND(Param.SonstigEinmaligKonto10="Depot",$A6=Param.SonstigEinmaligJahr10),Param.SonstigEinmaligBetrag10,0) -> 0 | AF6: =Param.SparerPauschbetrag-BF6 -> 0 | AG6: =IF(AND(A6>=Param.FireStartjahr,S6>0),MIN(N6*Q6,S6),0) -> 0 | AH6: =IF(AG6<=0,0,IF(S6<=0,0,AG6/(1-MAX(0,((T6/S6)*(1-Param.Teilfreistellung)-MIN(AF6,AG6)/AG6)*Param.KapSt)))) -> 0 | AI6: =AH6-AG6 -> 0 | AJ6: =T6-AH6*(T6/S6) -> 125243.65 | AK6: =S6-AH6 -> 308743.65 | AL6: =FV(AO6,12,-(U6/12),-AK6,0) -> 324088.02 | AM6: =AJ6+AL6-AK6-U6 -> 134588.02 | AN6: =AM6/AL6 -> 0.4152823 | AO6: =(1+IF(AND(A6>=Param.DepotRenditeSpezBeginn1,A6<=Param.DepotRenditeSpezEnde1),Param.DepotRenditeSpezProz1,IF(AND(A6>=Param.DepotRenditeSpezBeginn2,A6<=Param.DepotRenditeSpezEnde2),Param.DepotRenditeSpezProz2,IF(AND(A6>=Param.DepotRenditeSpezBeginn3,A6<=Param.DepotRenditeSpezEnde3),Param.DepotRenditeSpezProz3,IF(AND(A6>=Param.DepotRenditeSpezBeginn4,A6<=Param.DepotRenditeSpezEnde4),Param.DepotRenditeSpezProz4,IF(AND(A6>=Param.DepotRenditeSpezBeginn5,A6<=Param.DepotRenditeSpezEnde5),Param.DepotRenditeSpezProz5,Param.DepotRenditeDefault))))))^(1/12)-1 -> 0.0024662698 | AP6: =BJ5 -> 102181.73 | AQ6: =IF(A6<Param.FireStartjahr,Param.SparrateFestgeldMonatl*12*(1+Param.SparrateDynamikJaehrl)^($A6-Param.Startjahr),0) -> 1800 | AR6: =O6 -> 0 | AS6: =IF(AND(Param.SonstigEinmaligKonto1="Festgeld",$A6=Param.SonstigEinmaligJahr1),Param.SonstigEinmaligBetrag1,0) -> 0 | AT6: =IF(AND(Param.SonstigEinmaligKonto2="Festgeld",$A6=Param.SonstigEinmaligJahr2),Param.SonstigEinmaligBetrag2,0) -> 0 | AU6: =IF(AND(Param.SonstigEinmaligKonto3="Festgeld",$A6=Param.SonstigEinmaligJahr3),Param.SonstigEinmaligBetrag3,0) -> 0 | AV6: =IF(AND(Param.SonstigEinmaligKonto4="Festgeld",$A6=Param.SonstigEinmaligJahr4),Param.SonstigEinmaligBetrag4,0) -> 0 | AW6: =IF(AND(Param.SonstigEinmaligKonto5="Festgeld",$A6=Param.SonstigEinmaligJahr5),Param.SonstigEinmaligBetrag5,0) -> 0 | AX6: =IF(AND(Param.SonstigEinmaligKonto6="Festgeld",$A6=Param.SonstigEinmaligJahr6),Param.SonstigEinmaligBetrag6,0) -> 0 | AY6: =IF(AND(Param.SonstigEinmaligKonto7="Festgeld",$A6=Param.SonstigEinmaligJahr7),Param.SonstigEinmaligBetrag7,0) -> 0 | AZ6: =IF(AND(Param.SonstigEinmaligKonto8="Festgeld",$A6=Param.SonstigEinmaligJahr8),Param.SonstigEinmaligBetrag8,0) -> 0 | BA6: =IF(AND(Param.SonstigEinmaligKonto9="Festgeld",$A6=Param.SonstigEinmaligJahr9),Param.SonstigEinmaligBetrag9,0) -> 0 | BB6: =IF(AND(Param.SonstigEinmaligKonto10="Festgeld",$A6=Param.SonstigEinmaligJahr10),Param.SonstigEinmaligBetrag10,0) -> 0 | BC6: =IF(AND(A6>=Param.FireStartjahr,AP6>0),MIN(N6*R6,AP6),0) -> 0 | BD6: =Param.FestgeldZinssatz -> 0.02 | BE6: =(AP6+SUM(AQ6:BB6)-BC6)*BD6 -> 2079.6345 | BF6: =IF(BE6>Param.SparerPauschbetrag,Param.SparerPauschbetrag,BE6) -> 1000 | BG6: =BE6-BF6 -> 1079.6345 | BH6: =BG6*Param.KapSt -> 284.75361 | BI6: =BE6-BH6 -> 1794.8809 | BJ6: =AP6+SUM(AQ6:BB6)-BC6+BI6 -> 105776.61 | BK6: =AL6+BJ6 -> 429864.62 | BL6: =BK6/(1+Param.Inflationsrate)^(A6-Param.Startjahr) -> 419380.12 | BM6: =IF(BK6<N6,A6,"") | BN6: =AH6+BC6 -> 0 | BO6: =SUM(AR6:BB6) -> 0 | BP6: =BN6+(-1*BO6) -> 0 | BQ6: =AI6+BH6 -> 284.75361 | BR6: =IF(BK6>0,BP6/BK6,0) -> 0
A7: =A6+1 -> 2028 | B7: =B5+(3-1) -> 32 | C7: =IF(A7<Param.FireStartjahr,0,Param.EntnahmeBetragStart*(1+Param.Inflationsrate)^(A7-Param.Startjahr)) -> 0 | D7: =IF(OR($A7<Param.SonstigRegelmJahrBeginn1,$A7>Param.SonstigRegelmJahrEnd1),0,Param.SonstigRegelmBetragJaehrl1*(1+Param.SonstigRegelmSteig1)^(A7-Param.SonstigRegelmJahrBeginn1)) -> 0 | E7: =IF(OR($A7<Param.SonstigRegelmJahrBeginn2,$A7>Param.SonstigRegelmJahrEnd2),0,Param.SonstigRegelmBetragJaehrl2*(1+Param.SonstigRegelmSteig2)^($A7-Param.SonstigRegelmJahrBeginn2)) -> 0 | F7: =IF(OR($A7<Param.SonstigRegelmJahrBeginn3,$A7>Param.SonstigRegelmJahrEnd3),0,Param.SonstigRegelmBetragJaehrl3*(1+Param.SonstigRegelmSteig3)^($A7-Param.SonstigRegelmJahrBeginn3)) -> 3600 | G7: =IF(OR($A7<Param.SonstigRegelmJahrBeginn4,$A7>Param.SonstigRegelmJahrEnd4),0,Param.SonstigRegelmBetragJaehrl4*(1+Param.SonstigRegelmSteig4)^($A7-Param.SonstigRegelmJahrBeginn4)) -> 0 | H7: =IF(OR($A7<Param.SonstigRegelmJahrBeginn5,$A7>Param.SonstigRegelmJahrEnd5),0,Param.SonstigRegelmBetragJaehrl5*(1+Param.SonstigRegelmSteig5)^($A7-Param.SonstigRegelmJahrBeginn5)) -> 0 | I7: =IF(OR($A7<Param.SonstigRegelmJahrBeginn6,$A7>Param.SonstigRegelmJahrEnd6),0,Param.SonstigRegelmBetragJaehrl6*(1+Param.SonstigRegelmSteig6)^($A7-Param.SonstigRegelmJahrBeginn6)) -> 0 | J7: =IF(OR($A7<Param.SonstigRegelmJahrBeginn7,$A7>Param.SonstigRegelmJahrEnd7),0,Param.SonstigRegelmBetragJaehrl7*(1+Param.SonstigRegelmSteig7)^($A7-Param.SonstigRegelmJahrBeginn7)) -> 0 | K7: =IF(OR($A7<Param.SonstigRegelmJahrBeginn8,$A7>Param.SonstigRegelmJahrEnd8),0,Param.SonstigRegelmBetragJaehrl8*(1+Param.SonstigRegelmSteig8)^($A7-Param.SonstigRegelmJahrBeginn8)) -> 0 | L7: =IF(OR($A7<Param.SonstigRegelmJahrBeginn9,$A7>Param.SonstigRegelmJahrEnd9),0,Param.SonstigRegelmBetragJaehrl9*(1+Param.SonstigRegelmSteig9)^($A7-Param.SonstigRegelmJahrBeginn9)) -> 0 | M7: =IF(OR($A7<Param.SonstigRegelmJahrBeginn10,$A7>Param.SonstigRegelmJahrEnd10),0,Param.SonstigRegelmBetragJaehrl10*(1+Param.SonstigRegelmSteig10)^($A7-Param.SonstigRegelmJahrBeginn10)) -> 0 | N7: =MAX(0,C7-SUM(D7:M7)) -> 0 | O7: =IF(N7<=0,SUM(D7:M7)-C7,0) -> 3600 | P7: =S7+AP7 -> 429864.62 | Q7: =IF(P7>0,S7/P7,0) -> 0.75393042 | R7: =IF(P7>0,AP7/P7,0) -> 0.24606958 | S7: =AL6 -> 324088.02 | T7: =AM6 -> 134588.02 | U7: =IF(A7<Param.FireStartjahr,Param.SparrateDepotMonatl*12*(1+Param.SparrateDynamikJaehrl)^($A7-Param.Startjahr),0) -> 6000 | V7: =IF(AND(Param.SonstigEinmaligKonto1="Depot",$A7=Param.SonstigEinmaligJahr1),Param.SonstigEinmaligBetrag1,0) -> 0 | W7: =IF(AND(Param.SonstigEinmaligKonto2="Depot",$A7=Param.SonstigEinmaligJahr2),Param.SonstigEinmaligBetrag2,0) -> 0 | X7: =IF(AND(Param.SonstigEinmaligKonto3="Depot",$A7=Param.SonstigEinmaligJahr3),Param.SonstigEinmaligBetrag3,0) -> 0 | Y7: =IF(AND(Param.SonstigEinmaligKonto4="Depot",$A7=Param.SonstigEinmaligJahr4),Param.SonstigEinmaligBetrag4,0) -> 0 | Z7: =IF(AND(Param.SonstigEinmaligKonto5="Depot",$A7=Param.SonstigEinmaligJahr5),Param.SonstigEinmaligBetrag5,0) -> 0 | AA7: =IF(AND(Param.SonstigEinmaligKonto6="Depot",$A7=Param.SonstigEinmaligJahr6),Param.SonstigEinmaligBetrag6,0) -> 0 | AB7: =IF(AND(Param.SonstigEinmaligKonto7="Depot",$A7=Param.SonstigEinmaligJahr7),Param.SonstigEinmaligBetrag7,0) -> 0 | AC7: =IF(AND(Param.SonstigEinmaligKonto8="Depot",$A7=Param.SonstigEinmaligJahr8),Param.SonstigEinmaligBetrag8,0) -> 0 | AD7: =IF(AND(Param.SonstigEinmaligKonto9="Depot",$A7=Param.SonstigEinmaligJahr9),Param.SonstigEinmaligBetrag9,0) -> 0 | AE7: =IF(AND(Param.SonstigEinmaligKonto10="Depot",$A7=Param.SonstigEinmaligJahr10),Param.SonstigEinmaligBetrag10,0) -> 0 | AF7: =Param.SparerPauschbetrag-BF7 -> 0 | AG7: =IF(AND(A7>=Param.FireStartjahr,S7>0),MIN(N7*Q7,S7),0) -> 0 | AH7: =IF(AG7<=0,0,IF(S7<=0,0,AG7/(1-MAX(0,((T7/S7)*(1-Param.Teilfreistellung)-MIN(AF7,AG7)/AG7)*Param.KapSt)))) -> 0 | AI7: =AH7-AG7 -> 0 | AJ7: =T7-AH7*(T7/S7) -> 134588.02 | AK7: =S7-AH7 -> 324088.02 | AL7: =FV(AO7,12,-(U7/12),-AK7,0) -> 339892.72 | AM7: =AJ7+AL7-AK7-U7 -> 144392.72 | AN7: =AM7/AL7 -> 0.42481851 | AO7: =(1+IF(AND(A7>=Param.DepotRenditeSpezBeginn1,A7<=Param.DepotRenditeSpezEnde1),Param.DepotRenditeSpezProz1,IF(AND(A7>=Param.DepotRenditeSpezBeginn2,A7<=Param.DepotRenditeSpezEnde2),Param.DepotRenditeSpezProz2,IF(AND(A7>=Param.DepotRenditeSpezBeginn3,A7<=Param.DepotRenditeSpezEnde3),Param.DepotRenditeSpezProz3,IF(AND(A7>=Param.DepotRenditeSpezBeginn4,A7<=Param.DepotRenditeSpezEnde4),Param.DepotRenditeSpezProz4,IF(AND(A7>=Param.DepotRenditeSpezBeginn5,A7<=Param.DepotRenditeSpezEnde5),Param.DepotRenditeSpezProz5,Param.DepotRenditeDefault))))))^(1/12)-1 -> 0.0024662698 | AP7: =BJ6 -> 105776.61 | AQ7: =IF(A7<Param.FireStartjahr,Param.SparrateFestgeldMonatl*12*(1+Param.SparrateDynamikJaehrl)^($A7-Param.Startjahr),0) -> 1800 | AR7: =O7 -> 3600 | AS7: =IF(AND(Param.SonstigEinmaligKonto1="Festgeld",$A7=Param.SonstigEinmaligJahr1),Param.SonstigEinmaligBetrag1,0) -> 0 | AT7: =IF(AND(Param.SonstigEinmaligKonto2="Festgeld",$A7=Param.SonstigEinmaligJahr2),Param.SonstigEinmaligBetrag2,0) -> 0 | AU7: =IF(AND(Param.SonstigEinmaligKonto3="Festgeld",$A7=Param.SonstigEinmaligJahr3),Param.SonstigEinmaligBetrag3,0) -> 0 | AV7: =IF(AND(Param.SonstigEinmaligKonto4="Festgeld",$A7=Param.SonstigEinmaligJahr4),Param.SonstigEinmaligBetrag4,0) -> 0 | AW7: =IF(AND(Param.SonstigEinmaligKonto5="Festgeld",$A7=Param.SonstigEinmaligJahr5),Param.SonstigEinmaligBetrag5,0) -> 0 | AX7: =IF(AND(Param.SonstigEinmaligKonto6="Festgeld",$A7=Param.SonstigEinmaligJahr6),Param.SonstigEinmaligBetrag6,0) -> 0 | AY7: =IF(AND(Param.SonstigEinmaligKonto7="Festgeld",$A7=Param.SonstigEinmaligJahr7),Param.SonstigEinmaligBetrag7,0) -> 0 | AZ7: =IF(AND(Param.SonstigEinmaligKonto8="Festgeld",$A7=Param.SonstigEinmaligJahr8),Param.SonstigEinmaligBetrag8,0) -> 0 | BA7: =IF(AND(Param.SonstigEinmaligKonto9="Festgeld",$A7=Param.SonstigEinmaligJahr9),Param.SonstigEinmaligBetrag9,0) -> 0 | BB7: =IF(AND(Param.SonstigEinmaligKonto10="Festgeld",$A7=Param.SonstigEinmaligJahr10),Param.SonstigEinmaligBetrag10,0) -> 0 | BC7: =IF(AND(A7>=Param.FireStartjahr,AP7>0),MIN(N7*R7,AP7),0) -> 0 | BD7: =Param.FestgeldZinssatz -> 0.02 | BE7: =(AP7+SUM(AQ7:BB7)-BC7)*BD7 -> 2223.5322 | BF7: =IF(BE7>Param.SparerPauschbetrag,Param.SparerPauschbetrag,BE7) -> 1000 | BG7: =BE7-BF7 -> 1223.5322 | BH7: =BG7*Param.KapSt -> 322.70661 | BI7: =BE7-BH7 -> 1900.8256 | BJ7: =AP7+SUM(AQ7:BB7)-BC7+BI7 -> 113077.43 | BK7: =AL7+BJ7 -> 452970.15 | BL7: =BK7/(1+Param.Inflationsrate)^(A7-Param.Startjahr) -> 431143.51 | BM7: =IF(BK7<N7,A7,"") | BN7: =AH7+BC7 -> 0 | BO7: =SUM(AR7:BB7) -> 3600 | BP7: =BN7+(-1*BO7) -> -3600 | BQ7: =AI7+BH7 -> 322.70661 | BR7: =IF(BK7>0,BP7/BK7,0) -> -0.0079475436
A8: =A7+1 -> 2029 | B8: =B5+(4-1) -> 33 | C8: =IF(A8<Param.FireStartjahr,0,Param.EntnahmeBetragStart*(1+Param.Inflationsrate)^(A8-Param.Startjahr)) -> 0 | D8: =IF(OR($A8<Param.SonstigRegelmJahrBeginn1,$A8>Param.SonstigRegelmJahrEnd1),0,Param.SonstigRegelmBetragJaehrl1*(1+Param.SonstigRegelmSteig1)^(A8-Param.SonstigRegelmJahrBeginn1)) -> 0 | E8: =IF(OR($A8<Param.SonstigRegelmJahrBeginn2,$A8>Param.SonstigRegelmJahrEnd2),0,Param.SonstigRegelmBetragJaehrl2*(1+Param.SonstigRegelmSteig2)^($A8-Param.SonstigRegelmJahrBeginn2)) -> 0 | F8: =IF(OR($A8<Param.SonstigRegelmJahrBeginn3,$A8>Param.SonstigRegelmJahrEnd3),0,Param.SonstigRegelmBetragJaehrl3*(1+Param.SonstigRegelmSteig3)^($A8-Param.SonstigRegelmJahrBeginn3)) -> 3636 | G8: =IF(OR($A8<Param.SonstigRegelmJahrBeginn4,$A8>Param.SonstigRegelmJahrEnd4),0,Param.SonstigRegelmBetragJaehrl4*(1+Param.SonstigRegelmSteig4)^($A8-Param.SonstigRegelmJahrBeginn4)) -> 0 | H8: =IF(OR($A8<Param.SonstigRegelmJahrBeginn5,$A8>Param.SonstigRegelmJahrEnd5),0,Param.SonstigRegelmBetragJaehrl5*(1+Param.SonstigRegelmSteig5)^($A8-Param.SonstigRegelmJahrBeginn5)) -> 0 | I8: =IF(OR($A8<Param.SonstigRegelmJahrBeginn6,$A8>Param.SonstigRegelmJahrEnd6),0,Param.SonstigRegelmBetragJaehrl6*(1+Param.SonstigRegelmSteig6)^($A8-Param.SonstigRegelmJahrBeginn6)) -> 0 | J8: =IF(OR($A8<Param.SonstigRegelmJahrBeginn7,$A8>Param.SonstigRegelmJahrEnd7),0,Param.SonstigRegelmBetragJaehrl7*(1+Param.SonstigRegelmSteig7)^($A8-Param.SonstigRegelmJahrBeginn7)) -> 0 | K8: =IF(OR($A8<Param.SonstigRegelmJahrBeginn8,$A8>Param.SonstigRegelmJahrEnd8),0,Param.SonstigRegelmBetragJaehrl8*(1+Param.SonstigRegelmSteig8)^($A8-Param.SonstigRegelmJahrBeginn8)) -> 0 | L8: =IF(OR($A8<Param.SonstigRegelmJahrBeginn9,$A8>Param.SonstigRegelmJahrEnd9),0,Param.SonstigRegelmBetragJaehrl9*(1+Param.SonstigRegelmSteig9)^($A8-Param.SonstigRegelmJahrBeginn9)) -> 0 | M8: =IF(OR($A8<Param.SonstigRegelmJahrBeginn10,$A8>Param.SonstigRegelmJahrEnd10),0,Param.SonstigRegelmBetragJaehrl10*(1+Param.SonstigRegelmSteig10)^($A8-Param.SonstigRegelmJahrBeginn10)) -> 0 | N8: =MAX(0,C8-SUM(D8:M8)) -> 0 | O8: =IF(N8<=0,SUM(D8:M8)-C8,0) -> 3636 | P8: =S8+AP8 -> 452970.15 | Q8: =IF(P8>0,S8/P8,0) -> 0.75036449 | R8: =IF(P8>0,AP8/P8,0) -> 0.24963551 | S8: =AL7 -> 339892.72 | T8: =AM7 -> 144392.72 | U8: =IF(A8<Param.FireStartjahr,Param.SparrateDepotMonatl*12*(1+Param.SparrateDynamikJaehrl)^($A8-Param.Startjahr),0) -> 6000 | V8: =IF(AND(Param.SonstigEinmaligKonto1="Depot",$A8=Param.SonstigEinmaligJahr1),Param.SonstigEinmaligBetrag1,0) -> 0 | W8: =IF(AND(Param.SonstigEinmaligKonto2="Depot",$A8=Param.SonstigEinmaligJahr2),Param.SonstigEinmaligBetrag2,0) -> 0 | X8: =IF(AND(Param.SonstigEinmaligKonto3="Depot",$A8=Param.SonstigEinmaligJahr3),Param.SonstigEinmaligBetrag3,0) -> 0 | Y8: =IF(AND(Param.SonstigEinmaligKonto4="Depot",$A8=Param.SonstigEinmaligJahr4),Param.SonstigEinmaligBetrag4,0) -> 0 | Z8: =IF(AND(Param.SonstigEinmaligKonto5="Depot",$A8=Param.SonstigEinmaligJahr5),Param.SonstigEinmaligBetrag5,0) -> 0 | AA8: =IF(AND(Param.SonstigEinmaligKonto6="Depot",$A8=Param.SonstigEinmaligJahr6),Param.SonstigEinmaligBetrag6,0) -> 0 | AB8: =IF(AND(Param.SonstigEinmaligKonto7="Depot",$A8=Param.SonstigEinmaligJahr7),Param.SonstigEinmaligBetrag7,0) -> 0 | AC8: =IF(AND(Param.SonstigEinmaligKonto8="Depot",$A8=Param.SonstigEinmaligJahr8),Param.SonstigEinmaligBetrag8,0) -> 0 | AD8: =IF(AND(Param.SonstigEinmaligKonto9="Depot",$A8=Param.SonstigEinmaligJahr9),Param.SonstigEinmaligBetrag9,0) -> 0 | AE8: =IF(AND(Param.SonstigEinmaligKonto10="Depot",$A8=Param.SonstigEinmaligJahr10),Param.SonstigEinmaligBetrag10,0) -> 0 | AF8: =Param.SparerPauschbetrag-BF8 -> 0 | AG8: =IF(AND(A8>=Param.FireStartjahr,S8>0),MIN(N8*Q8,S8),0) -> 0 | AH8: =IF(AG8<=0,0,IF(S8<=0,0,AG8/(1-MAX(0,((T8/S8)*(1-Param.Teilfreistellung)-MIN(AF8,AG8)/AG8)*Param.KapSt)))) -> 0 | AI8: =AH8-AG8 -> 0 | AJ8: =T8-AH8*(T8/S8) -> 144392.72 | AK8: =S8-AH8 -> 339892.72 | AL8: =FV(AO8,12,-(U8/12),-AK8,0) -> 366449.54 | AM8: =AJ8+AL8-AK8-U8 -> 164949.54 | AN8: =AM8/AL8 -> 0.45012894 | AO8: =(1+IF(AND(A8>=Param.DepotRenditeSpezBeginn1,A8<=Param.DepotRenditeSpezEnde1),Param.DepotRenditeSpezProz1,IF(AND(A8>=Param.DepotRenditeSpezBeginn2,A8<=Param.DepotRenditeSpezEnde2),Param.DepotRenditeSpezProz2,IF(AND(A8>=Param.DepotRenditeSpezBeginn3,A8<=Param.DepotRenditeSpezEnde3),Param.DepotRenditeSpezProz3,IF(AND(A8>=Param.DepotRenditeSpezBeginn4,A8<=Param.DepotRenditeSpezEnde4),Param.DepotRenditeSpezProz4,IF(AND(A8>=Param.DepotRenditeSpezBeginn5,A8<=Param.DepotRenditeSpezEnde5),Param.DepotRenditeSpezProz5,Param.DepotRenditeDefault))))))^(1/12)-1 -> 0.0048675506 | AP8: =BJ7 -> 113077.43 | AQ8: =IF(A8<Param.FireStartjahr,Param.SparrateFestgeldMonatl*12*(1+Param.SparrateDynamikJaehrl)^($A8-Param.Startjahr),0) -> 1800 | AR8: =O8 -> 3636 | AS8: =IF(AND(Param.SonstigEinmaligKonto1="Festgeld",$A8=Param.SonstigEinmaligJahr1),Param.SonstigEinmaligBetrag1,0) -> 0 | AT8: =IF(AND(Param.SonstigEinmaligKonto2="Festgeld",$A8=Param.SonstigEinmaligJahr2),Param.SonstigEinmaligBetrag2,0) -> 0 | AU8: =IF(AND(Param.SonstigEinmaligKonto3="Festgeld",$A8=Param.SonstigEinmaligJahr3),Param.SonstigEinmaligBetrag3,0) -> 0 | AV8: =IF(AND(Param.SonstigEinmaligKonto4="Festgeld",$A8=Param.SonstigEinmaligJahr4),Param.SonstigEinmaligBetrag4,0) -> 0 | AW8: =IF(AND(Param.SonstigEinmaligKonto5="Festgeld",$A8=Param.SonstigEinmaligJahr5),Param.SonstigEinmaligBetrag5,0) -> 0 | AX8: =IF(AND(Param.SonstigEinmaligKonto6="Festgeld",$A8=Param.SonstigEinmaligJahr6),Param.SonstigEinmaligBetrag6,0) -> 0 | AY8: =IF(AND(Param.SonstigEinmaligKonto7="Festgeld",$A8=Param.SonstigEinmaligJahr7),Param.SonstigEinmaligBetrag7,0) -> 0 | AZ8: =IF(AND(Param.SonstigEinmaligKonto8="Festgeld",$A8=Param.SonstigEinmaligJahr8),Param.SonstigEinmaligBetrag8,0) -> 0 | BA8: =IF(AND(Param.SonstigEinmaligKonto9="Festgeld",$A8=Param.SonstigEinmaligJahr9),Param.SonstigEinmaligBetrag9,0) -> 0 | BB8: =IF(AND(Param.SonstigEinmaligKonto10="Festgeld",$A8=Param.SonstigEinmaligJahr10),Param.SonstigEinmaligBetrag10,0) -> 0 | BC8: =IF(AND(A8>=Param.FireStartjahr,AP8>0),MIN(N8*R8,AP8),0) -> 0 | BD8: =Param.FestgeldZinssatz -> 0.02 | BE8: =(AP8+SUM(AQ8:BB8)-BC8)*BD8 -> 2370.2687 | BF8: =IF(BE8>Param.SparerPauschbetrag,Param.SparerPauschbetrag,BE8) -> 1000 | BG8: =BE8-BF8 -> 1370.2687 | BH8: =BG8*Param.KapSt -> 361.40836 | BI8: =BE8-BH8 -> 2008.8603 | BJ8: =AP8+SUM(AQ8:BB8)-BC8+BI8 -> 120522.29 | BK8: =AL8+BJ8 -> 486971.84 | BL8: =BK8/(1+Param.Inflationsrate)^(A8-Param.Startjahr) -> 452201.76 | BM8: =IF(BK8<N8,A8,"") | BN8: =AH8+BC8 -> 0 | BO8: =SUM(AR8:BB8) -> 3636 | BP8: =BN8+(-1*BO8) -> -3636 | BQ8: =AI8+BH8 -> 361.40836 | BR8: =IF(BK8>0,BP8/BK8,0) -> -0.0074665509
A9: =A8+1 -> 2030 | B9: =B5+(5-1) -> 34 | C9: =IF(A9<Param.FireStartjahr,0,Param.EntnahmeBetragStart*(1+Param.Inflationsrate)^(A9-Param.Startjahr)) -> 0 | D9: =IF(OR($A9<Param.SonstigRegelmJahrBeginn1,$A9>Param.SonstigRegelmJahrEnd1),0,Param.SonstigRegelmBetragJaehrl1*(1+Param.SonstigRegelmSteig1)^(A9-Param.SonstigRegelmJahrBeginn1)) -> 0 | E9: =IF(OR($A9<Param.SonstigRegelmJahrBeginn2,$A9>Param.SonstigRegelmJahrEnd2),0,Param.SonstigRegelmBetragJaehrl2*(1+Param.SonstigRegelmSteig2)^($A9-Param.SonstigRegelmJahrBeginn2)) -> 0 | F9: =IF(OR($A9<Param.SonstigRegelmJahrBeginn3,$A9>Param.SonstigRegelmJahrEnd3),0,Param.SonstigRegelmBetragJaehrl3*(1+Param.SonstigRegelmSteig3)^($A9-Param.SonstigRegelmJahrBeginn3)) -> 3672.36 | G9: =IF(OR($A9<Param.SonstigRegelmJahrBeginn4,$A9>Param.SonstigRegelmJahrEnd4),0,Param.SonstigRegelmBetragJaehrl4*(1+Param.SonstigRegelmSteig4)^($A9-Param.SonstigRegelmJahrBeginn4)) -> 0 | H9: =IF(OR($A9<Param.SonstigRegelmJahrBeginn5,$A9>Param.SonstigRegelmJahrEnd5),0,Param.SonstigRegelmBetragJaehrl5*(1+Param.SonstigRegelmSteig5)^($A9-Param.SonstigRegelmJahrBeginn5)) -> 0 | I9: =IF(OR($A9<Param.SonstigRegelmJahrBeginn6,$A9>Param.SonstigRegelmJahrEnd6),0,Param.SonstigRegelmBetragJaehrl6*(1+Param.SonstigRegelmSteig6)^($A9-Param.SonstigRegelmJahrBeginn6)) -> 0 | J9: =IF(OR($A9<Param.SonstigRegelmJahrBeginn7,$A9>Param.SonstigRegelmJahrEnd7),0,Param.SonstigRegelmBetragJaehrl7*(1+Param.SonstigRegelmSteig7)^($A9-Param.SonstigRegelmJahrBeginn7)) -> 0 | K9: =IF(OR($A9<Param.SonstigRegelmJahrBeginn8,$A9>Param.SonstigRegelmJahrEnd8),0,Param.SonstigRegelmBetragJaehrl8*(1+Param.SonstigRegelmSteig8)^($A9-Param.SonstigRegelmJahrBeginn8)) -> 0 | L9: =IF(OR($A9<Param.SonstigRegelmJahrBeginn9,$A9>Param.SonstigRegelmJahrEnd9),0,Param.SonstigRegelmBetragJaehrl9*(1+Param.SonstigRegelmSteig9)^($A9-Param.SonstigRegelmJahrBeginn9)) -> 0 | M9: =IF(OR($A9<Param.SonstigRegelmJahrBeginn10,$A9>Param.SonstigRegelmJahrEnd10),0,Param.SonstigRegelmBetragJaehrl10*(1+Param.SonstigRegelmSteig10)^($A9-Param.SonstigRegelmJahrBeginn10)) -> 0 | N9: =MAX(0,C9-SUM(D9:M9)) -> 0 | O9: =IF(N9<=0,SUM(D9:M9)-C9,0) -> 3672.36 | P9: =S9+AP9 -> 486971.84 | Q9: =IF(P9>0,S9/P9,0) -> 0.75250664 | R9: =IF(P9>0,AP9/P9,0) -> 0.24749336 | S9: =AL8 -> 366449.54 | T9: =AM8 -> 164949.54 | U9: =IF(A9<Param.FireStartjahr,Param.SparrateDepotMonatl*12*(1+Param.SparrateDynamikJaehrl)^($A9-Param.Startjahr),0) -> 6000 | V9: =IF(AND(Param.SonstigEinmaligKonto1="Depot",$A9=Param.SonstigEinmaligJahr1),Param.SonstigEinmaligBetrag1,0) -> 0 | W9: =IF(AND(Param.SonstigEinmaligKonto2="Depot",$A9=Param.SonstigEinmaligJahr2),Param.SonstigEinmaligBetrag2,0) -> 0 | X9: =IF(AND(Param.SonstigEinmaligKonto3="Depot",$A9=Param.SonstigEinmaligJahr3),Param.SonstigEinmaligBetrag3,0) -> 0 | Y9: =IF(AND(Param.SonstigEinmaligKonto4="Depot",$A9=Param.SonstigEinmaligJahr4),Param.SonstigEinmaligBetrag4,0) -> 0 | Z9: =IF(AND(Param.SonstigEinmaligKonto5="Depot",$A9=Param.SonstigEinmaligJahr5),Param.SonstigEinmaligBetrag5,0) -> 0 | AA9: =IF(AND(Param.SonstigEinmaligKonto6="Depot",$A9=Param.SonstigEinmaligJahr6),Param.SonstigEinmaligBetrag6,0) -> 0 | AB9: =IF(AND(Param.SonstigEinmaligKonto7="Depot",$A9=Param.SonstigEinmaligJahr7),Param.SonstigEinmaligBetrag7,0) -> 0 | AC9: =IF(AND(Param.SonstigEinmaligKonto8="Depot",$A9=Param.SonstigEinmaligJahr8),Param.SonstigEinmaligBetrag8,0) -> 0 | AD9: =IF(AND(Param.SonstigEinmaligKonto9="Depot",$A9=Param.SonstigEinmaligJahr9),Param.SonstigEinmaligBetrag9,0) -> 0 | AE9: =IF(AND(Param.SonstigEinmaligKonto10="Depot",$A9=Param.SonstigEinmaligJahr10),Param.SonstigEinmaligBetrag10,0) -> 0 | AF9: =Param.SparerPauschbetrag-BF9 -> 0 | AG9: =IF(AND(A9>=Param.FireStartjahr,S9>0),MIN(N9*Q9,S9),0) -> 0 | AH9: =IF(AG9<=0,0,IF(S9<=0,0,AG9/(1-MAX(0,((T9/S9)*(1-Param.Teilfreistellung)-MIN(AF9,AG9)/AG9)*Param.KapSt)))) -> 0 | AI9: =AH9-AG9 -> 0 | AJ9: =T9-AH9*(T9/S9) -> 164949.54 | AK9: =S9-AH9 -> 366449.54 | AL9: =FV(AO9,12,-(U9/12),-AK9,0) -> 387216.75 | AM9: =AJ9+AL9-AK9-U9 -> 179716.75 | AN9: =AM9/AL9 -> 0.46412442 | AO9: =(1+IF(AND(A9>=Param.DepotRenditeSpezBeginn1,A9<=Param.DepotRenditeSpezEnde1),Param.DepotRenditeSpezProz1,IF(AND(A9>=Param.DepotRenditeSpezBeginn2,A9<=Param.DepotRenditeSpezEnde2),Param.DepotRenditeSpezProz2,IF(AND(A9>=Param.DepotRenditeSpezBeginn3,A9<=Param.DepotRenditeSpezEnde3),Param.DepotRenditeSpezProz3,IF(AND(A9>=Param.DepotRenditeSpezBeginn4,A9<=Param.DepotRenditeSpezEnde4),Param.DepotRenditeSpezProz4,IF(AND(A9>=Param.DepotRenditeSpezBeginn5,A9<=Param.DepotRenditeSpezEnde5),Param.DepotRenditeSpezProz5,Param.DepotRenditeDefault))))))^(1/12)-1 -> 0.0032737398 | AP9: =BJ8 -> 120522.29 | AQ9: =IF(A9<Param.FireStartjahr,Param.SparrateFestgeldMonatl*12*(1+Param.SparrateDynamikJaehrl)^($A9-Param.Startjahr),0) -> 1800 | AR9: =O9 -> 3672.36 | AS9: =IF(AND(Param.SonstigEinmaligKonto1="Festgeld",$A9=Param.SonstigEinmaligJahr1),Param.SonstigEinmaligBetrag1,0) -> 0 | AT9: =IF(AND(Param.SonstigEinmaligKonto2="Festgeld",$A9=Param.SonstigEinmaligJahr2),Param.SonstigEinmaligBetrag2,0) -> -25000 | AU9: =IF(AND(Param.SonstigEinmaligKonto3="Festgeld",$A9=Param.SonstigEinmaligJahr3),Param.SonstigEinmaligBetrag3,0) -> 0 | AV9: =IF(AND(Param.SonstigEinmaligKonto4="Festgeld",$A9=Param.SonstigEinmaligJahr4),Param.SonstigEinmaligBetrag4,0) -> 0 | AW9: =IF(AND(Param.SonstigEinmaligKonto5="Festgeld",$A9=Param.SonstigEinmaligJahr5),Param.SonstigEinmaligBetrag5,0) -> 0 | AX9: =IF(AND(Param.SonstigEinmaligKonto6="Festgeld",$A9=Param.SonstigEinmaligJahr6),Param.SonstigEinmaligBetrag6,0) -> 0 | AY9: =IF(AND(Param.SonstigEinmaligKonto7="Festgeld",$A9=Param.SonstigEinmaligJahr7),Param.SonstigEinmaligBetrag7,0) -> 0 | AZ9: =IF(AND(Param.SonstigEinmaligKonto8="Festgeld",$A9=Param.SonstigEinmaligJahr8),Param.SonstigEinmaligBetrag8,0) -> 0 | BA9: =IF(AND(Param.SonstigEinmaligKonto9="Festgeld",$A9=Param.SonstigEinmaligJahr9),Param.SonstigEinmaligBetrag9,0) -> 0 | BB9: =IF(AND(Param.SonstigEinmaligKonto10="Festgeld",$A9=Param.SonstigEinmaligJahr10),Param.SonstigEinmaligBetrag10,0) -> 0 | BC9: =IF(AND(A9>=Param.FireStartjahr,AP9>0),MIN(N9*R9,AP9),0) -> 0 | BD9: =Param.FestgeldZinssatz -> 0.02 | BE9: =(AP9+SUM(AQ9:BB9)-BC9)*BD9 -> 2019.8931 | BF9: =IF(BE9>Param.SparerPauschbetrag,Param.SparerPauschbetrag,BE9) -> 1000 | BG9: =BE9-BF9 -> 1019.8931 | BH9: =BG9*Param.KapSt -> 268.9968 | BI9: =BE9-BH9 -> 1750.8963 | BJ9: =AP9+SUM(AQ9:BB9)-BC9+BI9 -> 102745.55 | BK9: =AL9+BJ9 -> 489962.3 | BL9: =BK9/(1+Param.Inflationsrate)^(A9-Param.Startjahr) -> 443881.66 | BM9: =IF(BK9<N9,A9,"") | BN9: =AH9+BC9 -> 0 | BO9: =SUM(AR9:BB9) -> -21327.64 | BP9: =BN9+(-1*BO9) -> 21327.64 | BQ9: =AI9+BH9 -> 268.9968 | BR9: =IF(BK9>0,BP9/BK9,0) -> 0.043529145
A10: =A9+1 -> 2031 | B10: =B5+(6-1) -> 35 | C10: =IF(A10<Param.FireStartjahr,0,Param.EntnahmeBetragStart*(1+Param.Inflationsrate)^(A10-Param.Startjahr)) -> 0 | D10: =IF(OR($A10<Param.SonstigRegelmJahrBeginn1,$A10>Param.SonstigRegelmJahrEnd1),0,Param.SonstigRegelmBetragJaehrl1*(1+Param.SonstigRegelmSteig1)^(A10-Param.SonstigRegelmJahrBeginn1)) -> 0 | E10: =IF(OR($A10<Param.SonstigRegelmJahrBeginn2,$A10>Param.SonstigRegelmJahrEnd2),0,Param.SonstigRegelmBetragJaehrl2*(1+Param.SonstigRegelmSteig2)^($A10-Param.SonstigRegelmJahrBeginn2)) -> 0 | F10: =IF(OR($A10<Param.SonstigRegelmJahrBeginn3,$A10>Param.SonstigRegelmJahrEnd3),0,Param.SonstigRegelmBetragJaehrl3*(1+Param.SonstigRegelmSteig3)^($A10-Param.SonstigRegelmJahrBeginn3)) -> 3709.0836 | G10: =IF(OR($A10<Param.SonstigRegelmJahrBeginn4,$A10>Param.SonstigRegelmJahrEnd4),0,Param.SonstigRegelmBetragJaehrl4*(1+Param.SonstigRegelmSteig4)^($A10-Param.SonstigRegelmJahrBeginn4)) -> 0 | H10: =IF(OR($A10<Param.SonstigRegelmJahrBeginn5,$A10>Param.SonstigRegelmJahrEnd5),0,Param.SonstigRegelmBetragJaehrl5*(1+Param.SonstigRegelmSteig5)^($A10-Param.SonstigRegelmJahrBeginn5)) -> 0 | I10: =IF(OR($A10<Param.SonstigRegelmJahrBeginn6,$A10>Param.SonstigRegelmJahrEnd6),0,Param.SonstigRegelmBetragJaehrl6*(1+Param.SonstigRegelmSteig6)^($A10-Param.SonstigRegelmJahrBeginn6)) -> 0 | J10: =IF(OR($A10<Param.SonstigRegelmJahrBeginn7,$A10>Param.SonstigRegelmJahrEnd7),0,Param.SonstigRegelmBetragJaehrl7*(1+Param.SonstigRegelmSteig7)^($A10-Param.SonstigRegelmJahrBeginn7)) -> 0 | K10: =IF(OR($A10<Param.SonstigRegelmJahrBeginn8,$A10>Param.SonstigRegelmJahrEnd8),0,Param.SonstigRegelmBetragJaehrl8*(1+Param.SonstigRegelmSteig8)^($A10-Param.SonstigRegelmJahrBeginn8)) -> 0 | L10: =IF(OR($A10<Param.SonstigRegelmJahrBeginn9,$A10>Param.SonstigRegelmJahrEnd9),0,Param.SonstigRegelmBetragJaehrl9*(1+Param.SonstigRegelmSteig9)^($A10-Param.SonstigRegelmJahrBeginn9)) -> 0 | M10: =IF(OR($A10<Param.SonstigRegelmJahrBeginn10,$A10>Param.SonstigRegelmJahrEnd10),0,Param.SonstigRegelmBetragJaehrl10*(1+Param.SonstigRegelmSteig10)^($A10-Param.SonstigRegelmJahrBeginn10)) -> 0 | N10: =MAX(0,C10-SUM(D10:M10)) -> 0 | O10: =IF(N10<=0,SUM(D10:M10)-C10,0) -> 3709.0836 | P10: =S10+AP10 -> 489962.3 | Q10: =IF(P10>0,S10/P10,0) -> 0.79029907 | R10: =IF(P10>0,AP10/P10,0) -> 0.20970093 | S10: =AL9 -> 387216.75 | T10: =AM9 -> 179716.75 | U10: =IF(A10<Param.FireStartjahr,Param.SparrateDepotMonatl*12*(1+Param.SparrateDynamikJaehrl)^($A10-Param.Startjahr),0) -> 6000 | V10: =IF(AND(Param.SonstigEinmaligKonto1="Depot",$A10=Param.SonstigEinmaligJahr1),Param.SonstigEinmaligBetrag1,0) -> 0 | W10: =IF(AND(Param.SonstigEinmaligKonto2="Depot",$A10=Param.SonstigEinmaligJahr2),Param.SonstigEinmaligBetrag2,0) -> 0 | X10: =IF(AND(Param.SonstigEinmaligKonto3="Depot",$A10=Param.SonstigEinmaligJahr3),Param.SonstigEinmaligBetrag3,0) -> 0 | Y10: =IF(AND(Param.SonstigEinmaligKonto4="Depot",$A10=Param.SonstigEinmaligJahr4),Param.SonstigEinmaligBetrag4,0) -> 0 | Z10: =IF(AND(Param.SonstigEinmaligKonto5="Depot",$A10=Param.SonstigEinmaligJahr5),Param.SonstigEinmaligBetrag5,0) -> 0 | AA10: =IF(AND(Param.SonstigEinmaligKonto6="Depot",$A10=Param.SonstigEinmaligJahr6),Param.SonstigEinmaligBetrag6,0) -> 0 | AB10: =IF(AND(Param.SonstigEinmaligKonto7="Depot",$A10=Param.SonstigEinmaligJahr7),Param.SonstigEinmaligBetrag7,0) -> 0 | AC10: =IF(AND(Param.SonstigEinmaligKonto8="Depot",$A10=Param.SonstigEinmaligJahr8),Param.SonstigEinmaligBetrag8,0) -> 0 | AD10: =IF(AND(Param.SonstigEinmaligKonto9="Depot",$A10=Param.SonstigEinmaligJahr9),Param.SonstigEinmaligBetrag9,0) -> 0 | AE10: =IF(AND(Param.SonstigEinmaligKonto10="Depot",$A10=Param.SonstigEinmaligJahr10),Param.SonstigEinmaligBetrag10,0) -> 0 | AF10: =Param.SparerPauschbetrag-BF10 -> 0 | AG10: =IF(AND(A10>=Param.FireStartjahr,S10>0),MIN(N10*Q10,S10),0) -> 0 | AH10: =IF(AG10<=0,0,IF(S10<=0,0,AG10/(1-MAX(0,((T10/S10)*(1-Param.Teilfreistellung)-MIN(AF10,AG10)/AG10)*Param.KapSt)))) -> 0 | AI10: =AH10-AG10 -> 0 | AJ10: =T10-AH10*(T10/S10) -> 179716.75 | AK10: =S10-AH10 -> 387216.75 | AL10: =FV(AO10,12,-(U10/12),-AK10,0) -> 408814.64 | AM10: =AJ10+AL10-AK10-U10 -> 195314.64 | AN10: =AM10/AL10 -> 0.47775842 | AO10: =(1+IF(AND(A10>=Param.DepotRenditeSpezBeginn1,A10<=Param.DepotRenditeSpezEnde1),Param.DepotRenditeSpezProz1,IF(AND(A10>=Param.DepotRenditeSpezBeginn2,A10<=Param.DepotRenditeSpezEnde2),Param.DepotRenditeSpezProz2,IF(AND(A10>=Param.DepotRenditeSpezBeginn3,A10<=Param.DepotRenditeSpezEnde3),Param.DepotRenditeSpezProz3,IF(AND(A10>=Param.DepotRenditeSpezBeginn4,A10<=Param.DepotRenditeSpezEnde4),Param.DepotRenditeSpezProz4,IF(AND(A10>=Param.DepotRenditeSpezBeginn5,A10<=Param.DepotRenditeSpezEnde5),Param.DepotRenditeSpezProz5,Param.DepotRenditeDefault))))))^(1/12)-1 -> 0.0032737398 | AP10: =BJ9 -> 102745.55 | AQ10: =IF(A10<Param.FireStartjahr,Param.SparrateFestgeldMonatl*12*(1+Param.SparrateDynamikJaehrl)^($A10-Param.Startjahr),0) -> 1800 | AR10: =O10 -> 3709.0836 | AS10: =IF(AND(Param.SonstigEinmaligKonto1="Festgeld",$A10=Param.SonstigEinmaligJahr1),Param.SonstigEinmaligBetrag1,0) -> 0 | AT10: =IF(AND(Param.SonstigEinmaligKonto2="Festgeld",$A10=Param.SonstigEinmaligJahr2),Param.SonstigEinmaligBetrag2,0) -> 0 | AU10: =IF(AND(Param.SonstigEinmaligKonto3="Festgeld",$A10=Param.SonstigEinmaligJahr3),Param.SonstigEinmaligBetrag3,0) -> 0 | AV10: =IF(AND(Param.SonstigEinmaligKonto4="Festgeld",$A10=Param.SonstigEinmaligJahr4),Param.SonstigEinmaligBetrag4,0) -> 0 | AW10: =IF(AND(Param.SonstigEinmaligKonto5="Festgeld",$A10=Param.SonstigEinmaligJahr5),Param.SonstigEinmaligBetrag5,0) -> 0 | AX10: =IF(AND(Param.SonstigEinmaligKonto6="Festgeld",$A10=Param.SonstigEinmaligJahr6),Param.SonstigEinmaligBetrag6,0) -> 0 | AY10: =IF(AND(Param.SonstigEinmaligKonto7="Festgeld",$A10=Param.SonstigEinmaligJahr7),Param.SonstigEinmaligBetrag7,0) -> 0 | AZ10: =IF(AND(Param.SonstigEinmaligKonto8="Festgeld",$A10=Param.SonstigEinmaligJahr8),Param.SonstigEinmaligBetrag8,0) -> 0 | BA10: =IF(AND(Param.SonstigEinmaligKonto9="Festgeld",$A10=Param.SonstigEinmaligJahr9),Param.SonstigEinmaligBetrag9,0) -> 0 | BB10: =IF(AND(Param.SonstigEinmaligKonto10="Festgeld",$A10=Param.SonstigEinmaligJahr10),Param.SonstigEinmaligBetrag10,0) -> 0 | BC10: =IF(AND(A10>=Param.FireStartjahr,AP10>0),MIN(N10*R10,AP10),0) -> 0 | BD10: =Param.FestgeldZinssatz -> 0.02 | BE10: =(AP10+SUM(AQ10:BB10)-BC10)*BD10 -> 2165.0927 | BF10: =IF(BE10>Param.SparerPauschbetrag,Param.SparerPauschbetrag,BE10) -> 1000 | BG10: =BE10-BF10 -> 1165.0927 | BH10: =BG10*Param.KapSt -> 307.29319 | BI10: =BE10-BH10 -> 1857.7995 | BJ10: =AP10+SUM(AQ10:BB10)-BC10+BI10 -> 110112.43 | BK10: =AL10+BJ10 -> 518927.07 | BL10: =BK10/(1+Param.Inflationsrate)^(A10-Param.Startjahr) -> 458655.92 | BM10: =IF(BK10<N10,A10,"") | BN10: =AH10+BC10 -> 0 | BO10: =SUM(AR10:BB10) -> 3709.0836 | BP10: =BN10+(-1*BO10) -> -3709.0836 | BQ10: =AI10+BH10 -> 307.29319 | BR10: =IF(BK10>0,BP10/BK10,0) -> -0.0071476009
A11: =A10+1 -> 2032 | B11: =B5+(7-1) -> 36 | C11: =IF(A11<Param.FireStartjahr,0,Param.EntnahmeBetragStart*(1+Param.Inflationsrate)^(A11-Param.Startjahr)) -> 0 | D11: =IF(OR($A11<Param.SonstigRegelmJahrBeginn1,$A11>Param.SonstigRegelmJahrEnd1),0,Param.SonstigRegelmBetragJaehrl1*(1+Param.SonstigRegelmSteig1)^(A11-Param.SonstigRegelmJahrBeginn1)) -> 0 | E11: =IF(OR($A11<Param.SonstigRegelmJahrBeginn2,$A11>Param.SonstigRegelmJahrEnd2),0,Param.SonstigRegelmBetragJaehrl2*(1+Param.SonstigRegelmSteig2)^($A11-Param.SonstigRegelmJahrBeginn2)) -> 0 | F11: =IF(OR($A11<Param.SonstigRegelmJahrBeginn3,$A11>Param.SonstigRegelmJahrEnd3),0,Param.SonstigRegelmBetragJaehrl3*(1+Param.SonstigRegelmSteig3)^($A11-Param.SonstigRegelmJahrBeginn3)) -> 3746.1744 | G11: =IF(OR($A11<Param.SonstigRegelmJahrBeginn4,$A11>Param.SonstigRegelmJahrEnd4),0,Param.SonstigRegelmBetragJaehrl4*(1+Param.SonstigRegelmSteig4)^($A11-Param.SonstigRegelmJahrBeginn4)) -> 0 | H11: =IF(OR($A11<Param.SonstigRegelmJahrBeginn5,$A11>Param.SonstigRegelmJahrEnd5),0,Param.SonstigRegelmBetragJaehrl5*(1+Param.SonstigRegelmSteig5)^($A11-Param.SonstigRegelmJahrBeginn5)) -> 0 | I11: =IF(OR($A11<Param.SonstigRegelmJahrBeginn6,$A11>Param.SonstigRegelmJahrEnd6),0,Param.SonstigRegelmBetragJaehrl6*(1+Param.SonstigRegelmSteig6)^($A11-Param.SonstigRegelmJahrBeginn6)) -> 0 | J11: =IF(OR($A11<Param.SonstigRegelmJahrBeginn7,$A11>Param.SonstigRegelmJahrEnd7),0,Param.SonstigRegelmBetragJaehrl7*(1+Param.SonstigRegelmSteig7)^($A11-Param.SonstigRegelmJahrBeginn7)) -> 0 | K11: =IF(OR($A11<Param.SonstigRegelmJahrBeginn8,$A11>Param.SonstigRegelmJahrEnd8),0,Param.SonstigRegelmBetragJaehrl8*(1+Param.SonstigRegelmSteig8)^($A11-Param.SonstigRegelmJahrBeginn8)) -> 0 | L11: =IF(OR($A11<Param.SonstigRegelmJahrBeginn9,$A11>Param.SonstigRegelmJahrEnd9),0,Param.SonstigRegelmBetragJaehrl9*(1+Param.SonstigRegelmSteig9)^($A11-Param.SonstigRegelmJahrBeginn9)) -> 0 | M11: =IF(OR($A11<Param.SonstigRegelmJahrBeginn10,$A11>Param.SonstigRegelmJahrEnd10),0,Param.SonstigRegelmBetragJaehrl10*(1+Param.SonstigRegelmSteig10)^($A11-Param.SonstigRegelmJahrBeginn10)) -> 0 | N11: =MAX(0,C11-SUM(D11:M11)) -> 0 | O11: =IF(N11<=0,SUM(D11:M11)-C11,0) -> 3746.1744 | P11: =S11+AP11 -> 518927.07 | Q11: =IF(P11>0,S11/P11,0) -> 0.7878075 | R11: =IF(P11>0,AP11/P11,0) -> 0.2121925 | S11: =AL10 -> 408814.64 | T11: =AM10 -> 195314.64 | U11: =IF(A11<Param.FireStartjahr,Param.SparrateDepotMonatl*12*(1+Param.SparrateDynamikJaehrl)^($A11-Param.Startjahr),0) -> 6000 | V11: =IF(AND(Param.SonstigEinmaligKonto1="Depot",$A11=Param.SonstigEinmaligJahr1),Param.SonstigEinmaligBetrag1,0) -> 0 | W11: =IF(AND(Param.SonstigEinmaligKonto2="Depot",$A11=Param.SonstigEinmaligJahr2),Param.SonstigEinmaligBetrag2,0) -> 0 | X11: =IF(AND(Param.SonstigEinmaligKonto3="Depot",$A11=Param.SonstigEinmaligJahr3),Param.SonstigEinmaligBetrag3,0) -> 0 | Y11: =IF(AND(Param.SonstigEinmaligKonto4="Depot",$A11=Param.SonstigEinmaligJahr4),Param.SonstigEinmaligBetrag4,0) -> 0 | Z11: =IF(AND(Param.SonstigEinmaligKonto5="Depot",$A11=Param.SonstigEinmaligJahr5),Param.SonstigEinmaligBetrag5,0) -> 0 | AA11: =IF(AND(Param.SonstigEinmaligKonto6="Depot",$A11=Param.SonstigEinmaligJahr6),Param.SonstigEinmaligBetrag6,0) -> 0 | AB11: =IF(AND(Param.SonstigEinmaligKonto7="Depot",$A11=Param.SonstigEinmaligJahr7),Param.SonstigEinmaligBetrag7,0) -> 0 | AC11: =IF(AND(Param.SonstigEinmaligKonto8="Depot",$A11=Param.SonstigEinmaligJahr8),Param.SonstigEinmaligBetrag8,0) -> 0 | AD11: =IF(AND(Param.SonstigEinmaligKonto9="Depot",$A11=Param.SonstigEinmaligJahr9),Param.SonstigEinmaligBetrag9,0) -> 0 | AE11: =IF(AND(Param.SonstigEinmaligKonto10="Depot",$A11=Param.SonstigEinmaligJahr10),Param.SonstigEinmaligBetrag10,0) -> 0 | AF11: =Param.SparerPauschbetrag-BF11 -> 0 | AG11: =IF(AND(A11>=Param.FireStartjahr,S11>0),MIN(N11*Q11,S11),0) -> 0 | AH11: =IF(AG11<=0,0,IF(S11<=0,0,AG11/(1-MAX(0,((T11/S11)*(1-Param.Teilfreistellung)-MIN(AF11,AG11)/AG11)*Param.KapSt)))) -> 0 | AI11: =AH11-AG11 -> 0 | AJ11: =T11-AH11*(T11/S11) -> 195314.64 | AK11: =S11-AH11 -> 408814.64 | AL11: =FV(AO11,12,-(U11/12),-AK11,0) -> 431276.44 | AM11: =AJ11+AL11-AK11-U11 -> 211776.44 | AN11: =AM11/AL11 -> 0.4910457 | AO11: =(1+IF(AND(A11>=Param.DepotRenditeSpezBeginn1,A11<=Param.DepotRenditeSpezEnde1),Param.DepotRenditeSpezProz1,IF(AND(A11>=Param.DepotRenditeSpezBeginn2,A11<=Param.DepotRenditeSpezEnde2),Param.DepotRenditeSpezProz2,IF(AND(A11>=Param.DepotRenditeSpezBeginn3,A11<=Param.DepotRenditeSpezEnde3),Param.DepotRenditeSpezProz3,IF(AND(A11>=Param.DepotRenditeSpezBeginn4,A11<=Param.DepotRenditeSpezEnde4),Param.DepotRenditeSpezProz4,IF(AND(A11>=Param.DepotRenditeSpezBeginn5,A11<=Param.DepotRenditeSpezEnde5),Param.DepotRenditeSpezProz5,Param.DepotRenditeDefault))))))^(1/12)-1 -> 0.0032737398 | AP11: =BJ10 -> 110112.43 | AQ11: =IF(A11<Param.FireStartjahr,Param.SparrateFestgeldMonatl*12*(1+Param.SparrateDynamikJaehrl)^($A11-Param.Startjahr),0) -> 1800 | AR11: =O11 -> 3746.1744 | AS11: =IF(AND(Param.SonstigEinmaligKonto1="Festgeld",$A11=Param.SonstigEinmaligJahr1),Param.SonstigEinmaligBetrag1,0) -> 0 | AT11: =IF(AND(Param.SonstigEinmaligKonto2="Festgeld",$A11=Param.SonstigEinmaligJahr2),Param.SonstigEinmaligBetrag2,0) -> 0 | AU11: =IF(AND(Param.SonstigEinmaligKonto3="Festgeld",$A11=Param.SonstigEinmaligJahr3),Param.SonstigEinmaligBetrag3,0) -> 0 | AV11: =IF(AND(Param.SonstigEinmaligKonto4="Festgeld",$A11=Param.SonstigEinmaligJahr4),Param.SonstigEinmaligBetrag4,0) -> 0 | AW11: =IF(AND(Param.SonstigEinmaligKonto5="Festgeld",$A11=Param.SonstigEinmaligJahr5),Param.SonstigEinmaligBetrag5,0) -> 0 | AX11: =IF(AND(Param.SonstigEinmaligKonto6="Festgeld",$A11=Param.SonstigEinmaligJahr6),Param.SonstigEinmaligBetrag6,0) -> 0 | AY11: =IF(AND(Param.SonstigEinmaligKonto7="Festgeld",$A11=Param.SonstigEinmaligJahr7),Param.SonstigEinmaligBetrag7,0) -> 0 | AZ11: =IF(AND(Param.SonstigEinmaligKonto8="Festgeld",$A11=Param.SonstigEinmaligJahr8),Param.SonstigEinmaligBetrag8,0) -> 0 | BA11: =IF(AND(Param.SonstigEinmaligKonto9="Festgeld",$A11=Param.SonstigEinmaligJahr9),Param.SonstigEinmaligBetrag9,0) -> 0 | BB11: =IF(AND(Param.SonstigEinmaligKonto10="Festgeld",$A11=Param.SonstigEinmaligJahr10),Param.SonstigEinmaligBetrag10,0) -> 0 | BC11: =IF(AND(A11>=Param.FireStartjahr,AP11>0),MIN(N11*R11,AP11),0) -> 0 | BD11: =Param.FestgeldZinssatz -> 0.02 | BE11: =(AP11+SUM(AQ11:BB11)-BC11)*BD11 -> 2313.1722 | BF11: =IF(BE11>Param.SparerPauschbetrag,Param.SparerPauschbetrag,BE11) -> 1000 | BG11: =BE11-BF11 -> 1313.1722 | BH11: =BG11*Param.KapSt -> 346.34916 | BI11: =BE11-BH11 -> 1966.823 | BJ11: =AP11+SUM(AQ11:BB11)-BC11+BI11 -> 117625.43 | BK11: =AL11+BJ11 -> 548901.87 | BL11: =BK11/(1+Param.Inflationsrate)^(A11-Param.Startjahr) -> 473316.37 | BM11: =IF(BK11<N11,A11,"") | BN11: =AH11+BC11 -> 0 | BO11: =SUM(AR11:BB11) -> 3746.1744 | BP11: =BN11+(-1*BO11) -> -3746.1744 | BQ11: =AI11+BH11 -> 346.34916 | BR11: =IF(BK11>0,BP11/BK11,0) -> -0.0068248527
A12: =A11+1 -> 2033 | B12: =B5+(8-1) -> 37 | C12: =IF(A12<Param.FireStartjahr,0,Param.EntnahmeBetragStart*(1+Param.Inflationsrate)^(A12-Param.Startjahr)) -> 0 | D12: =IF(OR($A12<Param.SonstigRegelmJahrBeginn1,$A12>Param.SonstigRegelmJahrEnd1),0,Param.SonstigRegelmBetragJaehrl1*(1+Param.SonstigRegelmSteig1)^(A12-Param.SonstigRegelmJahrBeginn1)) -> 0 | E12: =IF(OR($A12<Param.SonstigRegelmJahrBeginn2,$A12>Param.SonstigRegelmJahrEnd2),0,Param.SonstigRegelmBetragJaehrl2*(1+Param.SonstigRegelmSteig2)^($A12-Param.SonstigRegelmJahrBeginn2)) -> 0 | F12: =IF(OR($A12<Param.SonstigRegelmJahrBeginn3,$A12>Param.SonstigRegelmJahrEnd3),0,Param.SonstigRegelmBetragJaehrl3*(1+Param.SonstigRegelmSteig3)^($A12-Param.SonstigRegelmJahrBeginn3)) -> 3783.6362 | G12: =IF(OR($A12<Param.SonstigRegelmJahrBeginn4,$A12>Param.SonstigRegelmJahrEnd4),0,Param.SonstigRegelmBetragJaehrl4*(1+Param.SonstigRegelmSteig4)^($A12-Param.SonstigRegelmJahrBeginn4)) -> 0 | H12: =IF(OR($A12<Param.SonstigRegelmJahrBeginn5,$A12>Param.SonstigRegelmJahrEnd5),0,Param.SonstigRegelmBetragJaehrl5*(1+Param.SonstigRegelmSteig5)^($A12-Param.SonstigRegelmJahrBeginn5)) -> 0 | I12: =IF(OR($A12<Param.SonstigRegelmJahrBeginn6,$A12>Param.SonstigRegelmJahrEnd6),0,Param.SonstigRegelmBetragJaehrl6*(1+Param.SonstigRegelmSteig6)^($A12-Param.SonstigRegelmJahrBeginn6)) -> 0 | J12: =IF(OR($A12<Param.SonstigRegelmJahrBeginn7,$A12>Param.SonstigRegelmJahrEnd7),0,Param.SonstigRegelmBetragJaehrl7*(1+Param.SonstigRegelmSteig7)^($A12-Param.SonstigRegelmJahrBeginn7)) -> 0 | K12: =IF(OR($A12<Param.SonstigRegelmJahrBeginn8,$A12>Param.SonstigRegelmJahrEnd8),0,Param.SonstigRegelmBetragJaehrl8*(1+Param.SonstigRegelmSteig8)^($A12-Param.SonstigRegelmJahrBeginn8)) -> 0 | L12: =IF(OR($A12<Param.SonstigRegelmJahrBeginn9,$A12>Param.SonstigRegelmJahrEnd9),0,Param.SonstigRegelmBetragJaehrl9*(1+Param.SonstigRegelmSteig9)^($A12-Param.SonstigRegelmJahrBeginn9)) -> 0 | M12: =IF(OR($A12<Param.SonstigRegelmJahrBeginn10,$A12>Param.SonstigRegelmJahrEnd10),0,Param.SonstigRegelmBetragJaehrl10*(1+Param.SonstigRegelmSteig10)^($A12-Param.SonstigRegelmJahrBeginn10)) -> 0 | N12: =MAX(0,C12-SUM(D12:M12)) -> 0 | O12: =IF(N12<=0,SUM(D12:M12)-C12,0) -> 3783.6362 | P12: =S12+AP12 -> 548901.87 | Q12: =IF(P12>0,S12/P12,0) -> 0.78570773 | R12: =IF(P12>0,AP12/P12,0) -> 0.21429227 | S12: =AL11 -> 431276.44 | T12: =AM11 -> 211776.44 | U12: =IF(A12<Param.FireStartjahr,Param.SparrateDepotMonatl*12*(1+Param.SparrateDynamikJaehrl)^($A12-Param.Startjahr),0) -> 6000 | V12: =IF(AND(Param.SonstigEinmaligKonto1="Depot",$A12=Param.SonstigEinmaligJahr1),Param.SonstigEinmaligBetrag1,0) -> 0 | W12: =IF(AND(Param.SonstigEinmaligKonto2="Depot",$A12=Param.SonstigEinmaligJahr2),Param.SonstigEinmaligBetrag2,0) -> 0 | X12: =IF(AND(Param.SonstigEinmaligKonto3="Depot",$A12=Param.SonstigEinmaligJahr3),Param.SonstigEinmaligBetrag3,0) -> 0 | Y12: =IF(AND(Param.SonstigEinmaligKonto4="Depot",$A12=Param.SonstigEinmaligJahr4),Param.SonstigEinmaligBetrag4,0) -> 0 | Z12: =IF(AND(Param.SonstigEinmaligKonto5="Depot",$A12=Param.SonstigEinmaligJahr5),Param.SonstigEinmaligBetrag5,0) -> 0 | AA12: =IF(AND(Param.SonstigEinmaligKonto6="Depot",$A12=Param.SonstigEinmaligJahr6),Param.SonstigEinmaligBetrag6,0) -> 0 | AB12: =IF(AND(Param.SonstigEinmaligKonto7="Depot",$A12=Param.SonstigEinmaligJahr7),Param.SonstigEinmaligBetrag7,0) -> 0 | AC12: =IF(AND(Param.SonstigEinmaligKonto8="Depot",$A12=Param.SonstigEinmaligJahr8),Param.SonstigEinmaligBetrag8,0) -> 0 | AD12: =IF(AND(Param.SonstigEinmaligKonto9="Depot",$A12=Param.SonstigEinmaligJahr9),Param.SonstigEinmaligBetrag9,0) -> 0 | AE12: =IF(AND(Param.SonstigEinmaligKonto10="Depot",$A12=Param.SonstigEinmaligJahr10),Param.SonstigEinmaligBetrag10,0) -> 0 | AF12: =Param.SparerPauschbetrag-BF12 -> 0 | AG12: =IF(AND(A12>=Param.FireStartjahr,S12>0),MIN(N12*Q12,S12),0) -> 0 | AH12: =IF(AG12<=0,0,IF(S12<=0,0,AG12/(1-MAX(0,((T12/S12)*(1-Param.Teilfreistellung)-MIN(AF12,AG12)/AG12)*Param.KapSt)))) -> 0 | AI12: =AH12-AG12 -> 0 | AJ12: =T12-AH12*(T12/S12) -> 211776.44 | AK12: =S12-AH12 -> 431276.44 | AL12: =FV(AO12,12,-(U12/12),-AK12,0) -> 454636.72 | AM12: =AJ12+AL12-AK12-U12 -> 229136.72 | AN12: =AM12/AL12 -> 0.50399959 | AO12: =(1+IF(AND(A12>=Param.DepotRenditeSpezBeginn1,A12<=Param.DepotRenditeSpezEnde1),Param.DepotRenditeSpezProz1,IF(AND(A12>=Param.DepotRenditeSpezBeginn2,A12<=Param.DepotRenditeSpezEnde2),Param.DepotRenditeSpezProz2,IF(AND(A12>=Param.DepotRenditeSpezBeginn3,A12<=Param.DepotRenditeSpezEnde3),Param.DepotRenditeSpezProz3,IF(AND(A12>=Param.DepotRenditeSpezBeginn4,A12<=Param.DepotRenditeSpezEnde4),Param.DepotRenditeSpezProz4,IF(AND(A12>=Param.DepotRenditeSpezBeginn5,A12<=Param.DepotRenditeSpezEnde5),Param.DepotRenditeSpezProz5,Param.DepotRenditeDefault))))))^(1/12)-1 -> 0.0032737398 | AP12: =BJ11 -> 117625.43 | AQ12: =IF(A12<Param.FireStartjahr,Param.SparrateFestgeldMonatl*12*(1+Param.SparrateDynamikJaehrl)^($A12-Param.Startjahr),0) -> 1800 | AR12: =O12 -> 3783.6362 | AS12: =IF(AND(Param.SonstigEinmaligKonto1="Festgeld",$A12=Param.SonstigEinmaligJahr1),Param.SonstigEinmaligBetrag1,0) -> 0 | AT12: =IF(AND(Param.SonstigEinmaligKonto2="Festgeld",$A12=Param.SonstigEinmaligJahr2),Param.SonstigEinmaligBetrag2,0) -> 0 | AU12: =IF(AND(Param.SonstigEinmaligKonto3="Festgeld",$A12=Param.SonstigEinmaligJahr3),Param.SonstigEinmaligBetrag3,0) -> 0 | AV12: =IF(AND(Param.SonstigEinmaligKonto4="Festgeld",$A12=Param.SonstigEinmaligJahr4),Param.SonstigEinmaligBetrag4,0) -> 0 | AW12: =IF(AND(Param.SonstigEinmaligKonto5="Festgeld",$A12=Param.SonstigEinmaligJahr5),Param.SonstigEinmaligBetrag5,0) -> 0 | AX12: =IF(AND(Param.SonstigEinmaligKonto6="Festgeld",$A12=Param.SonstigEinmaligJahr6),Param.SonstigEinmaligBetrag6,0) -> 0 | AY12: =IF(AND(Param.SonstigEinmaligKonto7="Festgeld",$A12=Param.SonstigEinmaligJahr7),Param.SonstigEinmaligBetrag7,0) -> 0 | AZ12: =IF(AND(Param.SonstigEinmaligKonto8="Festgeld",$A12=Param.SonstigEinmaligJahr8),Param.SonstigEinmaligBetrag8,0) -> 0 | BA12: =IF(AND(Param.SonstigEinmaligKonto9="Festgeld",$A12=Param.SonstigEinmaligJahr9),Param.SonstigEinmaligBetrag9,0) -> 0 | BB12: =IF(AND(Param.SonstigEinmaligKonto10="Festgeld",$A12=Param.SonstigEinmaligJahr10),Param.SonstigEinmaligBetrag10,0) -> 0 | BC12: =IF(AND(A12>=Param.FireStartjahr,AP12>0),MIN(N12*R12,AP12),0) -> 0 | BD12: =Param.FestgeldZinssatz -> 0.02 | BE12: =(AP12+SUM(AQ12:BB12)-BC12)*BD12 -> 2464.1813 | BF12: =IF(BE12>Param.SparerPauschbetrag,Param.SparerPauschbetrag,BE12) -> 1000 | BG12: =BE12-BF12 -> 1464.1813 | BH12: =BG12*Param.KapSt -> 386.17783 | BI12: =BE12-BH12 -> 2078.0035 | BJ12: =AP12+SUM(AQ12:BB12)-BC12+BI12 -> 125287.07 | BK12: =AL12+BJ12 -> 579923.79 | BL12: =BK12/(1+Param.Inflationsrate)^(A12-Param.Startjahr) -> 487869.73 | BM12: =IF(BK12<N12,A12,"") | BN12: =AH12+BC12 -> 0 | BO12: =SUM(AR12:BB12) -> 3783.6362 | BP12: =BN12+(-1*BO12) -> -3783.6362 | BQ12: =AI12+BH12 -> 386.17783 | BR12: =IF(BK12>0,BP12/BK12,0) -> -0.0065243679
A13: =A12+1 -> 2034 | B13: =B5+(9-1) -> 38 | C13: =IF(A13<Param.FireStartjahr,0,Param.EntnahmeBetragStart*(1+Param.Inflationsrate)^(A13-Param.Startjahr)) -> 0 | D13: =IF(OR($A13<Param.SonstigRegelmJahrBeginn1,$A13>Param.SonstigRegelmJahrEnd1),0,Param.SonstigRegelmBetragJaehrl1*(1+Param.SonstigRegelmSteig1)^(A13-Param.SonstigRegelmJahrBeginn1)) -> 0 | E13: =IF(OR($A13<Param.SonstigRegelmJahrBeginn2,$A13>Param.SonstigRegelmJahrEnd2),0,Param.SonstigRegelmBetragJaehrl2*(1+Param.SonstigRegelmSteig2)^($A13-Param.SonstigRegelmJahrBeginn2)) -> 0 | F13: =IF(OR($A13<Param.SonstigRegelmJahrBeginn3,$A13>Param.SonstigRegelmJahrEnd3),0,Param.SonstigRegelmBetragJaehrl3*(1+Param.SonstigRegelmSteig3)^($A13-Param.SonstigRegelmJahrBeginn3)) -> 3821.4725 | G13: =IF(OR($A13<Param.SonstigRegelmJahrBeginn4,$A13>Param.SonstigRegelmJahrEnd4),0,Param.SonstigRegelmBetragJaehrl4*(1+Param.SonstigRegelmSteig4)^($A13-Param.SonstigRegelmJahrBeginn4)) -> 0 | H13: =IF(OR($A13<Param.SonstigRegelmJahrBeginn5,$A13>Param.SonstigRegelmJahrEnd5),0,Param.SonstigRegelmBetragJaehrl5*(1+Param.SonstigRegelmSteig5)^($A13-Param.SonstigRegelmJahrBeginn5)) -> 0 | I13: =IF(OR($A13<Param.SonstigRegelmJahrBeginn6,$A13>Param.SonstigRegelmJahrEnd6),0,Param.SonstigRegelmBetragJaehrl6*(1+Param.SonstigRegelmSteig6)^($A13-Param.SonstigRegelmJahrBeginn6)) -> 0 | J13: =IF(OR($A13<Param.SonstigRegelmJahrBeginn7,$A13>Param.SonstigRegelmJahrEnd7),0,Param.SonstigRegelmBetragJaehrl7*(1+Param.SonstigRegelmSteig7)^($A13-Param.SonstigRegelmJahrBeginn7)) -> 0 | K13: =IF(OR($A13<Param.SonstigRegelmJahrBeginn8,$A13>Param.SonstigRegelmJahrEnd8),0,Param.SonstigRegelmBetragJaehrl8*(1+Param.SonstigRegelmSteig8)^($A13-Param.SonstigRegelmJahrBeginn8)) -> 0 | L13: =IF(OR($A13<Param.SonstigRegelmJahrBeginn9,$A13>Param.SonstigRegelmJahrEnd9),0,Param.SonstigRegelmBetragJaehrl9*(1+Param.SonstigRegelmSteig9)^($A13-Param.SonstigRegelmJahrBeginn9)) -> 0 | M13: =IF(OR($A13<Param.SonstigRegelmJahrBeginn10,$A13>Param.SonstigRegelmJahrEnd10),0,Param.SonstigRegelmBetragJaehrl10*(1+Param.SonstigRegelmSteig10)^($A13-Param.SonstigRegelmJahrBeginn10)) -> 0 | N13: =MAX(0,C13-SUM(D13:M13)) -> 0 | O13: =IF(N13<=0,SUM(D13:M13)-C13,0) -> 3821.4725 | P13: =S13+AP13 -> 579923.79 | Q13: =IF(P13>0,S13/P13,0) -> 0.78395942 | R13: =IF(P13>0,AP13/P13,0) -> 0.21604058 | S13: =AL12 -> 454636.72 | T13: =AM12 -> 229136.72 | U13: =IF(A13<Param.FireStartjahr,Param.SparrateDepotMonatl*12*(1+Param.SparrateDynamikJaehrl)^($A13-Param.Startjahr),0) -> 6000 | V13: =IF(AND(Param.SonstigEinmaligKonto1="Depot",$A13=Param.SonstigEinmaligJahr1),Param.SonstigEinmaligBetrag1,0) -> 0 | W13: =IF(AND(Param.SonstigEinmaligKonto2="Depot",$A13=Param.SonstigEinmaligJahr2),Param.SonstigEinmaligBetrag2,0) -> 0 | X13: =IF(AND(Param.SonstigEinmaligKonto3="Depot",$A13=Param.SonstigEinmaligJahr3),Param.SonstigEinmaligBetrag3,0) -> 0 | Y13: =IF(AND(Param.SonstigEinmaligKonto4="Depot",$A13=Param.SonstigEinmaligJahr4),Param.SonstigEinmaligBetrag4,0) -> 0 | Z13: =IF(AND(Param.SonstigEinmaligKonto5="Depot",$A13=Param.SonstigEinmaligJahr5),Param.SonstigEinmaligBetrag5,0) -> 0 | AA13: =IF(AND(Param.SonstigEinmaligKonto6="Depot",$A13=Param.SonstigEinmaligJahr6),Param.SonstigEinmaligBetrag6,0) -> 0 | AB13: =IF(AND(Param.SonstigEinmaligKonto7="Depot",$A13=Param.SonstigEinmaligJahr7),Param.SonstigEinmaligBetrag7,0) -> 0 | AC13: =IF(AND(Param.SonstigEinmaligKonto8="Depot",$A13=Param.SonstigEinmaligJahr8),Param.SonstigEinmaligBetrag8,0) -> 0 | AD13: =IF(AND(Param.SonstigEinmaligKonto9="Depot",$A13=Param.SonstigEinmaligJahr9),Param.SonstigEinmaligBetrag9,0) -> 0 | AE13: =IF(AND(Param.SonstigEinmaligKonto10="Depot",$A13=Param.SonstigEinmaligJahr10),Param.SonstigEinmaligBetrag10,0) -> 0 | AF13: =Param.SparerPauschbetrag-BF13 -> 0 | AG13: =IF(AND(A13>=Param.FireStartjahr,S13>0),MIN(N13*Q13,S13),0) -> 0 | AH13: =IF(AG13<=0,0,IF(S13<=0,0,AG13/(1-MAX(0,((T13/S13)*(1-Param.Teilfreistellung)-MIN(AF13,AG13)/AG13)*Param.KapSt)))) -> 0 | AI13: =AH13-AG13 -> 0 | AJ13: =T13-AH13*(T13/S13) -> 229136.72 | AK13: =S13-AH13 -> 454636.72 | AL13: =FV(AO13,12,-(U13/12),-AK13,0) -> 488078.19 | AM13: =AJ13+AL13-AK13-U13 -> 256578.19 | AN13: =AM13/AL13 -> 0.52569075 | AO13: =(1+IF(AND(A13>=Param.DepotRenditeSpezBeginn1,A13<=Param.DepotRenditeSpezEnde1),Param.DepotRenditeSpezProz1,IF(AND(A13>=Param.DepotRenditeSpezBeginn2,A13<=Param.DepotRenditeSpezEnde2),Param.DepotRenditeSpezProz2,IF(AND(A13>=Param.DepotRenditeSpezBeginn3,A13<=Param.DepotRenditeSpezEnde3),Param.DepotRenditeSpezProz3,IF(AND(A13>=Param.DepotRenditeSpezBeginn4,A13<=Param.DepotRenditeSpezEnde4),Param.DepotRenditeSpezProz4,IF(AND(A13>=Param.DepotRenditeSpezBeginn5,A13<=Param.DepotRenditeSpezEnde5),Param.DepotRenditeSpezProz5,Param.DepotRenditeDefault))))))^(1/12)-1 -> 0.0048675506 | AP13: =BJ12 -> 125287.07 | AQ13: =IF(A13<Param.FireStartjahr,Param.SparrateFestgeldMonatl*12*(1+Param.SparrateDynamikJaehrl)^($A13-Param.Startjahr),0) -> 1800 | AR13: =O13 -> 3821.4725 | AS13: =IF(AND(Param.SonstigEinmaligKonto1="Festgeld",$A13=Param.SonstigEinmaligJahr1),Param.SonstigEinmaligBetrag1,0) -> 0 | AT13: =IF(AND(Param.SonstigEinmaligKonto2="Festgeld",$A13=Param.SonstigEinmaligJahr2),Param.SonstigEinmaligBetrag2,0) -> 0 | AU13: =IF(AND(Param.SonstigEinmaligKonto3="Festgeld",$A13=Param.SonstigEinmaligJahr3),Param.SonstigEinmaligBetrag3,0) -> 0 | AV13: =IF(AND(Param.SonstigEinmaligKonto4="Festgeld",$A13=Param.SonstigEinmaligJahr4),Param.SonstigEinmaligBetrag4,0) -> 0 | AW13: =IF(AND(Param.SonstigEinmaligKonto5="Festgeld",$A13=Param.SonstigEinmaligJahr5),Param.SonstigEinmaligBetrag5,0) -> 0 | AX13: =IF(AND(Param.SonstigEinmaligKonto6="Festgeld",$A13=Param.SonstigEinmaligJahr6),Param.SonstigEinmaligBetrag6,0) -> 0 | AY13: =IF(AND(Param.SonstigEinmaligKonto7="Festgeld",$A13=Param.SonstigEinmaligJahr7),Param.SonstigEinmaligBetrag7,0) -> 0 | AZ13: =IF(AND(Param.SonstigEinmaligKonto8="Festgeld",$A13=Param.SonstigEinmaligJahr8),Param.SonstigEinmaligBetrag8,0) -> 0 | BA13: =IF(AND(Param.SonstigEinmaligKonto9="Festgeld",$A13=Param.SonstigEinmaligJahr9),Param.SonstigEinmaligBetrag9,0) -> 0 | BB13: =IF(AND(Param.SonstigEinmaligKonto10="Festgeld",$A13=Param.SonstigEinmaligJahr10),Param.SonstigEinmaligBetrag10,0) -> 0 | BC13: =IF(AND(A13>=Param.FireStartjahr,AP13>0),MIN(N13*R13,AP13),0) -> 0 | BD13: =Param.FestgeldZinssatz -> 0.02 | BE13: =(AP13+SUM(AQ13:BB13)-BC13)*BD13 -> 2618.1709 | BF13: =IF(BE13>Param.SparerPauschbetrag,Param.SparerPauschbetrag,BE13) -> 1000 | BG13: =BE13-BF13 -> 1618.1709 | BH13: =BG13*Param.KapSt -> 426.79257 | BI13: =BE13-BH13 -> 2191.3783 | BJ13: =AP13+SUM(AQ13:BB13)-BC13+BI13 -> 133099.92 | BK13: =AL13+BJ13 -> 621178.11 | BL13: =BK13/(1+Param.Inflationsrate)^(A13-Param.Startjahr) -> 509829.8 | BM13: =IF(BK13<N13,A13,"") | BN13: =AH13+BC13 -> 0 | BO13: =SUM(AR13:BB13) -> 3821.4725 | BP13: =BN13+(-1*BO13) -> -3821.4725 | BQ13: =AI13+BH13 -> 426.79257 | BR13: =IF(BK13>0,BP13/BK13,0) -> -0.0061519755
A14: =A13+1 -> 2035 | B14: =B5+(10-1) -> 39 | C14: =IF(A14<Param.FireStartjahr,0,Param.EntnahmeBetragStart*(1+Param.Inflationsrate)^(A14-Param.Startjahr)) -> 0 | D14: =IF(OR($A14<Param.SonstigRegelmJahrBeginn1,$A14>Param.SonstigRegelmJahrEnd1),0,Param.SonstigRegelmBetragJaehrl1*(1+Param.SonstigRegelmSteig1)^(A14-Param.SonstigRegelmJahrBeginn1)) -> 0 | E14: =IF(OR($A14<Param.SonstigRegelmJahrBeginn2,$A14>Param.SonstigRegelmJahrEnd2),0,Param.SonstigRegelmBetragJaehrl2*(1+Param.SonstigRegelmSteig2)^($A14-Param.SonstigRegelmJahrBeginn2)) -> 0 | F14: =IF(OR($A14<Param.SonstigRegelmJahrBeginn3,$A14>Param.SonstigRegelmJahrEnd3),0,Param.SonstigRegelmBetragJaehrl3*(1+Param.SonstigRegelmSteig3)^($A14-Param.SonstigRegelmJahrBeginn3)) -> 3859.6873 | G14: =IF(OR($A14<Param.SonstigRegelmJahrBeginn4,$A14>Param.SonstigRegelmJahrEnd4),0,Param.SonstigRegelmBetragJaehrl4*(1+Param.SonstigRegelmSteig4)^($A14-Param.SonstigRegelmJahrBeginn4)) -> 0 | H14: =IF(OR($A14<Param.SonstigRegelmJahrBeginn5,$A14>Param.SonstigRegelmJahrEnd5),0,Param.SonstigRegelmBetragJaehrl5*(1+Param.SonstigRegelmSteig5)^($A14-Param.SonstigRegelmJahrBeginn5)) -> 0 | I14: =IF(OR($A14<Param.SonstigRegelmJahrBeginn6,$A14>Param.SonstigRegelmJahrEnd6),0,Param.SonstigRegelmBetragJaehrl6*(1+Param.SonstigRegelmSteig6)^($A14-Param.SonstigRegelmJahrBeginn6)) -> 0 | J14: =IF(OR($A14<Param.SonstigRegelmJahrBeginn7,$A14>Param.SonstigRegelmJahrEnd7),0,Param.SonstigRegelmBetragJaehrl7*(1+Param.SonstigRegelmSteig7)^($A14-Param.SonstigRegelmJahrBeginn7)) -> 0 | K14: =IF(OR($A14<Param.SonstigRegelmJahrBeginn8,$A14>Param.SonstigRegelmJahrEnd8),0,Param.SonstigRegelmBetragJaehrl8*(1+Param.SonstigRegelmSteig8)^($A14-Param.SonstigRegelmJahrBeginn8)) -> 0 | L14: =IF(OR($A14<Param.SonstigRegelmJahrBeginn9,$A14>Param.SonstigRegelmJahrEnd9),0,Param.SonstigRegelmBetragJaehrl9*(1+Param.SonstigRegelmSteig9)^($A14-Param.SonstigRegelmJahrBeginn9)) -> 0 | M14: =IF(OR($A14<Param.SonstigRegelmJahrBeginn10,$A14>Param.SonstigRegelmJahrEnd10),0,Param.SonstigRegelmBetragJaehrl10*(1+Param.SonstigRegelmSteig10)^($A14-Param.SonstigRegelmJahrBeginn10)) -> 0 | N14: =MAX(0,C14-SUM(D14:M14)) -> 0 | O14: =IF(N14<=0,SUM(D14:M14)-C14,0) -> 3859.6873 | P14: =S14+AP14 -> 621178.11 | Q14: =IF(P14>0,S14/P14,0) -> 0.78572986 | R14: =IF(P14>0,AP14/P14,0) -> 0.21427014 | S14: =AL13 -> 488078.19 | T14: =AM13 -> 256578.19 | U14: =IF(A14<Param.FireStartjahr,Param.SparrateDepotMonatl*12*(1+Param.SparrateDynamikJaehrl)^($A14-Param.Startjahr),0) -> 6000 | V14: =IF(AND(Param.SonstigEinmaligKonto1="Depot",$A14=Param.SonstigEinmaligJahr1),Param.SonstigEinmaligBetrag1,0) -> 0 | W14: =IF(AND(Param.SonstigEinmaligKonto2="Depot",$A14=Param.SonstigEinmaligJahr2),Param.SonstigEinmaligBetrag2,0) -> 0 | X14: =IF(AND(Param.SonstigEinmaligKonto3="Depot",$A14=Param.SonstigEinmaligJahr3),Param.SonstigEinmaligBetrag3,0) -> 0 | Y14: =IF(AND(Param.SonstigEinmaligKonto4="Depot",$A14=Param.SonstigEinmaligJahr4),Param.SonstigEinmaligBetrag4,0) -> 0 | Z14: =IF(AND(Param.SonstigEinmaligKonto5="Depot",$A14=Param.SonstigEinmaligJahr5),Param.SonstigEinmaligBetrag5,0) -> 0 | AA14: =IF(AND(Param.SonstigEinmaligKonto6="Depot",$A14=Param.SonstigEinmaligJahr6),Param.SonstigEinmaligBetrag6,0) -> 0 | AB14: =IF(AND(Param.SonstigEinmaligKonto7="Depot",$A14=Param.SonstigEinmaligJahr7),Param.SonstigEinmaligBetrag7,0) -> 0 | AC14: =IF(AND(Param.SonstigEinmaligKonto8="Depot",$A14=Param.SonstigEinmaligJahr8),Param.SonstigEinmaligBetrag8,0) -> 0 | AD14: =IF(AND(Param.SonstigEinmaligKonto9="Depot",$A14=Param.SonstigEinmaligJahr9),Param.SonstigEinmaligBetrag9,0) -> 0 | AE14: =IF(AND(Param.SonstigEinmaligKonto10="Depot",$A14=Param.SonstigEinmaligJahr10),Param.SonstigEinmaligBetrag10,0) -> 0 | AF14: =Param.SparerPauschbetrag-BF14 -> 0 | AG14: =IF(AND(A14>=Param.FireStartjahr,S14>0),MIN(N14*Q14,S14),0) -> 0 | AH14: =IF(AG14<=0,0,IF(S14<=0,0,AG14/(1-MAX(0,((T14/S14)*(1-Param.Teilfreistellung)-MIN(AF14,AG14)/AG14)*Param.KapSt)))) -> 0 | AI14: =AH14-AG14 -> 0 | AJ14: =T14-AH14*(T14/S14) -> 256578.19 | AK14: =S14-AH14 -> 488078.19 | AL14: =FV(AO14,12,-(U14/12),-AK14,0) -> 523526.15 | AM14: =AJ14+AL14-AK14-U14 -> 286026.15 | AN14: =AM14/AL14 -> 0.54634548 | AO14: =(1+IF(AND(A14>=Param.DepotRenditeSpezBeginn1,A14<=Param.DepotRenditeSpezEnde1),Param.DepotRenditeSpezProz1,IF(AND(A14>=Param.DepotRenditeSpezBeginn2,A14<=Param.DepotRenditeSpezEnde2),Param.DepotRenditeSpezProz2,IF(AND(A14>=Param.DepotRenditeSpezBeginn3,A14<=Param.DepotRenditeSpezEnde3),Param.DepotRenditeSpezProz3,IF(AND(A14>=Param.DepotRenditeSpezBeginn4,A14<=Param.DepotRenditeSpezEnde4),Param.DepotRenditeSpezProz4,IF(AND(A14>=Param.DepotRenditeSpezBeginn5,A14<=Param.DepotRenditeSpezEnde5),Param.DepotRenditeSpezProz5,Param.DepotRenditeDefault))))))^(1/12)-1 -> 0.0048675506 | AP14: =BJ13 -> 133099.92 | AQ14: =IF(A14<Param.FireStartjahr,Param.SparrateFestgeldMonatl*12*(1+Param.SparrateDynamikJaehrl)^($A14-Param.Startjahr),0) -> 1800 | AR14: =O14 -> 3859.6873 | AS14: =IF(AND(Param.SonstigEinmaligKonto1="Festgeld",$A14=Param.SonstigEinmaligJahr1),Param.SonstigEinmaligBetrag1,0) -> 0 | AT14: =IF(AND(Param.SonstigEinmaligKonto2="Festgeld",$A14=Param.SonstigEinmaligJahr2),Param.SonstigEinmaligBetrag2,0) -> 0 | AU14: =IF(AND(Param.SonstigEinmaligKonto3="Festgeld",$A14=Param.SonstigEinmaligJahr3),Param.SonstigEinmaligBetrag3,0) -> 0 | AV14: =IF(AND(Param.SonstigEinmaligKonto4="Festgeld",$A14=Param.SonstigEinmaligJahr4),Param.SonstigEinmaligBetrag4,0) -> 0 | AW14: =IF(AND(Param.SonstigEinmaligKonto5="Festgeld",$A14=Param.SonstigEinmaligJahr5),Param.SonstigEinmaligBetrag5,0) -> 0 | AX14: =IF(AND(Param.SonstigEinmaligKonto6="Festgeld",$A14=Param.SonstigEinmaligJahr6),Param.SonstigEinmaligBetrag6,0) -> 0 | AY14: =IF(AND(Param.SonstigEinmaligKonto7="Festgeld",$A14=Param.SonstigEinmaligJahr7),Param.SonstigEinmaligBetrag7,0) -> 0 | AZ14: =IF(AND(Param.SonstigEinmaligKonto8="Festgeld",$A14=Param.SonstigEinmaligJahr8),Param.SonstigEinmaligBetrag8,0) -> 0 | BA14: =IF(AND(Param.SonstigEinmaligKonto9="Festgeld",$A14=Param.SonstigEinmaligJahr9),Param.SonstigEinmaligBetrag9,0) -> 0 | BB14: =IF(AND(Param.SonstigEinmaligKonto10="Festgeld",$A14=Param.SonstigEinmaligJahr10),Param.SonstigEinmaligBetrag10,0) -> 0 | BC14: =IF(AND(A14>=Param.FireStartjahr,AP14>0),MIN(N14*R14,AP14),0) -> 0 | BD14: =Param.FestgeldZinssatz -> 0.02 | BE14: =(AP14+SUM(AQ14:BB14)-BC14)*BD14 -> 2775.1922 | BF14: =IF(BE14>Param.SparerPauschbetrag,Param.SparerPauschbetrag,BE14) -> 1000 | BG14: =BE14-BF14 -> 1775.1922 | BH14: =BG14*Param.KapSt -> 468.20694 | BI14: =BE14-BH14 -> 2306.9852 | BJ14: =AP14+SUM(AQ14:BB14)-BC14+BI14 -> 141066.59 | BK14: =AL14+BJ14 -> 664592.74 | BL14: =BK14/(1+Param.Inflationsrate)^(A14-Param.Startjahr) -> 532158.26 | BM14: =IF(BK14<N14,A14,"") | BN14: =AH14+BC14 -> 0 | BO14: =SUM(AR14:BB14) -> 3859.6873 | BP14: =BN14+(-1*BO14) -> -3859.6873 | BQ14: =AI14+BH14 -> 468.20694 | BR14: =IF(BK14>0,BP14/BK14,0) -> -0.0058075977
A15: =A14+1 -> 2036 | B15: =B5+(11-1) -> 40 | C15: =IF(A15<Param.FireStartjahr,0,Param.EntnahmeBetragStart*(1+Param.Inflationsrate)^(A15-Param.Startjahr)) -> 0 | D15: =IF(OR($A15<Param.SonstigRegelmJahrBeginn1,$A15>Param.SonstigRegelmJahrEnd1),0,Param.SonstigRegelmBetragJaehrl1*(1+Param.SonstigRegelmSteig1)^(A15-Param.SonstigRegelmJahrBeginn1)) -> 0 | E15: =IF(OR($A15<Param.SonstigRegelmJahrBeginn2,$A15>Param.SonstigRegelmJahrEnd2),0,Param.SonstigRegelmBetragJaehrl2*(1+Param.SonstigRegelmSteig2)^($A15-Param.SonstigRegelmJahrBeginn2)) -> 0 | F15: =IF(OR($A15<Param.SonstigRegelmJahrBeginn3,$A15>Param.SonstigRegelmJahrEnd3),0,Param.SonstigRegelmBetragJaehrl3*(1+Param.SonstigRegelmSteig3)^($A15-Param.SonstigRegelmJahrBeginn3)) -> 3898.2841 | G15: =IF(OR($A15<Param.SonstigRegelmJahrBeginn4,$A15>Param.SonstigRegelmJahrEnd4),0,Param.SonstigRegelmBetragJaehrl4*(1+Param.SonstigRegelmSteig4)^($A15-Param.SonstigRegelmJahrBeginn4)) -> 0 | H15: =IF(OR($A15<Param.SonstigRegelmJahrBeginn5,$A15>Param.SonstigRegelmJahrEnd5),0,Param.SonstigRegelmBetragJaehrl5*(1+Param.SonstigRegelmSteig5)^($A15-Param.SonstigRegelmJahrBeginn5)) -> 0 | I15: =IF(OR($A15<Param.SonstigRegelmJahrBeginn6,$A15>Param.SonstigRegelmJahrEnd6),0,Param.SonstigRegelmBetragJaehrl6*(1+Param.SonstigRegelmSteig6)^($A15-Param.SonstigRegelmJahrBeginn6)) -> 0 | J15: =IF(OR($A15<Param.SonstigRegelmJahrBeginn7,$A15>Param.SonstigRegelmJahrEnd7),0,Param.SonstigRegelmBetragJaehrl7*(1+Param.SonstigRegelmSteig7)^($A15-Param.SonstigRegelmJahrBeginn7)) -> 0 | K15: =IF(OR($A15<Param.SonstigRegelmJahrBeginn8,$A15>Param.SonstigRegelmJahrEnd8),0,Param.SonstigRegelmBetragJaehrl8*(1+Param.SonstigRegelmSteig8)^($A15-Param.SonstigRegelmJahrBeginn8)) -> 0 | L15: =IF(OR($A15<Param.SonstigRegelmJahrBeginn9,$A15>Param.SonstigRegelmJahrEnd9),0,Param.SonstigRegelmBetragJaehrl9*(1+Param.SonstigRegelmSteig9)^($A15-Param.SonstigRegelmJahrBeginn9)) -> 0 | M15: =IF(OR($A15<Param.SonstigRegelmJahrBeginn10,$A15>Param.SonstigRegelmJahrEnd10),0,Param.SonstigRegelmBetragJaehrl10*(1+Param.SonstigRegelmSteig10)^($A15-Param.SonstigRegelmJahrBeginn10)) -> 0 | N15: =MAX(0,C15-SUM(D15:M15)) -> 0 | O15: =IF(N15<=0,SUM(D15:M15)-C15,0) -> 3898.2841 | P15: =S15+AP15 -> 664592.74 | Q15: =IF(P15>0,S15/P15,0) -> 0.78773979 | R15: =IF(P15>0,AP15/P15,0) -> 0.21226021 | S15: =AL14 -> 523526.15 | T15: =AM14 -> 286026.15 | U15: =IF(A15<Param.FireStartjahr,Param.SparrateDepotMonatl*12*(1+Param.SparrateDynamikJaehrl)^($A15-Param.Startjahr),0) -> 6000 | V15: =IF(AND(Param.SonstigEinmaligKonto1="Depot",$A15=Param.SonstigEinmaligJahr1),Param.SonstigEinmaligBetrag1,0) -> 0 | W15: =IF(AND(Param.SonstigEinmaligKonto2="Depot",$A15=Param.SonstigEinmaligJahr2),Param.SonstigEinmaligBetrag2,0) -> 0 | X15: =IF(AND(Param.SonstigEinmaligKonto3="Depot",$A15=Param.SonstigEinmaligJahr3),Param.SonstigEinmaligBetrag3,0) -> 0 | Y15: =IF(AND(Param.SonstigEinmaligKonto4="Depot",$A15=Param.SonstigEinmaligJahr4),Param.SonstigEinmaligBetrag4,0) -> 0 | Z15: =IF(AND(Param.SonstigEinmaligKonto5="Depot",$A15=Param.SonstigEinmaligJahr5),Param.SonstigEinmaligBetrag5,0) -> 0 | AA15: =IF(AND(Param.SonstigEinmaligKonto6="Depot",$A15=Param.SonstigEinmaligJahr6),Param.SonstigEinmaligBetrag6,0) -> 0 | AB15: =IF(AND(Param.SonstigEinmaligKonto7="Depot",$A15=Param.SonstigEinmaligJahr7),Param.SonstigEinmaligBetrag7,0) -> 0 | AC15: =IF(AND(Param.SonstigEinmaligKonto8="Depot",$A15=Param.SonstigEinmaligJahr8),Param.SonstigEinmaligBetrag8,0) -> 0 | AD15: =IF(AND(Param.SonstigEinmaligKonto9="Depot",$A15=Param.SonstigEinmaligJahr9),Param.SonstigEinmaligBetrag9,0) -> 0 | AE15: =IF(AND(Param.SonstigEinmaligKonto10="Depot",$A15=Param.SonstigEinmaligJahr10),Param.SonstigEinmaligBetrag10,0) -> 0 | AF15: =Param.SparerPauschbetrag-BF15 -> 0 | AG15: =IF(AND(A15>=Param.FireStartjahr,S15>0),MIN(N15*Q15,S15),0) -> 0 | AH15: =IF(AG15<=0,0,IF(S15<=0,0,AG15/(1-MAX(0,((T15/S15)*(1-Param.Teilfreistellung)-MIN(AF15,AG15)/AG15)*Param.KapSt)))) -> 0 | AI15: =AH15-AG15 -> 0 | AJ15: =T15-AH15*(T15/S15) -> 286026.15 | AK15: =S15-AH15 -> 523526.15 | AL15: =FV(AO15,12,-(U15/12),-AK15,0) -> 561100.98 | AM15: =AJ15+AL15-AK15-U15 -> 317600.98 | AN15: =AM15/AL15 -> 0.56603177 | AO15: =(1+IF(AND(A15>=Param.DepotRenditeSpezBeginn1,A15<=Param.DepotRenditeSpezEnde1),Param.DepotRenditeSpezProz1,IF(AND(A15>=Param.DepotRenditeSpezBeginn2,A15<=Param.DepotRenditeSpezEnde2),Param.DepotRenditeSpezProz2,IF(AND(A15>=Param.DepotRenditeSpezBeginn3,A15<=Param.DepotRenditeSpezEnde3),Param.DepotRenditeSpezProz3,IF(AND(A15>=Param.DepotRenditeSpezBeginn4,A15<=Param.DepotRenditeSpezEnde4),Param.DepotRenditeSpezProz4,IF(AND(A15>=Param.DepotRenditeSpezBeginn5,A15<=Param.DepotRenditeSpezEnde5),Param.DepotRenditeSpezProz5,Param.DepotRenditeDefault))))))^(1/12)-1 -> 0.0048675506 | AP15: =BJ14 -> 141066.59 | AQ15: =IF(A15<Param.FireStartjahr,Param.SparrateFestgeldMonatl*12*(1+Param.SparrateDynamikJaehrl)^($A15-Param.Startjahr),0) -> 1800 | AR15: =O15 -> 3898.2841 | AS15: =IF(AND(Param.SonstigEinmaligKonto1="Festgeld",$A15=Param.SonstigEinmaligJahr1),Param.SonstigEinmaligBetrag1,0) -> 0 | AT15: =IF(AND(Param.SonstigEinmaligKonto2="Festgeld",$A15=Param.SonstigEinmaligJahr2),Param.SonstigEinmaligBetrag2,0) -> 0 | AU15: =IF(AND(Param.SonstigEinmaligKonto3="Festgeld",$A15=Param.SonstigEinmaligJahr3),Param.SonstigEinmaligBetrag3,0) -> 0 | AV15: =IF(AND(Param.SonstigEinmaligKonto4="Festgeld",$A15=Param.SonstigEinmaligJahr4),Param.SonstigEinmaligBetrag4,0) -> 0 | AW15: =IF(AND(Param.SonstigEinmaligKonto5="Festgeld",$A15=Param.SonstigEinmaligJahr5),Param.SonstigEinmaligBetrag5,0) -> 0 | AX15: =IF(AND(Param.SonstigEinmaligKonto6="Festgeld",$A15=Param.SonstigEinmaligJahr6),Param.SonstigEinmaligBetrag6,0) -> 0 | AY15: =IF(AND(Param.SonstigEinmaligKonto7="Festgeld",$A15=Param.SonstigEinmaligJahr7),Param.SonstigEinmaligBetrag7,0) -> 0 | AZ15: =IF(AND(Param.SonstigEinmaligKonto8="Festgeld",$A15=Param.SonstigEinmaligJahr8),Param.SonstigEinmaligBetrag8,0) -> 0 | BA15: =IF(AND(Param.SonstigEinmaligKonto9="Festgeld",$A15=Param.SonstigEinmaligJahr9),Param.SonstigEinmaligBetrag9,0) -> 0 | BB15: =IF(AND(Param.SonstigEinmaligKonto10="Festgeld",$A15=Param.SonstigEinmaligJahr10),Param.SonstigEinmaligBetrag10,0) -> 0 | BC15: =IF(AND(A15>=Param.FireStartjahr,AP15>0),MIN(N15*R15,AP15),0) -> 0 | BD15: =Param.FestgeldZinssatz -> 0.02 | BE15: =(AP15+AQ15-BC15)*BD15 -> 2857.3319 | BF15: =IF(BE15>Param.SparerPauschbetrag,Param.SparerPauschbetrag,BE15) -> 1000 | BG15: =BE15-BF15 -> 1857.3319 | BH15: =BG15*Param.KapSt -> 489.87128 | BI15: =BE15-BH15 -> 2367.4606 | BJ15: =AP15+SUM(AQ15:BB15)-BC15+BI15 -> 149132.34 | BK15: =AL15+BJ15 -> 710233.32 | BL15: =BK15/(1+Param.Inflationsrate)^(A15-Param.Startjahr) -> 554833.13 | BM15: =IF(BK15<N15,A15,"") | BN15: =AH15+BC15 -> 0 | BO15: =SUM(AR15:BB15) -> 3898.2841 | BP15: =BN15+(-1*BO15) -> -3898.2841 | BQ15: =AI15+BH15 -> 489.87128 | BR15: =IF(BK15>0,BP15/BK15,0) -> -0.0054887374
A16: =A15+1 -> 2037 | B16: =B5+(12-1) -> 41 | C16: =IF(A16<Param.FireStartjahr,0,Param.EntnahmeBetragStart*(1+Param.Inflationsrate)^(A16-Param.Startjahr)) -> 0 | D16: =IF(OR($A16<Param.SonstigRegelmJahrBeginn1,$A16>Param.SonstigRegelmJahrEnd1),0,Param.SonstigRegelmBetragJaehrl1*(1+Param.SonstigRegelmSteig1)^(A16-Param.SonstigRegelmJahrBeginn1)) -> 0 | E16: =IF(OR($A16<Param.SonstigRegelmJahrBeginn2,$A16>Param.SonstigRegelmJahrEnd2),0,Param.SonstigRegelmBetragJaehrl2*(1+Param.SonstigRegelmSteig2)^($A16-Param.SonstigRegelmJahrBeginn2)) -> 0 | F16: =IF(OR($A16<Param.SonstigRegelmJahrBeginn3,$A16>Param.SonstigRegelmJahrEnd3),0,Param.SonstigRegelmBetragJaehrl3*(1+Param.SonstigRegelmSteig3)^($A16-Param.SonstigRegelmJahrBeginn3)) -> 3937.267 | G16: =IF(OR($A16<Param.SonstigRegelmJahrBeginn4,$A16>Param.SonstigRegelmJahrEnd4),0,Param.SonstigRegelmBetragJaehrl4*(1+Param.SonstigRegelmSteig4)^($A16-Param.SonstigRegelmJahrBeginn4)) -> 0 | H16: =IF(OR($A16<Param.SonstigRegelmJahrBeginn5,$A16>Param.SonstigRegelmJahrEnd5),0,Param.SonstigRegelmBetragJaehrl5*(1+Param.SonstigRegelmSteig5)^($A16-Param.SonstigRegelmJahrBeginn5)) -> 0 | I16: =IF(OR($A16<Param.SonstigRegelmJahrBeginn6,$A16>Param.SonstigRegelmJahrEnd6),0,Param.SonstigRegelmBetragJaehrl6*(1+Param.SonstigRegelmSteig6)^($A16-Param.SonstigRegelmJahrBeginn6)) -> 0 | J16: =IF(OR($A16<Param.SonstigRegelmJahrBeginn7,$A16>Param.SonstigRegelmJahrEnd7),0,Param.SonstigRegelmBetragJaehrl7*(1+Param.SonstigRegelmSteig7)^($A16-Param.SonstigRegelmJahrBeginn7)) -> 0 | K16: =IF(OR($A16<Param.SonstigRegelmJahrBeginn8,$A16>Param.SonstigRegelmJahrEnd8),0,Param.SonstigRegelmBetragJaehrl8*(1+Param.SonstigRegelmSteig8)^($A16-Param.SonstigRegelmJahrBeginn8)) -> 0 | L16: =IF(OR($A16<Param.SonstigRegelmJahrBeginn9,$A16>Param.SonstigRegelmJahrEnd9),0,Param.SonstigRegelmBetragJaehrl9*(1+Param.SonstigRegelmSteig9)^($A16-Param.SonstigRegelmJahrBeginn9)) -> 0 | M16: =IF(OR($A16<Param.SonstigRegelmJahrBeginn10,$A16>Param.SonstigRegelmJahrEnd10),0,Param.SonstigRegelmBetragJaehrl10*(1+Param.SonstigRegelmSteig10)^($A16-Param.SonstigRegelmJahrBeginn10)) -> 0 | N16: =MAX(0,C16-SUM(D16:M16)) -> 0 | O16: =IF(N16<=0,SUM(D16:M16)-C16,0) -> 3937.267 | P16: =S16+AP16 -> 710233.32 | Q16: =IF(P16>0,S16/P16,0) -> 0.79002345 | R16: =IF(P16>0,AP16/P16,0) -> 0.20997655 | S16: =AL15 -> 561100.98 | T16: =AM15 -> 317600.98 | U16: =IF(A16<Param.FireStartjahr,Param.SparrateDepotMonatl*12*(1+Param.SparrateDynamikJaehrl)^($A16-Param.Startjahr),0) -> 6000 | V16: =IF(AND(Param.SonstigEinmaligKonto1="Depot",$A16=Param.SonstigEinmaligJahr1),Param.SonstigEinmaligBetrag1,0) -> 0 | W16: =IF(AND(Param.SonstigEinmaligKonto2="Depot",$A16=Param.SonstigEinmaligJahr2),Param.SonstigEinmaligBetrag2,0) -> 0 | X16: =IF(AND(Param.SonstigEinmaligKonto3="Depot",$A16=Param.SonstigEinmaligJahr3),Param.SonstigEinmaligBetrag3,0) -> 0 | Y16: =IF(AND(Param.SonstigEinmaligKonto4="Depot",$A16=Param.SonstigEinmaligJahr4),Param.SonstigEinmaligBetrag4,0) -> 0 | Z16: =IF(AND(Param.SonstigEinmaligKonto5="Depot",$A16=Param.SonstigEinmaligJahr5),Param.SonstigEinmaligBetrag5,0) -> 0 | AA16: =IF(AND(Param.SonstigEinmaligKonto6="Depot",$A16=Param.SonstigEinmaligJahr6),Param.SonstigEinmaligBetrag6,0) -> 0 | AB16: =IF(AND(Param.SonstigEinmaligKonto7="Depot",$A16=Param.SonstigEinmaligJahr7),Param.SonstigEinmaligBetrag7,0) -> 0 | AC16: =IF(AND(Param.SonstigEinmaligKonto8="Depot",$A16=Param.SonstigEinmaligJahr8),Param.SonstigEinmaligBetrag8,0) -> 0 | AD16: =IF(AND(Param.SonstigEinmaligKonto9="Depot",$A16=Param.SonstigEinmaligJahr9),Param.SonstigEinmaligBetrag9,0) -> 0 | AE16: =IF(AND(Param.SonstigEinmaligKonto10="Depot",$A16=Param.SonstigEinmaligJahr10),Param.SonstigEinmaligBetrag10,0) -> 0 | AF16: =Param.SparerPauschbetrag-BF16 -> 0 | AG16: =IF(AND(A16>=Param.FireStartjahr,S16>0),MIN(N16*Q16,S16),0) -> 0 | AH16: =IF(AG16<=0,0,IF(S16<=0,0,AG16/(1-MAX(0,((T16/S16)*(1-Param.Teilfreistellung)-MIN(AF16,AG16)/AG16)*Param.KapSt)))) -> 0 | AI16: =AH16-AG16 -> 0 | AJ16: =T16-AH16*(T16/S16) -> 317600.98 | AK16: =S16-AH16 -> 561100.98 | AL16: =FV(AO16,12,-(U16/12),-AK16,0) -> 600930.3 | AM16: =AJ16+AL16-AK16-U16 -> 351430.3 | AN16: =AM16/AL16 -> 0.58481042 | AO16: =(1+IF(AND(A16>=Param.DepotRenditeSpezBeginn1,A16<=Param.DepotRenditeSpezEnde1),Param.DepotRenditeSpezProz1,IF(AND(A16>=Param.DepotRenditeSpezBeginn2,A16<=Param.DepotRenditeSpezEnde2),Param.DepotRenditeSpezProz2,IF(AND(A16>=Param.DepotRenditeSpezBeginn3,A16<=Param.DepotRenditeSpezEnde3),Param.DepotRenditeSpezProz3,IF(AND(A16>=Param.DepotRenditeSpezBeginn4,A16<=Param.DepotRenditeSpezEnde4),Param.DepotRenditeSpezProz4,IF(AND(A16>=Param.DepotRenditeSpezBeginn5,A16<=Param.DepotRenditeSpezEnde5),Param.DepotRenditeSpezProz5,Param.DepotRenditeDefault))))))^(1/12)-1 -> 0.0048675506 | AP16: =BJ15 -> 149132.34 | AQ16: =IF(A16<Param.FireStartjahr,Param.SparrateFestgeldMonatl*12*(1+Param.SparrateDynamikJaehrl)^($A16-Param.Startjahr),0) -> 1800 | AR16: =O16 -> 3937.267 | AS16: =IF(AND(Param.SonstigEinmaligKonto1="Festgeld",$A16=Param.SonstigEinmaligJahr1),Param.SonstigEinmaligBetrag1,0) -> 0 | AT16: =IF(AND(Param.SonstigEinmaligKonto2="Festgeld",$A16=Param.SonstigEinmaligJahr2),Param.SonstigEinmaligBetrag2,0) -> 0 | AU16: =IF(AND(Param.SonstigEinmaligKonto3="Festgeld",$A16=Param.SonstigEinmaligJahr3),Param.SonstigEinmaligBetrag3,0) -> 0 | AV16: =IF(AND(Param.SonstigEinmaligKonto4="Festgeld",$A16=Param.SonstigEinmaligJahr4),Param.SonstigEinmaligBetrag4,0) -> 0 | AW16: =IF(AND(Param.SonstigEinmaligKonto5="Festgeld",$A16=Param.SonstigEinmaligJahr5),Param.SonstigEinmaligBetrag5,0) -> 0 | AX16: =IF(AND(Param.SonstigEinmaligKonto6="Festgeld",$A16=Param.SonstigEinmaligJahr6),Param.SonstigEinmaligBetrag6,0) -> 0 | AY16: =IF(AND(Param.SonstigEinmaligKonto7="Festgeld",$A16=Param.SonstigEinmaligJahr7),Param.SonstigEinmaligBetrag7,0) -> 0 | AZ16: =IF(AND(Param.SonstigEinmaligKonto8="Festgeld",$A16=Param.SonstigEinmaligJahr8),Param.SonstigEinmaligBetrag8,0) -> 0 | BA16: =IF(AND(Param.SonstigEinmaligKonto9="Festgeld",$A16=Param.SonstigEinmaligJahr9),Param.SonstigEinmaligBetrag9,0) -> 0 | BB16: =IF(AND(Param.SonstigEinmaligKonto10="Festgeld",$A16=Param.SonstigEinmaligJahr10),Param.SonstigEinmaligBetrag10,0) -> 0 | BC16: =IF(AND(A16>=Param.FireStartjahr,AP16>0),MIN(N16*R16,AP16),0) -> 0 | BD16: =Param.FestgeldZinssatz -> 0.02 | BE16: =(AP16+AQ16-BC16)*BD16 -> 3018.6468 | BF16: =IF(BE16>Param.SparerPauschbetrag,Param.SparerPauschbetrag,BE16) -> 1000 | BG16: =BE16-BF16 -> 2018.6468 | BH16: =BG16*Param.KapSt -> 532.41809 | BI16: =BE16-BH16 -> 2486.2287 | BJ16: =AP16+SUM(AQ16:BB16)-BC16+BI16 -> 157355.83 | BK16: =AL16+BJ16 -> 758286.14 | BL16: =BK16/(1+Param.Inflationsrate)^(A16-Param.Startjahr) -> 577923.82 | BM16: =IF(BK16<N16,A16,"") | BN16: =AH16+BC16 -> 0 | BO16: =SUM(AR16:BB16) -> 3937.267 | BP16: =BN16+(-1*BO16) -> -3937.267 | BQ16: =AI16+BH16 -> 532.41809 | BR16: =IF(BK16>0,BP16/BK16,0) -> -0.0051923236
A17: =A16+1 -> 2038 | B17: =B5+(13-1) -> 42 | C17: =IF(A17<Param.FireStartjahr,0,Param.EntnahmeBetragStart*(1+Param.Inflationsrate)^(A17-Param.Startjahr)) -> 0 | D17: =IF(OR($A17<Param.SonstigRegelmJahrBeginn1,$A17>Param.SonstigRegelmJahrEnd1),0,Param.SonstigRegelmBetragJaehrl1*(1+Param.SonstigRegelmSteig1)^(A17-Param.SonstigRegelmJahrBeginn1)) -> 0 | E17: =IF(OR($A17<Param.SonstigRegelmJahrBeginn2,$A17>Param.SonstigRegelmJahrEnd2),0,Param.SonstigRegelmBetragJaehrl2*(1+Param.SonstigRegelmSteig2)^($A17-Param.SonstigRegelmJahrBeginn2)) -> 0 | F17: =IF(OR($A17<Param.SonstigRegelmJahrBeginn3,$A17>Param.SonstigRegelmJahrEnd3),0,Param.SonstigRegelmBetragJaehrl3*(1+Param.SonstigRegelmSteig3)^($A17-Param.SonstigRegelmJahrBeginn3)) -> 3976.6397 | G17: =IF(OR($A17<Param.SonstigRegelmJahrBeginn4,$A17>Param.SonstigRegelmJahrEnd4),0,Param.SonstigRegelmBetragJaehrl4*(1+Param.SonstigRegelmSteig4)^($A17-Param.SonstigRegelmJahrBeginn4)) -> 0 | H17: =IF(OR($A17<Param.SonstigRegelmJahrBeginn5,$A17>Param.SonstigRegelmJahrEnd5),0,Param.SonstigRegelmBetragJaehrl5*(1+Param.SonstigRegelmSteig5)^($A17-Param.SonstigRegelmJahrBeginn5)) -> 0 | I17: =IF(OR($A17<Param.SonstigRegelmJahrBeginn6,$A17>Param.SonstigRegelmJahrEnd6),0,Param.SonstigRegelmBetragJaehrl6*(1+Param.SonstigRegelmSteig6)^($A17-Param.SonstigRegelmJahrBeginn6)) -> 0 | J17: =IF(OR($A17<Param.SonstigRegelmJahrBeginn7,$A17>Param.SonstigRegelmJahrEnd7),0,Param.SonstigRegelmBetragJaehrl7*(1+Param.SonstigRegelmSteig7)^($A17-Param.SonstigRegelmJahrBeginn7)) -> 0 | K17: =IF(OR($A17<Param.SonstigRegelmJahrBeginn8,$A17>Param.SonstigRegelmJahrEnd8),0,Param.SonstigRegelmBetragJaehrl8*(1+Param.SonstigRegelmSteig8)^($A17-Param.SonstigRegelmJahrBeginn8)) -> 0 | L17: =IF(OR($A17<Param.SonstigRegelmJahrBeginn9,$A17>Param.SonstigRegelmJahrEnd9),0,Param.SonstigRegelmBetragJaehrl9*(1+Param.SonstigRegelmSteig9)^($A17-Param.SonstigRegelmJahrBeginn9)) -> 0 | M17: =IF(OR($A17<Param.SonstigRegelmJahrBeginn10,$A17>Param.SonstigRegelmJahrEnd10),0,Param.SonstigRegelmBetragJaehrl10*(1+Param.SonstigRegelmSteig10)^($A17-Param.SonstigRegelmJahrBeginn10)) -> 0 | N17: =MAX(0,C17-SUM(D17:M17)) -> 0 | O17: =IF(N17<=0,SUM(D17:M17)-C17,0) -> 3976.6397 | P17: =S17+AP17 -> 758286.14 | Q17: =IF(P17>0,S17/P17,0) -> 0.79248489 | R17: =IF(P17>0,AP17/P17,0) -> 0.20751511 | S17: =AL16 -> 600930.3 | T17: =AM16 -> 351430.3 | U17: =IF(A17<Param.FireStartjahr,Param.SparrateDepotMonatl*12*(1+Param.SparrateDynamikJaehrl)^($A17-Param.Startjahr),0) -> 6000 | V17: =IF(AND(Param.SonstigEinmaligKonto1="Depot",$A17=Param.SonstigEinmaligJahr1),Param.SonstigEinmaligBetrag1,0) -> 0 | W17: =IF(AND(Param.SonstigEinmaligKonto2="Depot",$A17=Param.SonstigEinmaligJahr2),Param.SonstigEinmaligBetrag2,0) -> 0 | X17: =IF(AND(Param.SonstigEinmaligKonto3="Depot",$A17=Param.SonstigEinmaligJahr3),Param.SonstigEinmaligBetrag3,0) -> 0 | Y17: =IF(AND(Param.SonstigEinmaligKonto4="Depot",$A17=Param.SonstigEinmaligJahr4),Param.SonstigEinmaligBetrag4,0) -> 0 | Z17: =IF(AND(Param.SonstigEinmaligKonto5="Depot",$A17=Param.SonstigEinmaligJahr5),Param.SonstigEinmaligBetrag5,0) -> 0 | AA17: =IF(AND(Param.SonstigEinmaligKonto6="Depot",$A17=Param.SonstigEinmaligJahr6),Param.SonstigEinmaligBetrag6,0) -> 0 | AB17: =IF(AND(Param.SonstigEinmaligKonto7="Depot",$A17=Param.SonstigEinmaligJahr7),Param.SonstigEinmaligBetrag7,0) -> 0 | AC17: =IF(AND(Param.SonstigEinmaligKonto8="Depot",$A17=Param.SonstigEinmaligJahr8),Param.SonstigEinmaligBetrag8,0) -> 0 | AD17: =IF(AND(Param.SonstigEinmaligKonto9="Depot",$A17=Param.SonstigEinmaligJahr9),Param.SonstigEinmaligBetrag9,0) -> 0 | AE17: =IF(AND(Param.SonstigEinmaligKonto10="Depot",$A17=Param.SonstigEinmaligJahr10),Param.SonstigEinmaligBetrag10,0) -> 0 | AF17: =Param.SparerPauschbetrag-BF17 -> 0 | AG17: =IF(AND(A17>=Param.FireStartjahr,S17>0),MIN(N17*Q17,S17),0) -> 0 | AH17: =IF(AG17<=0,0,IF(S17<=0,0,AG17/(1-MAX(0,((T17/S17)*(1-Param.Teilfreistellung)-MIN(AF17,AG17)/AG17)*Param.KapSt)))) -> 0 | AI17: =AH17-AG17 -> 0 | AJ17: =T17-AH17*(T17/S17) -> 351430.3 | AK17: =S17-AH17 -> 600930.3 | AL17: =FV(AO17,12,-(U17/12),-AK17,0) -> 643149.38 | AM17: =AJ17+AL17-AK17-U17 -> 387649.38 | AN17: =AM17/AL17 -> 0.60273615 | AO17: =(1+IF(AND(A17>=Param.DepotRenditeSpezBeginn1,A17<=Param.DepotRenditeSpezEnde1),Param.DepotRenditeSpezProz1,IF(AND(A17>=Param.DepotRenditeSpezBeginn2,A17<=Param.DepotRenditeSpezEnde2),Param.DepotRenditeSpezProz2,IF(AND(A17>=Param.DepotRenditeSpezBeginn3,A17<=Param.DepotRenditeSpezEnde3),Param.DepotRenditeSpezProz3,IF(AND(A17>=Param.DepotRenditeSpezBeginn4,A17<=Param.DepotRenditeSpezEnde4),Param.DepotRenditeSpezProz4,IF(AND(A17>=Param.DepotRenditeSpezBeginn5,A17<=Param.DepotRenditeSpezEnde5),Param.DepotRenditeSpezProz5,Param.DepotRenditeDefault))))))^(1/12)-1 -> 0.0048675506 | AP17: =BJ16 -> 157355.83 | AQ17: =IF(A17<Param.FireStartjahr,Param.SparrateFestgeldMonatl*12*(1+Param.SparrateDynamikJaehrl)^($A17-Param.Startjahr),0) -> 1800 | AR17: =O17 -> 3976.6397 | AS17: =IF(AND(Param.SonstigEinmaligKonto1="Festgeld",$A17=Param.SonstigEinmaligJahr1),Param.SonstigEinmaligBetrag1,0) -> 0 | AT17: =IF(AND(Param.SonstigEinmaligKonto2="Festgeld",$A17=Param.SonstigEinmaligJahr2),Param.SonstigEinmaligBetrag2,0) -> 0 | AU17: =IF(AND(Param.SonstigEinmaligKonto3="Festgeld",$A17=Param.SonstigEinmaligJahr3),Param.SonstigEinmaligBetrag3,0) -> 0 | AV17: =IF(AND(Param.SonstigEinmaligKonto4="Festgeld",$A17=Param.SonstigEinmaligJahr4),Param.SonstigEinmaligBetrag4,0) -> 0 | AW17: =IF(AND(Param.SonstigEinmaligKonto5="Festgeld",$A17=Param.SonstigEinmaligJahr5),Param.SonstigEinmaligBetrag5,0) -> 0 | AX17: =IF(AND(Param.SonstigEinmaligKonto6="Festgeld",$A17=Param.SonstigEinmaligJahr6),Param.SonstigEinmaligBetrag6,0) -> 0 | AY17: =IF(AND(Param.SonstigEinmaligKonto7="Festgeld",$A17=Param.SonstigEinmaligJahr7),Param.SonstigEinmaligBetrag7,0) -> 0 | AZ17: =IF(AND(Param.SonstigEinmaligKonto8="Festgeld",$A17=Param.SonstigEinmaligJahr8),Param.SonstigEinmaligBetrag8,0) -> 0 | BA17: =IF(AND(Param.SonstigEinmaligKonto9="Festgeld",$A17=Param.SonstigEinmaligJahr9),Param.SonstigEinmaligBetrag9,0) -> 0 | BB17: =IF(AND(Param.SonstigEinmaligKonto10="Festgeld",$A17=Param.SonstigEinmaligJahr10),Param.SonstigEinmaligBetrag10,0) -> 0 | BC17: =IF(AND(A17>=Param.FireStartjahr,AP17>0),MIN(N17*R17,AP17),0) -> 0 | BD17: =Param.FestgeldZinssatz -> 0.02 | BE17: =(AP17+AQ17-BC17)*BD17 -> 3183.1167 | BF17: =IF(BE17>Param.SparerPauschbetrag,Param.SparerPauschbetrag,BE17) -> 1000 | BG17: =BE17-BF17 -> 2183.1167 | BH17: =BG17*Param.KapSt -> 575.79703 | BI17: =BE17-BH17 -> 2607.3197 | BJ17: =AP17+SUM(AQ17:BB17)-BC17+BI17 -> 165739.79 | BK17: =AL17+BJ17 -> 808889.18 | BL17: =BK17/(1+Param.Inflationsrate)^(A17-Param.Startjahr) -> 601454.31 | BM17: =IF(BK17<N17,A17,"") | BN17: =AH17+BC17 -> 0 | BO17: =SUM(AR17:BB17) -> 3976.6397 | BP17: =BN17+(-1*BO17) -> -3976.6397 | BQ17: =AI17+BH17 -> 575.79703 | BR17: =IF(BK17>0,BP17/BK17,0) -> -0.0049161736
A18: =A17+1 -> 2039 | B18: =B5+(14-1) -> 43 | C18: =IF(A18<Param.FireStartjahr,0,Param.EntnahmeBetragStart*(1+Param.Inflationsrate)^(A18-Param.Startjahr)) -> 0 | D18: =IF(OR($A18<Param.SonstigRegelmJahrBeginn1,$A18>Param.SonstigRegelmJahrEnd1),0,Param.SonstigRegelmBetragJaehrl1*(1+Param.SonstigRegelmSteig1)^(A18-Param.SonstigRegelmJahrBeginn1)) -> 0 | E18: =IF(OR($A18<Param.SonstigRegelmJahrBeginn2,$A18>Param.SonstigRegelmJahrEnd2),0,Param.SonstigRegelmBetragJaehrl2*(1+Param.SonstigRegelmSteig2)^($A18-Param.SonstigRegelmJahrBeginn2)) -> 0 | F18: =IF(OR($A18<Param.SonstigRegelmJahrBeginn3,$A18>Param.SonstigRegelmJahrEnd3),0,Param.SonstigRegelmBetragJaehrl3*(1+Param.SonstigRegelmSteig3)^($A18-Param.SonstigRegelmJahrBeginn3)) -> 4016.406 | G18: =IF(OR($A18<Param.SonstigRegelmJahrBeginn4,$A18>Param.SonstigRegelmJahrEnd4),0,Param.SonstigRegelmBetragJaehrl4*(1+Param.SonstigRegelmSteig4)^($A18-Param.SonstigRegelmJahrBeginn4)) -> 0 | H18: =IF(OR($A18<Param.SonstigRegelmJahrBeginn5,$A18>Param.SonstigRegelmJahrEnd5),0,Param.SonstigRegelmBetragJaehrl5*(1+Param.SonstigRegelmSteig5)^($A18-Param.SonstigRegelmJahrBeginn5)) -> 0 | I18: =IF(OR($A18<Param.SonstigRegelmJahrBeginn6,$A18>Param.SonstigRegelmJahrEnd6),0,Param.SonstigRegelmBetragJaehrl6*(1+Param.SonstigRegelmSteig6)^($A18-Param.SonstigRegelmJahrBeginn6)) -> 0 | J18: =IF(OR($A18<Param.SonstigRegelmJahrBeginn7,$A18>Param.SonstigRegelmJahrEnd7),0,Param.SonstigRegelmBetragJaehrl7*(1+Param.SonstigRegelmSteig7)^($A18-Param.SonstigRegelmJahrBeginn7)) -> 0 | K18: =IF(OR($A18<Param.SonstigRegelmJahrBeginn8,$A18>Param.SonstigRegelmJahrEnd8),0,Param.SonstigRegelmBetragJaehrl8*(1+Param.SonstigRegelmSteig8)^($A18-Param.SonstigRegelmJahrBeginn8)) -> 0 | L18: =IF(OR($A18<Param.SonstigRegelmJahrBeginn9,$A18>Param.SonstigRegelmJahrEnd9),0,Param.SonstigRegelmBetragJaehrl9*(1+Param.SonstigRegelmSteig9)^($A18-Param.SonstigRegelmJahrBeginn9)) -> 0 | M18: =IF(OR($A18<Param.SonstigRegelmJahrBeginn10,$A18>Param.SonstigRegelmJahrEnd10),0,Param.SonstigRegelmBetragJaehrl10*(1+Param.SonstigRegelmSteig10)^($A18-Param.SonstigRegelmJahrBeginn10)) -> 0 | N18: =MAX(0,C18-SUM(D18:M18)) -> 0 | O18: =IF(N18<=0,SUM(D18:M18)-C18,0) -> 4016.406 | P18: =S18+AP18 -> 808889.18 | Q18: =IF(P18>0,S18/P18,0) -> 0.79510198 | R18: =IF(P18>0,AP18/P18,0) -> 0.20489802 | S18: =AL17 -> 643149.38 | T18: =AM17 -> 387649.38 | U18: =IF(A18<Param.FireStartjahr,Param.SparrateDepotMonatl*12*(1+Param.SparrateDynamikJaehrl)^($A18-Param.Startjahr),0) -> 6000 | V18: =IF(AND(Param.SonstigEinmaligKonto1="Depot",$A18=Param.SonstigEinmaligJahr1),Param.SonstigEinmaligBetrag1,0) -> 0 | W18: =IF(AND(Param.SonstigEinmaligKonto2="Depot",$A18=Param.SonstigEinmaligJahr2),Param.SonstigEinmaligBetrag2,0) -> 0 | X18: =IF(AND(Param.SonstigEinmaligKonto3="Depot",$A18=Param.SonstigEinmaligJahr3),Param.SonstigEinmaligBetrag3,0) -> 0 | Y18: =IF(AND(Param.SonstigEinmaligKonto4="Depot",$A18=Param.SonstigEinmaligJahr4),Param.SonstigEinmaligBetrag4,0) -> 0 | Z18: =IF(AND(Param.SonstigEinmaligKonto5="Depot",$A18=Param.SonstigEinmaligJahr5),Param.SonstigEinmaligBetrag5,0) -> 0 | AA18: =IF(AND(Param.SonstigEinmaligKonto6="Depot",$A18=Param.SonstigEinmaligJahr6),Param.SonstigEinmaligBetrag6,0) -> 0 | AB18: =IF(AND(Param.SonstigEinmaligKonto7="Depot",$A18=Param.SonstigEinmaligJahr7),Param.SonstigEinmaligBetrag7,0) -> 0 | AC18: =IF(AND(Param.SonstigEinmaligKonto8="Depot",$A18=Param.SonstigEinmaligJahr8),Param.SonstigEinmaligBetrag8,0) -> 0 | AD18: =IF(AND(Param.SonstigEinmaligKonto9="Depot",$A18=Param.SonstigEinmaligJahr9),Param.SonstigEinmaligBetrag9,0) -> 0 | AE18: =IF(AND(Param.SonstigEinmaligKonto10="Depot",$A18=Param.SonstigEinmaligJahr10),Param.SonstigEinmaligBetrag10,0) -> 0 | AF18: =Param.SparerPauschbetrag-BF18 -> 0 | AG18: =IF(AND(A18>=Param.FireStartjahr,S18>0),MIN(N18*Q18,S18),0) -> 0 | AH18: =IF(AG18<=0,0,IF(S18<=0,0,AG18/(1-MAX(0,((T18/S18)*(1-Param.Teilfreistellung)-MIN(AF18,AG18)/AG18)*Param.KapSt)))) -> 0 | AI18: =AH18-AG18 -> 0 | AJ18: =T18-AH18*(T18/S18) -> 387649.38 | AK18: =S18-AH18 -> 643149.38 | AL18: =FV(AO18,12,-(U18/12),-AK18,0) -> 687901.61 | AM18: =AJ18+AL18-AK18-U18 -> 426401.61 | AN18: =AM18/AL18 -> 0.61985843 | AO18: =(1+IF(AND(A18>=Param.DepotRenditeSpezBeginn1,A18<=Param.DepotRenditeSpezEnde1),Param.DepotRenditeSpezProz1,IF(AND(A18>=Param.DepotRenditeSpezBeginn2,A18<=Param.DepotRenditeSpezEnde2),Param.DepotRenditeSpezProz2,IF(AND(A18>=Param.DepotRenditeSpezBeginn3,A18<=Param.DepotRenditeSpezEnde3),Param.DepotRenditeSpezProz3,IF(AND(A18>=Param.DepotRenditeSpezBeginn4,A18<=Param.DepotRenditeSpezEnde4),Param.DepotRenditeSpezProz4,IF(AND(A18>=Param.DepotRenditeSpezBeginn5,A18<=Param.DepotRenditeSpezEnde5),Param.DepotRenditeSpezProz5,Param.DepotRenditeDefault))))))^(1/12)-1 -> 0.0048675506 | AP18: =BJ17 -> 165739.79 | AQ18: =IF(A18<Param.FireStartjahr,Param.SparrateFestgeldMonatl*12*(1+Param.SparrateDynamikJaehrl)^($A18-Param.Startjahr),0) -> 1800 | AR18: =O18 -> 4016.406 | AS18: =IF(AND(Param.SonstigEinmaligKonto1="Festgeld",$A18=Param.SonstigEinmaligJahr1),Param.SonstigEinmaligBetrag1,0) -> 0 | AT18: =IF(AND(Param.SonstigEinmaligKonto2="Festgeld",$A18=Param.SonstigEinmaligJahr2),Param.SonstigEinmaligBetrag2,0) -> 0 | AU18: =IF(AND(Param.SonstigEinmaligKonto3="Festgeld",$A18=Param.SonstigEinmaligJahr3),Param.SonstigEinmaligBetrag3,0) -> 0 | AV18: =IF(AND(Param.SonstigEinmaligKonto4="Festgeld",$A18=Param.SonstigEinmaligJahr4),Param.SonstigEinmaligBetrag4,0) -> 0 | AW18: =IF(AND(Param.SonstigEinmaligKonto5="Festgeld",$A18=Param.SonstigEinmaligJahr5),Param.SonstigEinmaligBetrag5,0) -> 0 | AX18: =IF(AND(Param.SonstigEinmaligKonto6="Festgeld",$A18=Param.SonstigEinmaligJahr6),Param.SonstigEinmaligBetrag6,0) -> 0 | AY18: =IF(AND(Param.SonstigEinmaligKonto7="Festgeld",$A18=Param.SonstigEinmaligJahr7),Param.SonstigEinmaligBetrag7,0) -> 0 | AZ18: =IF(AND(Param.SonstigEinmaligKonto8="Festgeld",$A18=Param.SonstigEinmaligJahr8),Param.SonstigEinmaligBetrag8,0) -> 0 | BA18: =IF(AND(Param.SonstigEinmaligKonto9="Festgeld",$A18=Param.SonstigEinmaligJahr9),Param.SonstigEinmaligBetrag9,0) -> 0 | BB18: =IF(AND(Param.SonstigEinmaligKonto10="Festgeld",$A18=Param.SonstigEinmaligJahr10),Param.SonstigEinmaligBetrag10,0) -> 0 | BC18: =IF(AND(A18>=Param.FireStartjahr,AP18>0),MIN(N18*R18,AP18),0) -> 0 | BD18: =Param.FestgeldZinssatz -> 0.02 | BE18: =(AP18+AQ18-BC18)*BD18 -> 3350.7959 | BF18: =IF(BE18>Param.SparerPauschbetrag,Param.SparerPauschbetrag,BE18) -> 1000 | BG18: =BE18-BF18 -> 2350.7959 | BH18: =BG18*Param.KapSt -> 620.02241 | BI18: =BE18-BH18 -> 2730.7735 | BJ18: =AP18+SUM(AQ18:BB18)-BC18+BI18 -> 174286.97 | BK18: =AL18+BJ18 -> 862188.58 | BL18: =BK18/(1+Param.Inflationsrate)^(A18-Param.Startjahr) -> 625449.17 | BM18: =IF(BK18<N18,A18,"") | BN18: =AH18+BC18 -> 0 | BO18: =SUM(AR18:BB18) -> 4016.406 | BP18: =BN18+(-1*BO18) -> -4016.406 | BQ18: =AI18+BH18 -> 620.02241 | BR18: =IF(BK18>0,BP18/BK18,0) -> -0.0046583846
A19: =A18+1 -> 2040 | B19: =B5+(15-1) -> 44 | C19: =IF(A19<Param.FireStartjahr,0,Param.EntnahmeBetragStart*(1+Param.Inflationsrate)^(A19-Param.Startjahr)) -> 0 | D19: =IF(OR($A19<Param.SonstigRegelmJahrBeginn1,$A19>Param.SonstigRegelmJahrEnd1),0,Param.SonstigRegelmBetragJaehrl1*(1+Param.SonstigRegelmSteig1)^(A19-Param.SonstigRegelmJahrBeginn1)) -> 0 | E19: =IF(OR($A19<Param.SonstigRegelmJahrBeginn2,$A19>Param.SonstigRegelmJahrEnd2),0,Param.SonstigRegelmBetragJaehrl2*(1+Param.SonstigRegelmSteig2)^($A19-Param.SonstigRegelmJahrBeginn2)) -> 0 | F19: =IF(OR($A19<Param.SonstigRegelmJahrBeginn3,$A19>Param.SonstigRegelmJahrEnd3),0,Param.SonstigRegelmBetragJaehrl3*(1+Param.SonstigRegelmSteig3)^($A19-Param.SonstigRegelmJahrBeginn3)) -> 0 | G19: =IF(OR($A19<Param.SonstigRegelmJahrBeginn4,$A19>Param.SonstigRegelmJahrEnd4),0,Param.SonstigRegelmBetragJaehrl4*(1+Param.SonstigRegelmSteig4)^($A19-Param.SonstigRegelmJahrBeginn4)) -> 0 | H19: =IF(OR($A19<Param.SonstigRegelmJahrBeginn5,$A19>Param.SonstigRegelmJahrEnd5),0,Param.SonstigRegelmBetragJaehrl5*(1+Param.SonstigRegelmSteig5)^($A19-Param.SonstigRegelmJahrBeginn5)) -> 0 | I19: =IF(OR($A19<Param.SonstigRegelmJahrBeginn6,$A19>Param.SonstigRegelmJahrEnd6),0,Param.SonstigRegelmBetragJaehrl6*(1+Param.SonstigRegelmSteig6)^($A19-Param.SonstigRegelmJahrBeginn6)) -> 0 | J19: =IF(OR($A19<Param.SonstigRegelmJahrBeginn7,$A19>Param.SonstigRegelmJahrEnd7),0,Param.SonstigRegelmBetragJaehrl7*(1+Param.SonstigRegelmSteig7)^($A19-Param.SonstigRegelmJahrBeginn7)) -> 0 | K19: =IF(OR($A19<Param.SonstigRegelmJahrBeginn8,$A19>Param.SonstigRegelmJahrEnd8),0,Param.SonstigRegelmBetragJaehrl8*(1+Param.SonstigRegelmSteig8)^($A19-Param.SonstigRegelmJahrBeginn8)) -> 0 | L19: =IF(OR($A19<Param.SonstigRegelmJahrBeginn9,$A19>Param.SonstigRegelmJahrEnd9),0,Param.SonstigRegelmBetragJaehrl9*(1+Param.SonstigRegelmSteig9)^($A19-Param.SonstigRegelmJahrBeginn9)) -> 0 | M19: =IF(OR($A19<Param.SonstigRegelmJahrBeginn10,$A19>Param.SonstigRegelmJahrEnd10),0,Param.SonstigRegelmBetragJaehrl10*(1+Param.SonstigRegelmSteig10)^($A19-Param.SonstigRegelmJahrBeginn10)) -> 0 | N19: =MAX(0,C19-SUM(D19:M19)) -> 0 | O19: =IF(N19<=0,SUM(D19:M19)-C19,0) -> 0 | P19: =S19+AP19 -> 862188.58 | Q19: =IF(P19>0,S19/P19,0) -> 0.79785516 | R19: =IF(P19>0,AP19/P19,0) -> 0.20214484 | S19: =AL18 -> 687901.61 | T19: =AM18 -> 426401.61 | U19: =IF(A19<Param.FireStartjahr,Param.SparrateDepotMonatl*12*(1+Param.SparrateDynamikJaehrl)^($A19-Param.Startjahr),0) -> 6000 | V19: =IF(AND(Param.SonstigEinmaligKonto1="Depot",$A19=Param.SonstigEinmaligJahr1),Param.SonstigEinmaligBetrag1,0) -> 0 | W19: =IF(AND(Param.SonstigEinmaligKonto2="Depot",$A19=Param.SonstigEinmaligJahr2),Param.SonstigEinmaligBetrag2,0) -> 0 | X19: =IF(AND(Param.SonstigEinmaligKonto3="Depot",$A19=Param.SonstigEinmaligJahr3),Param.SonstigEinmaligBetrag3,0) -> 0 | Y19: =IF(AND(Param.SonstigEinmaligKonto4="Depot",$A19=Param.SonstigEinmaligJahr4),Param.SonstigEinmaligBetrag4,0) -> 0 | Z19: =IF(AND(Param.SonstigEinmaligKonto5="Depot",$A19=Param.SonstigEinmaligJahr5),Param.SonstigEinmaligBetrag5,0) -> 0 | AA19: =IF(AND(Param.SonstigEinmaligKonto6="Depot",$A19=Param.SonstigEinmaligJahr6),Param.SonstigEinmaligBetrag6,0) -> 0 | AB19: =IF(AND(Param.SonstigEinmaligKonto7="Depot",$A19=Param.SonstigEinmaligJahr7),Param.SonstigEinmaligBetrag7,0) -> 0 | AC19: =IF(AND(Param.SonstigEinmaligKonto8="Depot",$A19=Param.SonstigEinmaligJahr8),Param.SonstigEinmaligBetrag8,0) -> 0 | AD19: =IF(AND(Param.SonstigEinmaligKonto9="Depot",$A19=Param.SonstigEinmaligJahr9),Param.SonstigEinmaligBetrag9,0) -> 0 | AE19: =IF(AND(Param.SonstigEinmaligKonto10="Depot",$A19=Param.SonstigEinmaligJahr10),Param.SonstigEinmaligBetrag10,0) -> 0 | AF19: =Param.SparerPauschbetrag-BF19 -> 0 | AG19: =IF(AND(A19>=Param.FireStartjahr,S19>0),MIN(N19*Q19,S19),0) -> 0 | AH19: =IF(AG19<=0,0,IF(S19<=0,0,AG19/(1-MAX(0,((T19/S19)*(1-Param.Teilfreistellung)-MIN(AF19,AG19)/AG19)*Param.KapSt)))) -> 0 | AI19: =AH19-AG19 -> 0 | AJ19: =T19-AH19*(T19/S19) -> 426401.61 | AK19: =S19-AH19 -> 687901.61 | AL19: =FV(AO19,12,-(U19/12),-AK19,0) -> 735338.97 | AM19: =AJ19+AL19-AK19-U19 -> 467838.97 | AN19: =AM19/AL19 -> 0.63622219 | AO19: =(1+IF(AND(A19>=Param.DepotRenditeSpezBeginn1,A19<=Param.DepotRenditeSpezEnde1),Param.DepotRenditeSpezProz1,IF(AND(A19>=Param.DepotRenditeSpezBeginn2,A19<=Param.DepotRenditeSpezEnde2),Param.DepotRenditeSpezProz2,IF(AND(A19>=Param.DepotRenditeSpezBeginn3,A19<=Param.DepotRenditeSpezEnde3),Param.DepotRenditeSpezProz3,IF(AND(A19>=Param.DepotRenditeSpezBeginn4,A19<=Param.DepotRenditeSpezEnde4),Param.DepotRenditeSpezProz4,IF(AND(A19>=Param.DepotRenditeSpezBeginn5,A19<=Param.DepotRenditeSpezEnde5),Param.DepotRenditeSpezProz5,Param.DepotRenditeDefault))))))^(1/12)-1 -> 0.0048675506 | AP19: =BJ18 -> 174286.97 | AQ19: =IF(A19<Param.FireStartjahr,Param.SparrateFestgeldMonatl*12*(1+Param.SparrateDynamikJaehrl)^($A19-Param.Startjahr),0) -> 1800 | AR19: =O19 -> 0 | AS19: =IF(AND(Param.SonstigEinmaligKonto1="Festgeld",$A19=Param.SonstigEinmaligJahr1),Param.SonstigEinmaligBetrag1,0) -> 0 | AT19: =IF(AND(Param.SonstigEinmaligKonto2="Festgeld",$A19=Param.SonstigEinmaligJahr2),Param.SonstigEinmaligBetrag2,0) -> 0 | AU19: =IF(AND(Param.SonstigEinmaligKonto3="Festgeld",$A19=Param.SonstigEinmaligJahr3),Param.SonstigEinmaligBetrag3,0) -> 100000 | AV19: =IF(AND(Param.SonstigEinmaligKonto4="Festgeld",$A19=Param.SonstigEinmaligJahr4),Param.SonstigEinmaligBetrag4,0) -> 0 | AW19: =IF(AND(Param.SonstigEinmaligKonto5="Festgeld",$A19=Param.SonstigEinmaligJahr5),Param.SonstigEinmaligBetrag5,0) -> 0 | AX19: =IF(AND(Param.SonstigEinmaligKonto6="Festgeld",$A19=Param.SonstigEinmaligJahr6),Param.SonstigEinmaligBetrag6,0) -> 0 | AY19: =IF(AND(Param.SonstigEinmaligKonto7="Festgeld",$A19=Param.SonstigEinmaligJahr7),Param.SonstigEinmaligBetrag7,0) -> 0 | AZ19: =IF(AND(Param.SonstigEinmaligKonto8="Festgeld",$A19=Param.SonstigEinmaligJahr8),Param.SonstigEinmaligBetrag8,0) -> 0 | BA19: =IF(AND(Param.SonstigEinmaligKonto9="Festgeld",$A19=Param.SonstigEinmaligJahr9),Param.SonstigEinmaligBetrag9,0) -> 0 | BB19: =IF(AND(Param.SonstigEinmaligKonto10="Festgeld",$A19=Param.SonstigEinmaligJahr10),Param.SonstigEinmaligBetrag10,0) -> 0 | BC19: =IF(AND(A19>=Param.FireStartjahr,AP19>0),MIN(N19*R19,AP19),0) -> 0 | BD19: =Param.FestgeldZinssatz -> 0.02 | BE19: =(AP19+AQ19-BC19)*BD19 -> 3521.7395 | BF19: =IF(BE19>Param.SparerPauschbetrag,Param.SparerPauschbetrag,BE19) -> 1000 | BG19: =BE19-BF19 -> 2521.7395 | BH19: =BG19*Param.KapSt -> 665.10878 | BI19: =BE19-BH19 -> 2856.6307 | BJ19: =AP19+SUM(AQ19:BB19)-BC19+BI19 -> 278943.6 | BK19: =AL19+BJ19 -> 1014282.6 | BL19: =BK19/(1+Param.Inflationsrate)^(A19-Param.Startjahr) -> 717835.36 | BM19: =IF(BK19<N19,A19,"") | BN19: =AH19+BC19 -> 0 | BO19: =SUM(AR19:BB19) -> 100000 | BP19: =BN19+(-1*BO19) -> -100000 | BQ19: =AI19+BH19 -> 665.10878 | BR19: =IF(BK19>0,BP19/BK19,0) -> -0.098591854
A20: =A19+1 -> 2041 | B20: =B5+(16-1) -> 45 | C20: =IF(A20<Param.FireStartjahr,0,Param.EntnahmeBetragStart*(1+Param.Inflationsrate)^(A20-Param.Startjahr)) -> 0 | D20: =IF(OR($A20<Param.SonstigRegelmJahrBeginn1,$A20>Param.SonstigRegelmJahrEnd1),0,Param.SonstigRegelmBetragJaehrl1*(1+Param.SonstigRegelmSteig1)^(A20-Param.SonstigRegelmJahrBeginn1)) -> 0 | E20: =IF(OR($A20<Param.SonstigRegelmJahrBeginn2,$A20>Param.SonstigRegelmJahrEnd2),0,Param.SonstigRegelmBetragJaehrl2*(1+Param.SonstigRegelmSteig2)^($A20-Param.SonstigRegelmJahrBeginn2)) -> 0 | F20: =IF(OR($A20<Param.SonstigRegelmJahrBeginn3,$A20>Param.SonstigRegelmJahrEnd3),0,Param.SonstigRegelmBetragJaehrl3*(1+Param.SonstigRegelmSteig3)^($A20-Param.SonstigRegelmJahrBeginn3)) -> 0 | G20: =IF(OR($A20<Param.SonstigRegelmJahrBeginn4,$A20>Param.SonstigRegelmJahrEnd4),0,Param.SonstigRegelmBetragJaehrl4*(1+Param.SonstigRegelmSteig4)^($A20-Param.SonstigRegelmJahrBeginn4)) -> 0 | H20: =IF(OR($A20<Param.SonstigRegelmJahrBeginn5,$A20>Param.SonstigRegelmJahrEnd5),0,Param.SonstigRegelmBetragJaehrl5*(1+Param.SonstigRegelmSteig5)^($A20-Param.SonstigRegelmJahrBeginn5)) -> 0 | I20: =IF(OR($A20<Param.SonstigRegelmJahrBeginn6,$A20>Param.SonstigRegelmJahrEnd6),0,Param.SonstigRegelmBetragJaehrl6*(1+Param.SonstigRegelmSteig6)^($A20-Param.SonstigRegelmJahrBeginn6)) -> 0 | J20: =IF(OR($A20<Param.SonstigRegelmJahrBeginn7,$A20>Param.SonstigRegelmJahrEnd7),0,Param.SonstigRegelmBetragJaehrl7*(1+Param.SonstigRegelmSteig7)^($A20-Param.SonstigRegelmJahrBeginn7)) -> 0 | K20: =IF(OR($A20<Param.SonstigRegelmJahrBeginn8,$A20>Param.SonstigRegelmJahrEnd8),0,Param.SonstigRegelmBetragJaehrl8*(1+Param.SonstigRegelmSteig8)^($A20-Param.SonstigRegelmJahrBeginn8)) -> 0 | L20: =IF(OR($A20<Param.SonstigRegelmJahrBeginn9,$A20>Param.SonstigRegelmJahrEnd9),0,Param.SonstigRegelmBetragJaehrl9*(1+Param.SonstigRegelmSteig9)^($A20-Param.SonstigRegelmJahrBeginn9)) -> 0 | M20: =IF(OR($A20<Param.SonstigRegelmJahrBeginn10,$A20>Param.SonstigRegelmJahrEnd10),0,Param.SonstigRegelmBetragJaehrl10*(1+Param.SonstigRegelmSteig10)^($A20-Param.SonstigRegelmJahrBeginn10)) -> 0 | N20: =MAX(0,C20-SUM(D20:M20)) -> 0 | O20: =IF(N20<=0,SUM(D20:M20)-C20,0) -> 0 | P20: =S20+AP20 -> 1014282.6 | Q20: =IF(P20>0,S20/P20,0) -> 0.72498433 | R20: =IF(P20>0,AP20/P20,0) -> 0.27501567 | S20: =AL19 -> 735338.97 | T20: =AM19 -> 467838.97 | U20: =IF(A20<Param.FireStartjahr,Param.SparrateDepotMonatl*12*(1+Param.SparrateDynamikJaehrl)^($A20-Param.Startjahr),0) -> 6000 | V20: =IF(AND(Param.SonstigEinmaligKonto1="Depot",$A20=Param.SonstigEinmaligJahr1),Param.SonstigEinmaligBetrag1,0) -> 0 | W20: =IF(AND(Param.SonstigEinmaligKonto2="Depot",$A20=Param.SonstigEinmaligJahr2),Param.SonstigEinmaligBetrag2,0) -> 0 | X20: =IF(AND(Param.SonstigEinmaligKonto3="Depot",$A20=Param.SonstigEinmaligJahr3),Param.SonstigEinmaligBetrag3,0) -> 0 | Y20: =IF(AND(Param.SonstigEinmaligKonto4="Depot",$A20=Param.SonstigEinmaligJahr4),Param.SonstigEinmaligBetrag4,0) -> 0 | Z20: =IF(AND(Param.SonstigEinmaligKonto5="Depot",$A20=Param.SonstigEinmaligJahr5),Param.SonstigEinmaligBetrag5,0) -> 0 | AA20: =IF(AND(Param.SonstigEinmaligKonto6="Depot",$A20=Param.SonstigEinmaligJahr6),Param.SonstigEinmaligBetrag6,0) -> 0 | AB20: =IF(AND(Param.SonstigEinmaligKonto7="Depot",$A20=Param.SonstigEinmaligJahr7),Param.SonstigEinmaligBetrag7,0) -> 0 | AC20: =IF(AND(Param.SonstigEinmaligKonto8="Depot",$A20=Param.SonstigEinmaligJahr8),Param.SonstigEinmaligBetrag8,0) -> 0 | AD20: =IF(AND(Param.SonstigEinmaligKonto9="Depot",$A20=Param.SonstigEinmaligJahr9),Param.SonstigEinmaligBetrag9,0) -> 0 | AE20: =IF(AND(Param.SonstigEinmaligKonto10="Depot",$A20=Param.SonstigEinmaligJahr10),Param.SonstigEinmaligBetrag10,0) -> 0 | AF20: =Param.SparerPauschbetrag-BF20 -> 0 | AG20: =IF(AND(A20>=Param.FireStartjahr,S20>0),MIN(N20*Q20,S20),0) -> 0 | AH20: =IF(AG20<=0,0,IF(S20<=0,0,AG20/(1-MAX(0,((T20/S20)*(1-Param.Teilfreistellung)-MIN(AF20,AG20)/AG20)*Param.KapSt)))) -> 0 | AI20: =AH20-AG20 -> 0 | AJ20: =T20-AH20*(T20/S20) -> 467838.97 | AK20: =S20-AH20 -> 735338.97 | AL20: =FV(AO20,12,-(U20/12),-AK20,0) -> 785622.57 | AM20: =AJ20+AL20-AK20-U20 -> 512122.57 | AN20: =AM20/AL20 -> 0.65186846 | AO20: =(1+IF(AND(A20>=Param.DepotRenditeSpezBeginn1,A20<=Param.DepotRenditeSpezEnde1),Param.DepotRenditeSpezProz1,IF(AND(A20>=Param.DepotRenditeSpezBeginn2,A20<=Param.DepotRenditeSpezEnde2),Param.DepotRenditeSpezProz2,IF(AND(A20>=Param.DepotRenditeSpezBeginn3,A20<=Param.DepotRenditeSpezEnde3),Param.DepotRenditeSpezProz3,IF(AND(A20>=Param.DepotRenditeSpezBeginn4,A20<=Param.DepotRenditeSpezEnde4),Param.DepotRenditeSpezProz4,IF(AND(A20>=Param.DepotRenditeSpezBeginn5,A20<=Param.DepotRenditeSpezEnde5),Param.DepotRenditeSpezProz5,Param.DepotRenditeDefault))))))^(1/12)-1 -> 0.0048675506 | AP20: =BJ19 -> 278943.6 | AQ20: =IF(A20<Param.FireStartjahr,Param.SparrateFestgeldMonatl*12*(1+Param.SparrateDynamikJaehrl)^($A20-Param.Startjahr),0) -> 1800 | AR20: =O20 -> 0 | AS20: =IF(AND(Param.SonstigEinmaligKonto1="Festgeld",$A20=Param.SonstigEinmaligJahr1),Param.SonstigEinmaligBetrag1,0) -> 0 | AT20: =IF(AND(Param.SonstigEinmaligKonto2="Festgeld",$A20=Param.SonstigEinmaligJahr2),Param.SonstigEinmaligBetrag2,0) -> 0 | AU20: =IF(AND(Param.SonstigEinmaligKonto3="Festgeld",$A20=Param.SonstigEinmaligJahr3),Param.SonstigEinmaligBetrag3,0) -> 0 | AV20: =IF(AND(Param.SonstigEinmaligKonto4="Festgeld",$A20=Param.SonstigEinmaligJahr4),Param.SonstigEinmaligBetrag4,0) -> 0 | AW20: =IF(AND(Param.SonstigEinmaligKonto5="Festgeld",$A20=Param.SonstigEinmaligJahr5),Param.SonstigEinmaligBetrag5,0) -> 0 | AX20: =IF(AND(Param.SonstigEinmaligKonto6="Festgeld",$A20=Param.SonstigEinmaligJahr6),Param.SonstigEinmaligBetrag6,0) -> 0 | AY20: =IF(AND(Param.SonstigEinmaligKonto7="Festgeld",$A20=Param.SonstigEinmaligJahr7),Param.SonstigEinmaligBetrag7,0) -> 0 | AZ20: =IF(AND(Param.SonstigEinmaligKonto8="Festgeld",$A20=Param.SonstigEinmaligJahr8),Param.SonstigEinmaligBetrag8,0) -> 0 | BA20: =IF(AND(Param.SonstigEinmaligKonto9="Festgeld",$A20=Param.SonstigEinmaligJahr9),Param.SonstigEinmaligBetrag9,0) -> 0 | BB20: =IF(AND(Param.SonstigEinmaligKonto10="Festgeld",$A20=Param.SonstigEinmaligJahr10),Param.SonstigEinmaligBetrag10,0) -> 0 | BC20: =IF(AND(A20>=Param.FireStartjahr,AP20>0),MIN(N20*R20,AP20),0) -> 0 | BD20: =Param.FestgeldZinssatz -> 0.02 | BE20: =(AP20+AQ20-BC20)*BD20 -> 5614.8721 | BF20: =IF(BE20>Param.SparerPauschbetrag,Param.SparerPauschbetrag,BE20) -> 1000 | BG20: =BE20-BF20 -> 4614.8721 | BH20: =BG20*Param.KapSt -> 1217.1725 | BI20: =BE20-BH20 -> 4397.6996 | BJ20: =AP20+SUM(AQ20:BB20)-BC20+BI20 -> 285141.3 | BK20: =AL20+BJ20 -> 1070763.9 | BL20: =BK20/(1+Param.Inflationsrate)^(A20-Param.Startjahr) -> 739325.58 | BM20: =IF(BK20<N20,A20,"") | BN20: =AH20+BC20 -> 0 | BO20: =SUM(AR20:BB20) -> 0 | BP20: =BN20+(-1*BO20) -> 0 | BQ20: =AI20+BH20 -> 1217.1725 | BR20: =IF(BK20>0,BP20/BK20,0) -> 0
A21: =A20+1 -> 2042 | B21: =B5+(17-1) -> 46 | C21: =IF(A21<Param.FireStartjahr,0,Param.EntnahmeBetragStart*(1+Param.Inflationsrate)^(A21-Param.Startjahr)) -> 0 | D21: =IF(OR($A21<Param.SonstigRegelmJahrBeginn1,$A21>Param.SonstigRegelmJahrEnd1),0,Param.SonstigRegelmBetragJaehrl1*(1+Param.SonstigRegelmSteig1)^(A21-Param.SonstigRegelmJahrBeginn1)) -> 0 | E21: =IF(OR($A21<Param.SonstigRegelmJahrBeginn2,$A21>Param.SonstigRegelmJahrEnd2),0,Param.SonstigRegelmBetragJaehrl2*(1+Param.SonstigRegelmSteig2)^($A21-Param.SonstigRegelmJahrBeginn2)) -> 0 | F21: =IF(OR($A21<Param.SonstigRegelmJahrBeginn3,$A21>Param.SonstigRegelmJahrEnd3),0,Param.SonstigRegelmBetragJaehrl3*(1+Param.SonstigRegelmSteig3)^($A21-Param.SonstigRegelmJahrBeginn3)) -> 0 | G21: =IF(OR($A21<Param.SonstigRegelmJahrBeginn4,$A21>Param.SonstigRegelmJahrEnd4),0,Param.SonstigRegelmBetragJaehrl4*(1+Param.SonstigRegelmSteig4)^($A21-Param.SonstigRegelmJahrBeginn4)) -> 0 | H21: =IF(OR($A21<Param.SonstigRegelmJahrBeginn5,$A21>Param.SonstigRegelmJahrEnd5),0,Param.SonstigRegelmBetragJaehrl5*(1+Param.SonstigRegelmSteig5)^($A21-Param.SonstigRegelmJahrBeginn5)) -> 0 | I21: =IF(OR($A21<Param.SonstigRegelmJahrBeginn6,$A21>Param.SonstigRegelmJahrEnd6),0,Param.SonstigRegelmBetragJaehrl6*(1+Param.SonstigRegelmSteig6)^($A21-Param.SonstigRegelmJahrBeginn6)) -> 0 | J21: =IF(OR($A21<Param.SonstigRegelmJahrBeginn7,$A21>Param.SonstigRegelmJahrEnd7),0,Param.SonstigRegelmBetragJaehrl7*(1+Param.SonstigRegelmSteig7)^($A21-Param.SonstigRegelmJahrBeginn7)) -> 0 | K21: =IF(OR($A21<Param.SonstigRegelmJahrBeginn8,$A21>Param.SonstigRegelmJahrEnd8),0,Param.SonstigRegelmBetragJaehrl8*(1+Param.SonstigRegelmSteig8)^($A21-Param.SonstigRegelmJahrBeginn8)) -> 0 | L21: =IF(OR($A21<Param.SonstigRegelmJahrBeginn9,$A21>Param.SonstigRegelmJahrEnd9),0,Param.SonstigRegelmBetragJaehrl9*(1+Param.SonstigRegelmSteig9)^($A21-Param.SonstigRegelmJahrBeginn9)) -> 0 | M21: =IF(OR($A21<Param.SonstigRegelmJahrBeginn10,$A21>Param.SonstigRegelmJahrEnd10),0,Param.SonstigRegelmBetragJaehrl10*(1+Param.SonstigRegelmSteig10)^($A21-Param.SonstigRegelmJahrBeginn10)) -> 0 | N21: =MAX(0,C21-SUM(D21:M21)) -> 0 | O21: =IF(N21<=0,SUM(D21:M21)-C21,0) -> 0 | P21: =S21+AP21 -> 1070763.9 | Q21: =IF(P21>0,S21/P21,0) -> 0.73370291 | R21: =IF(P21>0,AP21/P21,0) -> 0.26629709 | S21: =AL20 -> 785622.57 | T21: =AM20 -> 512122.57 | U21: =IF(A21<Param.FireStartjahr,Param.SparrateDepotMonatl*12*(1+Param.SparrateDynamikJaehrl)^($A21-Param.Startjahr),0) -> 6000 | V21: =IF(AND(Param.SonstigEinmaligKonto1="Depot",$A21=Param.SonstigEinmaligJahr1),Param.SonstigEinmaligBetrag1,0) -> 0 | W21: =IF(AND(Param.SonstigEinmaligKonto2="Depot",$A21=Param.SonstigEinmaligJahr2),Param.SonstigEinmaligBetrag2,0) -> 0 | X21: =IF(AND(Param.SonstigEinmaligKonto3="Depot",$A21=Param.SonstigEinmaligJahr3),Param.SonstigEinmaligBetrag3,0) -> 0 | Y21: =IF(AND(Param.SonstigEinmaligKonto4="Depot",$A21=Param.SonstigEinmaligJahr4),Param.SonstigEinmaligBetrag4,0) -> 0 | Z21: =IF(AND(Param.SonstigEinmaligKonto5="Depot",$A21=Param.SonstigEinmaligJahr5),Param.SonstigEinmaligBetrag5,0) -> 0 | AA21: =IF(AND(Param.SonstigEinmaligKonto6="Depot",$A21=Param.SonstigEinmaligJahr6),Param.SonstigEinmaligBetrag6,0) -> 0 | AB21: =IF(AND(Param.SonstigEinmaligKonto7="Depot",$A21=Param.SonstigEinmaligJahr7),Param.SonstigEinmaligBetrag7,0) -> 0 | AC21: =IF(AND(Param.SonstigEinmaligKonto8="Depot",$A21=Param.SonstigEinmaligJahr8),Param.SonstigEinmaligBetrag8,0) -> 0 | AD21: =IF(AND(Param.SonstigEinmaligKonto9="Depot",$A21=Param.SonstigEinmaligJahr9),Param.SonstigEinmaligBetrag9,0) -> 0 | AE21: =IF(AND(Param.SonstigEinmaligKonto10="Depot",$A21=Param.SonstigEinmaligJahr10),Param.SonstigEinmaligBetrag10,0) -> 0 | AF21: =Param.SparerPauschbetrag-BF21 -> 0 | AG21: =IF(AND(A21>=Param.FireStartjahr,S21>0),MIN(N21*Q21,S21),0) -> 0 | AH21: =IF(AG21<=0,0,IF(S21<=0,0,AG21/(1-MAX(0,((T21/S21)*(1-Param.Teilfreistellung)-MIN(AF21,AG21)/AG21)*Param.KapSt)))) -> 0 | AI21: =AH21-AG21 -> 0 | AJ21: =T21-AH21*(T21/S21) -> 512122.57 | AK21: =S21-AH21 -> 785622.57 | AL21: =FV(AO21,12,-(U21/12),-AK21,0) -> 838923.19 | AM21: =AJ21+AL21-AK21-U21 -> 559423.19 | AN21: =AM21/AL21 -> 0.66683482 | AO21: =(1+IF(AND(A21>=Param.DepotRenditeSpezBeginn1,A21<=Param.DepotRenditeSpezEnde1),Param.DepotRenditeSpezProz1,IF(AND(A21>=Param.DepotRenditeSpezBeginn2,A21<=Param.DepotRenditeSpezEnde2),Param.DepotRenditeSpezProz2,IF(AND(A21>=Param.DepotRenditeSpezBeginn3,A21<=Param.DepotRenditeSpezEnde3),Param.DepotRenditeSpezProz3,IF(AND(A21>=Param.DepotRenditeSpezBeginn4,A21<=Param.DepotRenditeSpezEnde4),Param.DepotRenditeSpezProz4,IF(AND(A21>=Param.DepotRenditeSpezBeginn5,A21<=Param.DepotRenditeSpezEnde5),Param.DepotRenditeSpezProz5,Param.DepotRenditeDefault))))))^(1/12)-1 -> 0.0048675506 | AP21: =BJ20 -> 285141.3 | AQ21: =IF(A21<Param.FireStartjahr,Param.SparrateFestgeldMonatl*12*(1+Param.SparrateDynamikJaehrl)^($A21-Param.Startjahr),0) -> 1800 | AR21: =O21 -> 0 | AS21: =IF(AND(Param.SonstigEinmaligKonto1="Festgeld",$A21=Param.SonstigEinmaligJahr1),Param.SonstigEinmaligBetrag1,0) -> 0 | AT21: =IF(AND(Param.SonstigEinmaligKonto2="Festgeld",$A21=Param.SonstigEinmaligJahr2),Param.SonstigEinmaligBetrag2,0) -> 0 | AU21: =IF(AND(Param.SonstigEinmaligKonto3="Festgeld",$A21=Param.SonstigEinmaligJahr3),Param.SonstigEinmaligBetrag3,0) -> 0 | AV21: =IF(AND(Param.SonstigEinmaligKonto4="Festgeld",$A21=Param.SonstigEinmaligJahr4),Param.SonstigEinmaligBetrag4,0) -> 0 | AW21: =IF(AND(Param.SonstigEinmaligKonto5="Festgeld",$A21=Param.SonstigEinmaligJahr5),Param.SonstigEinmaligBetrag5,0) -> 0 | AX21: =IF(AND(Param.SonstigEinmaligKonto6="Festgeld",$A21=Param.SonstigEinmaligJahr6),Param.SonstigEinmaligBetrag6,0) -> 0 | AY21: =IF(AND(Param.SonstigEinmaligKonto7="Festgeld",$A21=Param.SonstigEinmaligJahr7),Param.SonstigEinmaligBetrag7,0) -> 0 | AZ21: =IF(AND(Param.SonstigEinmaligKonto8="Festgeld",$A21=Param.SonstigEinmaligJahr8),Param.SonstigEinmaligBetrag8,0) -> 0 | BA21: =IF(AND(Param.SonstigEinmaligKonto9="Festgeld",$A21=Param.SonstigEinmaligJahr9),Param.SonstigEinmaligBetrag9,0) -> 0 | BB21: =IF(AND(Param.SonstigEinmaligKonto10="Festgeld",$A21=Param.SonstigEinmaligJahr10),Param.SonstigEinmaligBetrag10,0) -> 0 | BC21: =IF(AND(A21>=Param.FireStartjahr,AP21>0),MIN(N21*R21,AP21),0) -> 0 | BD21: =Param.FestgeldZinssatz -> 0.02 | BE21: =(AP21+AQ21-BC21)*BD21 -> 5738.8261 | BF21: =IF(BE21>Param.SparerPauschbetrag,Param.SparerPauschbetrag,BE21) -> 1000 | BG21: =BE21-BF21 -> 4738.8261 | BH21: =BG21*Param.KapSt -> 1249.8654 | BI21: =BE21-BH21 -> 4488.9607 | BJ21: =AP21+SUM(AQ21:BB21)-BC21+BI21 -> 291430.26 | BK21: =AL21+BJ21 -> 1130353.5 | BL21: =BK21/(1+Param.Inflationsrate)^(A21-Param.Startjahr) -> 761434.27 | BM21: =IF(BK21<N21,A21,"") | BN21: =AH21+BC21 -> 0 | BO21: =SUM(AR21:BB21) -> 0 | BP21: =BN21+(-1*BO21) -> 0 | BQ21: =AI21+BH21 -> 1249.8654 | BR21: =IF(BK21>0,BP21/BK21,0) -> 0
A22: =A21+1 -> 2043 | B22: =B5+(18-1) -> 47 | C22: =IF(A22<Param.FireStartjahr,0,Param.EntnahmeBetragStart*(1+Param.Inflationsrate)^(A22-Param.Startjahr)) -> 0 | D22: =IF(OR($A22<Param.SonstigRegelmJahrBeginn1,$A22>Param.SonstigRegelmJahrEnd1),0,Param.SonstigRegelmBetragJaehrl1*(1+Param.SonstigRegelmSteig1)^(A22-Param.SonstigRegelmJahrBeginn1)) -> 0 | E22: =IF(OR($A22<Param.SonstigRegelmJahrBeginn2,$A22>Param.SonstigRegelmJahrEnd2),0,Param.SonstigRegelmBetragJaehrl2*(1+Param.SonstigRegelmSteig2)^($A22-Param.SonstigRegelmJahrBeginn2)) -> 0 | F22: =IF(OR($A22<Param.SonstigRegelmJahrBeginn3,$A22>Param.SonstigRegelmJahrEnd3),0,Param.SonstigRegelmBetragJaehrl3*(1+Param.SonstigRegelmSteig3)^($A22-Param.SonstigRegelmJahrBeginn3)) -> 0 | G22: =IF(OR($A22<Param.SonstigRegelmJahrBeginn4,$A22>Param.SonstigRegelmJahrEnd4),0,Param.SonstigRegelmBetragJaehrl4*(1+Param.SonstigRegelmSteig4)^($A22-Param.SonstigRegelmJahrBeginn4)) -> 0 | H22: =IF(OR($A22<Param.SonstigRegelmJahrBeginn5,$A22>Param.SonstigRegelmJahrEnd5),0,Param.SonstigRegelmBetragJaehrl5*(1+Param.SonstigRegelmSteig5)^($A22-Param.SonstigRegelmJahrBeginn5)) -> 0 | I22: =IF(OR($A22<Param.SonstigRegelmJahrBeginn6,$A22>Param.SonstigRegelmJahrEnd6),0,Param.SonstigRegelmBetragJaehrl6*(1+Param.SonstigRegelmSteig6)^($A22-Param.SonstigRegelmJahrBeginn6)) -> 0 | J22: =IF(OR($A22<Param.SonstigRegelmJahrBeginn7,$A22>Param.SonstigRegelmJahrEnd7),0,Param.SonstigRegelmBetragJaehrl7*(1+Param.SonstigRegelmSteig7)^($A22-Param.SonstigRegelmJahrBeginn7)) -> 0 | K22: =IF(OR($A22<Param.SonstigRegelmJahrBeginn8,$A22>Param.SonstigRegelmJahrEnd8),0,Param.SonstigRegelmBetragJaehrl8*(1+Param.SonstigRegelmSteig8)^($A22-Param.SonstigRegelmJahrBeginn8)) -> 0 | L22: =IF(OR($A22<Param.SonstigRegelmJahrBeginn9,$A22>Param.SonstigRegelmJahrEnd9),0,Param.SonstigRegelmBetragJaehrl9*(1+Param.SonstigRegelmSteig9)^($A22-Param.SonstigRegelmJahrBeginn9)) -> 0 | M22: =IF(OR($A22<Param.SonstigRegelmJahrBeginn10,$A22>Param.SonstigRegelmJahrEnd10),0,Param.SonstigRegelmBetragJaehrl10*(1+Param.SonstigRegelmSteig10)^($A22-Param.SonstigRegelmJahrBeginn10)) -> 0 | N22: =MAX(0,C22-SUM(D22:M22)) -> 0 | O22: =IF(N22<=0,SUM(D22:M22)-C22,0) -> 0 | P22: =S22+AP22 -> 1130353.5 | Q22: =IF(P22>0,S22/P22,0) -> 0.74217776 | R22: =IF(P22>0,AP22/P22,0) -> 0.25782224 | S22: =AL21 -> 838923.19 | T22: =AM21 -> 559423.19 | U22: =IF(A22<Param.FireStartjahr,Param.SparrateDepotMonatl*12*(1+Param.SparrateDynamikJaehrl)^($A22-Param.Startjahr),0) -> 6000 | V22: =IF(AND(Param.SonstigEinmaligKonto1="Depot",$A22=Param.SonstigEinmaligJahr1),Param.SonstigEinmaligBetrag1,0) -> 0 | W22: =IF(AND(Param.SonstigEinmaligKonto2="Depot",$A22=Param.SonstigEinmaligJahr2),Param.SonstigEinmaligBetrag2,0) -> 0 | X22: =IF(AND(Param.SonstigEinmaligKonto3="Depot",$A22=Param.SonstigEinmaligJahr3),Param.SonstigEinmaligBetrag3,0) -> 0 | Y22: =IF(AND(Param.SonstigEinmaligKonto4="Depot",$A22=Param.SonstigEinmaligJahr4),Param.SonstigEinmaligBetrag4,0) -> 0 | Z22: =IF(AND(Param.SonstigEinmaligKonto5="Depot",$A22=Param.SonstigEinmaligJahr5),Param.SonstigEinmaligBetrag5,0) -> 0 | AA22: =IF(AND(Param.SonstigEinmaligKonto6="Depot",$A22=Param.SonstigEinmaligJahr6),Param.SonstigEinmaligBetrag6,0) -> 0 | AB22: =IF(AND(Param.SonstigEinmaligKonto7="Depot",$A22=Param.SonstigEinmaligJahr7),Param.SonstigEinmaligBetrag7,0) -> 0 | AC22: =IF(AND(Param.SonstigEinmaligKonto8="Depot",$A22=Param.SonstigEinmaligJahr8),Param.SonstigEinmaligBetrag8,0) -> 0 | AD22: =IF(AND(Param.SonstigEinmaligKonto9="Depot",$A22=Param.SonstigEinmaligJahr9),Param.SonstigEinmaligBetrag9,0) -> 0 | AE22: =IF(AND(Param.SonstigEinmaligKonto10="Depot",$A22=Param.SonstigEinmaligJahr10),Param.SonstigEinmaligBetrag10,0) -> 0 | AF22: =Param.SparerPauschbetrag-BF22 -> 0 | AG22: =IF(AND(A22>=Param.FireStartjahr,S22>0),MIN(N22*Q22,S22),0) -> 0 | AH22: =IF(AG22<=0,0,IF(S22<=0,0,AG22/(1-MAX(0,((T22/S22)*(1-Param.Teilfreistellung)-MIN(AF22,AG22)/AG22)*Param.KapSt)))) -> 0 | AI22: =AH22-AG22 -> 0 | AJ22: =T22-AH22*(T22/S22) -> 559423.19 | AK22: =S22-AH22 -> 838923.19 | AL22: =FV(AO22,12,-(U22/12),-AK22,0) -> 895421.85 | AM22: =AJ22+AL22-AK22-U22 -> 609921.85 | AN22: =AM22/AL22 -> 0.68115587 | AO22: =(1+IF(AND(A22>=Param.DepotRenditeSpezBeginn1,A22<=Param.DepotRenditeSpezEnde1),Param.DepotRenditeSpezProz1,IF(AND(A22>=Param.DepotRenditeSpezBeginn2,A22<=Param.DepotRenditeSpezEnde2),Param.DepotRenditeSpezProz2,IF(AND(A22>=Param.DepotRenditeSpezBeginn3,A22<=Param.DepotRenditeSpezEnde3),Param.DepotRenditeSpezProz3,IF(AND(A22>=Param.DepotRenditeSpezBeginn4,A22<=Param.DepotRenditeSpezEnde4),Param.DepotRenditeSpezProz4,IF(AND(A22>=Param.DepotRenditeSpezBeginn5,A22<=Param.DepotRenditeSpezEnde5),Param.DepotRenditeSpezProz5,Param.DepotRenditeDefault))))))^(1/12)-1 -> 0.0048675506 | AP22: =BJ21 -> 291430.26 | AQ22: =IF(A22<Param.FireStartjahr,Param.SparrateFestgeldMonatl*12*(1+Param.SparrateDynamikJaehrl)^($A22-Param.Startjahr),0) -> 1800 | AR22: =O22 -> 0 | AS22: =IF(AND(Param.SonstigEinmaligKonto1="Festgeld",$A22=Param.SonstigEinmaligJahr1),Param.SonstigEinmaligBetrag1,0) -> 0 | AT22: =IF(AND(Param.SonstigEinmaligKonto2="Festgeld",$A22=Param.SonstigEinmaligJahr2),Param.SonstigEinmaligBetrag2,0) -> 0 | AU22: =IF(AND(Param.SonstigEinmaligKonto3="Festgeld",$A22=Param.SonstigEinmaligJahr3),Param.SonstigEinmaligBetrag3,0) -> 0 | AV22: =IF(AND(Param.SonstigEinmaligKonto4="Festgeld",$A22=Param.SonstigEinmaligJahr4),Param.SonstigEinmaligBetrag4,0) -> 0 | AW22: =IF(AND(Param.SonstigEinmaligKonto5="Festgeld",$A22=Param.SonstigEinmaligJahr5),Param.SonstigEinmaligBetrag5,0) -> 0 | AX22: =IF(AND(Param.SonstigEinmaligKonto6="Festgeld",$A22=Param.SonstigEinmaligJahr6),Param.SonstigEinmaligBetrag6,0) -> 0 | AY22: =IF(AND(Param.SonstigEinmaligKonto7="Festgeld",$A22=Param.SonstigEinmaligJahr7),Param.SonstigEinmaligBetrag7,0) -> 0 | AZ22: =IF(AND(Param.SonstigEinmaligKonto8="Festgeld",$A22=Param.SonstigEinmaligJahr8),Param.SonstigEinmaligBetrag8,0) -> 0 | BA22: =IF(AND(Param.SonstigEinmaligKonto9="Festgeld",$A22=Param.SonstigEinmaligJahr9),Param.SonstigEinmaligBetrag9,0) -> 0 | BB22: =IF(AND(Param.SonstigEinmaligKonto10="Festgeld",$A22=Param.SonstigEinmaligJahr10),Param.SonstigEinmaligBetrag10,0) -> 0 | BC22: =IF(AND(A22>=Param.FireStartjahr,AP22>0),MIN(N22*R22,AP22),0) -> 0 | BD22: =Param.FestgeldZinssatz -> 0.02 | BE22: =(AP22+AQ22-BC22)*BD22 -> 5864.6053 | BF22: =IF(BE22>Param.SparerPauschbetrag,Param.SparerPauschbetrag,BE22) -> 1000 | BG22: =BE22-BF22 -> 4864.6053 | BH22: =BG22*Param.KapSt -> 1283.0396 | BI22: =BE22-BH22 -> 4581.5656 | BJ22: =AP22+SUM(AQ22:BB22)-BC22+BI22 -> 297811.83 | BK22: =AL22+BJ22 -> 1193233.7 | BL22: =BK22/(1+Param.Inflationsrate)^(A22-Param.Startjahr) -> 784187.27 | BM22: =IF(BK22<N22,A22,"") | BN22: =AH22+BC22 -> 0 | BO22: =SUM(AR22:BB22) -> 0 | BP22: =BN22+(-1*BO22) -> 0 | BQ22: =AI22+BH22 -> 1283.0396 | BR22: =IF(BK22>0,BP22/BK22,0) -> 0
A23: =A22+1 -> 2044 | B23: =B5+(19-1) -> 48 | C23: =IF(A23<Param.FireStartjahr,0,Param.EntnahmeBetragStart*(1+Param.Inflationsrate)^(A23-Param.Startjahr)) -> 0 | D23: =IF(OR($A23<Param.SonstigRegelmJahrBeginn1,$A23>Param.SonstigRegelmJahrEnd1),0,Param.SonstigRegelmBetragJaehrl1*(1+Param.SonstigRegelmSteig1)^(A23-Param.SonstigRegelmJahrBeginn1)) -> 0 | E23: =IF(OR($A23<Param.SonstigRegelmJahrBeginn2,$A23>Param.SonstigRegelmJahrEnd2),0,Param.SonstigRegelmBetragJaehrl2*(1+Param.SonstigRegelmSteig2)^($A23-Param.SonstigRegelmJahrBeginn2)) -> 0 | F23: =IF(OR($A23<Param.SonstigRegelmJahrBeginn3,$A23>Param.SonstigRegelmJahrEnd3),0,Param.SonstigRegelmBetragJaehrl3*(1+Param.SonstigRegelmSteig3)^($A23-Param.SonstigRegelmJahrBeginn3)) -> 0 | G23: =IF(OR($A23<Param.SonstigRegelmJahrBeginn4,$A23>Param.SonstigRegelmJahrEnd4),0,Param.SonstigRegelmBetragJaehrl4*(1+Param.SonstigRegelmSteig4)^($A23-Param.SonstigRegelmJahrBeginn4)) -> 0 | H23: =IF(OR($A23<Param.SonstigRegelmJahrBeginn5,$A23>Param.SonstigRegelmJahrEnd5),0,Param.SonstigRegelmBetragJaehrl5*(1+Param.SonstigRegelmSteig5)^($A23-Param.SonstigRegelmJahrBeginn5)) -> 0 | I23: =IF(OR($A23<Param.SonstigRegelmJahrBeginn6,$A23>Param.SonstigRegelmJahrEnd6),0,Param.SonstigRegelmBetragJaehrl6*(1+Param.SonstigRegelmSteig6)^($A23-Param.SonstigRegelmJahrBeginn6)) -> 0 | J23: =IF(OR($A23<Param.SonstigRegelmJahrBeginn7,$A23>Param.SonstigRegelmJahrEnd7),0,Param.SonstigRegelmBetragJaehrl7*(1+Param.SonstigRegelmSteig7)^($A23-Param.SonstigRegelmJahrBeginn7)) -> 0 | K23: =IF(OR($A23<Param.SonstigRegelmJahrBeginn8,$A23>Param.SonstigRegelmJahrEnd8),0,Param.SonstigRegelmBetragJaehrl8*(1+Param.SonstigRegelmSteig8)^($A23-Param.SonstigRegelmJahrBeginn8)) -> 0 | L23: =IF(OR($A23<Param.SonstigRegelmJahrBeginn9,$A23>Param.SonstigRegelmJahrEnd9),0,Param.SonstigRegelmBetragJaehrl9*(1+Param.SonstigRegelmSteig9)^($A23-Param.SonstigRegelmJahrBeginn9)) -> 0 | M23: =IF(OR($A23<Param.SonstigRegelmJahrBeginn10,$A23>Param.SonstigRegelmJahrEnd10),0,Param.SonstigRegelmBetragJaehrl10*(1+Param.SonstigRegelmSteig10)^($A23-Param.SonstigRegelmJahrBeginn10)) -> 0 | N23: =MAX(0,C23-SUM(D23:M23)) -> 0 | O23: =IF(N23<=0,SUM(D23:M23)-C23,0) -> 0 | P23: =S23+AP23 -> 1193233.7 | Q23: =IF(P23>0,S23/P23,0) -> 0.75041617 | R23: =IF(P23>0,AP23/P23,0) -> 0.24958383 | S23: =AL22 -> 895421.85 | T23: =AM22 -> 609921.85 | U23: =IF(A23<Param.FireStartjahr,Param.SparrateDepotMonatl*12*(1+Param.SparrateDynamikJaehrl)^($A23-Param.Startjahr),0) -> 6000 | V23: =IF(AND(Param.SonstigEinmaligKonto1="Depot",$A23=Param.SonstigEinmaligJahr1),Param.SonstigEinmaligBetrag1,0) -> 0 | W23: =IF(AND(Param.SonstigEinmaligKonto2="Depot",$A23=Param.SonstigEinmaligJahr2),Param.SonstigEinmaligBetrag2,0) -> 0 | X23: =IF(AND(Param.SonstigEinmaligKonto3="Depot",$A23=Param.SonstigEinmaligJahr3),Param.SonstigEinmaligBetrag3,0) -> 0 | Y23: =IF(AND(Param.SonstigEinmaligKonto4="Depot",$A23=Param.SonstigEinmaligJahr4),Param.SonstigEinmaligBetrag4,0) -> 0 | Z23: =IF(AND(Param.SonstigEinmaligKonto5="Depot",$A23=Param.SonstigEinmaligJahr5),Param.SonstigEinmaligBetrag5,0) -> 0 | AA23: =IF(AND(Param.SonstigEinmaligKonto6="Depot",$A23=Param.SonstigEinmaligJahr6),Param.SonstigEinmaligBetrag6,0) -> 0 | AB23: =IF(AND(Param.SonstigEinmaligKonto7="Depot",$A23=Param.SonstigEinmaligJahr7),Param.SonstigEinmaligBetrag7,0) -> 0 | AC23: =IF(AND(Param.SonstigEinmaligKonto8="Depot",$A23=Param.SonstigEinmaligJahr8),Param.SonstigEinmaligBetrag8,0) -> 0 | AD23: =IF(AND(Param.SonstigEinmaligKonto9="Depot",$A23=Param.SonstigEinmaligJahr9),Param.SonstigEinmaligBetrag9,0) -> 0 | AE23: =IF(AND(Param.SonstigEinmaligKonto10="Depot",$A23=Param.SonstigEinmaligJahr10),Param.SonstigEinmaligBetrag10,0) -> 0 | AF23: =Param.SparerPauschbetrag-BF23 -> 0 | AG23: =IF(AND(A23>=Param.FireStartjahr,S23>0),MIN(N23*Q23,S23),0) -> 0 | AH23: =IF(AG23<=0,0,IF(S23<=0,0,AG23/(1-MAX(0,((T23/S23)*(1-Param.Teilfreistellung)-MIN(AF23,AG23)/AG23)*Param.KapSt)))) -> 0 | AI23: =AH23-AG23 -> 0 | AJ23: =T23-AH23*(T23/S23) -> 609921.85 | AK23: =S23-AH23 -> 895421.85 | AL23: =FV(AO23,12,-(U23/12),-AK23,0) -> 955310.42 | AM23: =AJ23+AL23-AK23-U23 -> 663810.42 | AN23: =AM23/AL23 -> 0.69486358 | AO23: =(1+IF(AND(A23>=Param.DepotRenditeSpezBeginn1,A23<=Param.DepotRenditeSpezEnde1),Param.DepotRenditeSpezProz1,IF(AND(A23>=Param.DepotRenditeSpezBeginn2,A23<=Param.DepotRenditeSpezEnde2),Param.DepotRenditeSpezProz2,IF(AND(A23>=Param.DepotRenditeSpezBeginn3,A23<=Param.DepotRenditeSpezEnde3),Param.DepotRenditeSpezProz3,IF(AND(A23>=Param.DepotRenditeSpezBeginn4,A23<=Param.DepotRenditeSpezEnde4),Param.DepotRenditeSpezProz4,IF(AND(A23>=Param.DepotRenditeSpezBeginn5,A23<=Param.DepotRenditeSpezEnde5),Param.DepotRenditeSpezProz5,Param.DepotRenditeDefault))))))^(1/12)-1 -> 0.0048675506 | AP23: =BJ22 -> 297811.83 | AQ23: =IF(A23<Param.FireStartjahr,Param.SparrateFestgeldMonatl*12*(1+Param.SparrateDynamikJaehrl)^($A23-Param.Startjahr),0) -> 1800 | AR23: =O23 -> 0 | AS23: =IF(AND(Param.SonstigEinmaligKonto1="Festgeld",$A23=Param.SonstigEinmaligJahr1),Param.SonstigEinmaligBetrag1,0) -> 0 | AT23: =IF(AND(Param.SonstigEinmaligKonto2="Festgeld",$A23=Param.SonstigEinmaligJahr2),Param.SonstigEinmaligBetrag2,0) -> 0 | AU23: =IF(AND(Param.SonstigEinmaligKonto3="Festgeld",$A23=Param.SonstigEinmaligJahr3),Param.SonstigEinmaligBetrag3,0) -> 0 | AV23: =IF(AND(Param.SonstigEinmaligKonto4="Festgeld",$A23=Param.SonstigEinmaligJahr4),Param.SonstigEinmaligBetrag4,0) -> 0 | AW23: =IF(AND(Param.SonstigEinmaligKonto5="Festgeld",$A23=Param.SonstigEinmaligJahr5),Param.SonstigEinmaligBetrag5,0) -> 0 | AX23: =IF(AND(Param.SonstigEinmaligKonto6="Festgeld",$A23=Param.SonstigEinmaligJahr6),Param.SonstigEinmaligBetrag6,0) -> 0 | AY23: =IF(AND(Param.SonstigEinmaligKonto7="Festgeld",$A23=Param.SonstigEinmaligJahr7),Param.SonstigEinmaligBetrag7,0) -> 0 | AZ23: =IF(AND(Param.SonstigEinmaligKonto8="Festgeld",$A23=Param.SonstigEinmaligJahr8),Param.SonstigEinmaligBetrag8,0) -> 0 | BA23: =IF(AND(Param.SonstigEinmaligKonto9="Festgeld",$A23=Param.SonstigEinmaligJahr9),Param.SonstigEinmaligBetrag9,0) -> 0 | BB23: =IF(AND(Param.SonstigEinmaligKonto10="Festgeld",$A23=Param.SonstigEinmaligJahr10),Param.SonstigEinmaligBetrag10,0) -> 0 | BC23: =IF(AND(A23>=Param.FireStartjahr,AP23>0),MIN(N23*R23,AP23),0) -> 0 | BD23: =Param.FestgeldZinssatz -> 0.02 | BE23: =(AP23+AQ23-BC23)*BD23 -> 5992.2366 | BF23: =IF(BE23>Param.SparerPauschbetrag,Param.SparerPauschbetrag,BE23) -> 1000 | BG23: =BE23-BF23 -> 4992.2366 | BH23: =BG23*Param.KapSt -> 1316.7024 | BI23: =BE23-BH23 -> 4675.5342 | BJ23: =AP23+SUM(AQ23:BB23)-BC23+BI23 -> 304287.36 | BK23: =AL23+BJ23 -> 1259597.8 | BL23: =BK23/(1+Param.Inflationsrate)^(A23-Param.Startjahr) -> 807611.16 | BM23: =IF(BK23<N23,A23,"") | BN23: =AH23+BC23 -> 0 | BO23: =SUM(AR23:BB23) -> 0 | BP23: =BN23+(-1*BO23) -> 0 | BQ23: =AI23+BH23 -> 1316.7024 | BR23: =IF(BK23>0,BP23/BK23,0) -> 0
A24: =A23+1 -> 2045 | B24: =B5+(20-1) -> 49 | C24: =IF(A24<Param.FireStartjahr,0,Param.EntnahmeBetragStart*(1+Param.Inflationsrate)^(A24-Param.Startjahr)) -> 47959.506 | D24: =IF(OR($A24<Param.SonstigRegelmJahrBeginn1,$A24>Param.SonstigRegelmJahrEnd1),0,Param.SonstigRegelmBetragJaehrl1*(1+Param.SonstigRegelmSteig1)^(A24-Param.SonstigRegelmJahrBeginn1)) -> 0 | E24: =IF(OR($A24<Param.SonstigRegelmJahrBeginn2,$A24>Param.SonstigRegelmJahrEnd2),0,Param.SonstigRegelmBetragJaehrl2*(1+Param.SonstigRegelmSteig2)^($A24-Param.SonstigRegelmJahrBeginn2)) -> -7200 | F24: =IF(OR($A24<Param.SonstigRegelmJahrBeginn3,$A24>Param.SonstigRegelmJahrEnd3),0,Param.SonstigRegelmBetragJaehrl3*(1+Param.SonstigRegelmSteig3)^($A24-Param.SonstigRegelmJahrBeginn3)) -> 0 | G24: =IF(OR($A24<Param.SonstigRegelmJahrBeginn4,$A24>Param.SonstigRegelmJahrEnd4),0,Param.SonstigRegelmBetragJaehrl4*(1+Param.SonstigRegelmSteig4)^($A24-Param.SonstigRegelmJahrBeginn4)) -> 0 | H24: =IF(OR($A24<Param.SonstigRegelmJahrBeginn5,$A24>Param.SonstigRegelmJahrEnd5),0,Param.SonstigRegelmBetragJaehrl5*(1+Param.SonstigRegelmSteig5)^($A24-Param.SonstigRegelmJahrBeginn5)) -> 0 | I24: =IF(OR($A24<Param.SonstigRegelmJahrBeginn6,$A24>Param.SonstigRegelmJahrEnd6),0,Param.SonstigRegelmBetragJaehrl6*(1+Param.SonstigRegelmSteig6)^($A24-Param.SonstigRegelmJahrBeginn6)) -> 0 | J24: =IF(OR($A24<Param.SonstigRegelmJahrBeginn7,$A24>Param.SonstigRegelmJahrEnd7),0,Param.SonstigRegelmBetragJaehrl7*(1+Param.SonstigRegelmSteig7)^($A24-Param.SonstigRegelmJahrBeginn7)) -> 0 | K24: =IF(OR($A24<Param.SonstigRegelmJahrBeginn8,$A24>Param.SonstigRegelmJahrEnd8),0,Param.SonstigRegelmBetragJaehrl8*(1+Param.SonstigRegelmSteig8)^($A24-Param.SonstigRegelmJahrBeginn8)) -> 0 | L24: =IF(OR($A24<Param.SonstigRegelmJahrBeginn9,$A24>Param.SonstigRegelmJahrEnd9),0,Param.SonstigRegelmBetragJaehrl9*(1+Param.SonstigRegelmSteig9)^($A24-Param.SonstigRegelmJahrBeginn9)) -> 0 | M24: =IF(OR($A24<Param.SonstigRegelmJahrBeginn10,$A24>Param.SonstigRegelmJahrEnd10),0,Param.SonstigRegelmBetragJaehrl10*(1+Param.SonstigRegelmSteig10)^($A24-Param.SonstigRegelmJahrBeginn10)) -> 0 | N24: =MAX(0,C24-SUM(D24:M24)) -> 55159.506 | O24: =IF(N24<=0,SUM(D24:M24)-C24,0) -> 0 | P24: =S24+AP24 -> 1259597.8 | Q24: =IF(P24>0,S24/P24,0) -> 0.75842498 | R24: =IF(P24>0,AP24/P24,0) -> 0.24157502 | S24: =AL23 -> 955310.42 | T24: =AM23 -> 663810.42 | U24: =IF(A24<Param.FireStartjahr,Param.SparrateDepotMonatl*12*(1+Param.SparrateDynamikJaehrl)^($A24-Param.Startjahr),0) -> 0 | V24: =IF(AND(Param.SonstigEinmaligKonto1="Depot",$A24=Param.SonstigEinmaligJahr1),Param.SonstigEinmaligBetrag1,0) -> 0 | W24: =IF(AND(Param.SonstigEinmaligKonto2="Depot",$A24=Param.SonstigEinmaligJahr2),Param.SonstigEinmaligBetrag2,0) -> 0 | X24: =IF(AND(Param.SonstigEinmaligKonto3="Depot",$A24=Param.SonstigEinmaligJahr3),Param.SonstigEinmaligBetrag3,0) -> 0 | Y24: =IF(AND(Param.SonstigEinmaligKonto4="Depot",$A24=Param.SonstigEinmaligJahr4),Param.SonstigEinmaligBetrag4,0) -> 0 | Z24: =IF(AND(Param.SonstigEinmaligKonto5="Depot",$A24=Param.SonstigEinmaligJahr5),Param.SonstigEinmaligBetrag5,0) -> 0 | AA24: =IF(AND(Param.SonstigEinmaligKonto6="Depot",$A24=Param.SonstigEinmaligJahr6),Param.SonstigEinmaligBetrag6,0) -> 0 | AB24: =IF(AND(Param.SonstigEinmaligKonto7="Depot",$A24=Param.SonstigEinmaligJahr7),Param.SonstigEinmaligBetrag7,0) -> 0 | AC24: =IF(AND(Param.SonstigEinmaligKonto8="Depot",$A24=Param.SonstigEinmaligJahr8),Param.SonstigEinmaligBetrag8,0) -> 0 | AD24: =IF(AND(Param.SonstigEinmaligKonto9="Depot",$A24=Param.SonstigEinmaligJahr9),Param.SonstigEinmaligBetrag9,0) -> 0 | AE24: =IF(AND(Param.SonstigEinmaligKonto10="Depot",$A24=Param.SonstigEinmaligJahr10),Param.SonstigEinmaligBetrag10,0) -> 0 | AF24: =Param.SparerPauschbetrag-BF24 -> 0 | AG24: =IF(AND(A24>=Param.FireStartjahr,S24>0),MIN(N24*Q24,S24),0) -> 41834.347 | AH24: =IF(AG24<=0,0,IF(S24<=0,0,AG24/(1-MAX(0,((T24/S24)*(1-Param.Teilfreistellung)-MIN(AF24,AG24)/AG24)*Param.KapSt)))) -> 47991.084 | AI24: =AH24-AG24 -> 6156.7372 | AJ24: =T24-AH24*(T24/S24) -> 630463.17 | AK24: =S24-AH24 -> 907319.34 | AL24: =FV(AO24,12,-(U24/12),-AK24,0) -> 970831.69 | AM24: =AJ24+AL24-AK24-U24 -> 693975.52 | AN24: =AM24/AL24 -> 0.71482578 | AO24: =(1+IF(AND(A24>=Param.DepotRenditeSpezBeginn1,A24<=Param.DepotRenditeSpezEnde1),Param.DepotRenditeSpezProz1,IF(AND(A24>=Param.DepotRenditeSpezBeginn2,A24<=Param.DepotRenditeSpezEnde2),Param.DepotRenditeSpezProz2,IF(AND(A24>=Param.DepotRenditeSpezBeginn3,A24<=Param.DepotRenditeSpezEnde3),Param.DepotRenditeSpezProz3,IF(AND(A24>=Param.DepotRenditeSpezBeginn4,A24<=Param.DepotRenditeSpezEnde4),Param.DepotRenditeSpezProz4,IF(AND(A24>=Param.DepotRenditeSpezBeginn5,A24<=Param.DepotRenditeSpezEnde5),Param.DepotRenditeSpezProz5,Param.DepotRenditeDefault))))))^(1/12)-1 -> 0.0056541454 | AP24: =BJ23 -> 304287.36 | AQ24: =IF(A24<Param.FireStartjahr,Param.SparrateFestgeldMonatl*12*(1+Param.SparrateDynamikJaehrl)^($A24-Param.Startjahr),0) -> 0 | AR24: =O24 -> 0 | AS24: =IF(AND(Param.SonstigEinmaligKonto1="Festgeld",$A24=Param.SonstigEinmaligJahr1),Param.SonstigEinmaligBetrag1,0) -> 0 | AT24: =IF(AND(Param.SonstigEinmaligKonto2="Festgeld",$A24=Param.SonstigEinmaligJahr2),Param.SonstigEinmaligBetrag2,0) -> 0 | AU24: =IF(AND(Param.SonstigEinmaligKonto3="Festgeld",$A24=Param.SonstigEinmaligJahr3),Param.SonstigEinmaligBetrag3,0) -> 0 | AV24: =IF(AND(Param.SonstigEinmaligKonto4="Festgeld",$A24=Param.SonstigEinmaligJahr4),Param.SonstigEinmaligBetrag4,0) -> 0 | AW24: =IF(AND(Param.SonstigEinmaligKonto5="Festgeld",$A24=Param.SonstigEinmaligJahr5),Param.SonstigEinmaligBetrag5,0) -> 0 | AX24: =IF(AND(Param.SonstigEinmaligKonto6="Festgeld",$A24=Param.SonstigEinmaligJahr6),Param.SonstigEinmaligBetrag6,0) -> 0 | AY24: =IF(AND(Param.SonstigEinmaligKonto7="Festgeld",$A24=Param.SonstigEinmaligJahr7),Param.SonstigEinmaligBetrag7,0) -> 0 | AZ24: =IF(AND(Param.SonstigEinmaligKonto8="Festgeld",$A24=Param.SonstigEinmaligJahr8),Param.SonstigEinmaligBetrag8,0) -> 0 | BA24: =IF(AND(Param.SonstigEinmaligKonto9="Festgeld",$A24=Param.SonstigEinmaligJahr9),Param.SonstigEinmaligBetrag9,0) -> 0 | BB24: =IF(AND(Param.SonstigEinmaligKonto10="Festgeld",$A24=Param.SonstigEinmaligJahr10),Param.SonstigEinmaligBetrag10,0) -> 0 | BC24: =IF(AND(A24>=Param.FireStartjahr,AP24>0),MIN(N24*R24,AP24),0) -> 13325.159 | BD24: =Param.FestgeldZinssatz -> 0.02 | BE24: =(AP24+AQ24-BC24)*BD24 -> 5819.2441 | BF24: =IF(BE24>Param.SparerPauschbetrag,Param.SparerPauschbetrag,BE24) -> 1000 | BG24: =BE24-BF24 -> 4819.2441 | BH24: =BG24*Param.KapSt -> 1271.0756 | BI24: =BE24-BH24 -> 4548.1685 | BJ24: =AP24+SUM(AQ24:BB24)-BC24+BI24 -> 295510.37 | BK24: =AL24+BJ24 -> 1266342.1 | BL24: =BK24/(1+Param.Inflationsrate)^(A24-Param.Startjahr) -> 792132.06 | BM24: =IF(BK24<N24,A24,"") | BN24: =AH24+BC24 -> 61316.243 | BO24: =SUM(AR24:BB24) -> 0 | BP24: =BN24+(-1*BO24) -> 61316.243 | BQ24: =AI24+BH24 -> 7427.8129 | BR24: =IF(BK24>0,BP24/BK24,0) -> 0.048419968
A25: =A24+1 -> 2046 | B25: =B5+(21-1) -> 50 | C25: =IF(A25<Param.FireStartjahr,0,Param.EntnahmeBetragStart*(1+Param.Inflationsrate)^(A25-Param.Startjahr)) -> 49158.493 | D25: =IF(OR($A25<Param.SonstigRegelmJahrBeginn1,$A25>Param.SonstigRegelmJahrEnd1),0,Param.SonstigRegelmBetragJaehrl1*(1+Param.SonstigRegelmSteig1)^(A25-Param.SonstigRegelmJahrBeginn1)) -> 0 | E25: =IF(OR($A25<Param.SonstigRegelmJahrBeginn2,$A25>Param.SonstigRegelmJahrEnd2),0,Param.SonstigRegelmBetragJaehrl2*(1+Param.SonstigRegelmSteig2)^($A25-Param.SonstigRegelmJahrBeginn2)) -> -7344 | F25: =IF(OR($A25<Param.SonstigRegelmJahrBeginn3,$A25>Param.SonstigRegelmJahrEnd3),0,Param.SonstigRegelmBetragJaehrl3*(1+Param.SonstigRegelmSteig3)^($A25-Param.SonstigRegelmJahrBeginn3)) -> 0 | G25: =IF(OR($A25<Param.SonstigRegelmJahrBeginn4,$A25>Param.SonstigRegelmJahrEnd4),0,Param.SonstigRegelmBetragJaehrl4*(1+Param.SonstigRegelmSteig4)^($A25-Param.SonstigRegelmJahrBeginn4)) -> 0 | H25: =IF(OR($A25<Param.SonstigRegelmJahrBeginn5,$A25>Param.SonstigRegelmJahrEnd5),0,Param.SonstigRegelmBetragJaehrl5*(1+Param.SonstigRegelmSteig5)^($A25-Param.SonstigRegelmJahrBeginn5)) -> 0 | I25: =IF(OR($A25<Param.SonstigRegelmJahrBeginn6,$A25>Param.SonstigRegelmJahrEnd6),0,Param.SonstigRegelmBetragJaehrl6*(1+Param.SonstigRegelmSteig6)^($A25-Param.SonstigRegelmJahrBeginn6)) -> 0 | J25: =IF(OR($A25<Param.SonstigRegelmJahrBeginn7,$A25>Param.SonstigRegelmJahrEnd7),0,Param.SonstigRegelmBetragJaehrl7*(1+Param.SonstigRegelmSteig7)^($A25-Param.SonstigRegelmJahrBeginn7)) -> 0 | K25: =IF(OR($A25<Param.SonstigRegelmJahrBeginn8,$A25>Param.SonstigRegelmJahrEnd8),0,Param.SonstigRegelmBetragJaehrl8*(1+Param.SonstigRegelmSteig8)^($A25-Param.SonstigRegelmJahrBeginn8)) -> 0 | L25: =IF(OR($A25<Param.SonstigRegelmJahrBeginn9,$A25>Param.SonstigRegelmJahrEnd9),0,Param.SonstigRegelmBetragJaehrl9*(1+Param.SonstigRegelmSteig9)^($A25-Param.SonstigRegelmJahrBeginn9)) -> 0 | M25: =IF(OR($A25<Param.SonstigRegelmJahrBeginn10,$A25>Param.SonstigRegelmJahrEnd10),0,Param.SonstigRegelmBetragJaehrl10*(1+Param.SonstigRegelmSteig10)^($A25-Param.SonstigRegelmJahrBeginn10)) -> 0 | N25: =MAX(0,C25-SUM(D25:M25)) -> 56502.493 | O25: =IF(N25<=0,SUM(D25:M25)-C25,0) -> 0 | P25: =S25+AP25 -> 1266342.1 | Q25: =IF(P25>0,S25/P25,0) -> 0.76664254 | R25: =IF(P25>0,AP25/P25,0) -> 0.23335746 | S25: =AL24 -> 970831.69 | T25: =AM24 -> 693975.52 | U25: =IF(A25<Param.FireStartjahr,Param.SparrateDepotMonatl*12*(1+Param.SparrateDynamikJaehrl)^($A25-Param.Startjahr),0) -> 0 | V25: =IF(AND(Param.SonstigEinmaligKonto1="Depot",$A25=Param.SonstigEinmaligJahr1),Param.SonstigEinmaligBetrag1,0) -> 0 | W25: =IF(AND(Param.SonstigEinmaligKonto2="Depot",$A25=Param.SonstigEinmaligJahr2),Param.SonstigEinmaligBetrag2,0) -> 0 | X25: =IF(AND(Param.SonstigEinmaligKonto3="Depot",$A25=Param.SonstigEinmaligJahr3),Param.SonstigEinmaligBetrag3,0) -> 0 | Y25: =IF(AND(Param.SonstigEinmaligKonto4="Depot",$A25=Param.SonstigEinmaligJahr4),Param.SonstigEinmaligBetrag4,0) -> 0 | Z25: =IF(AND(Param.SonstigEinmaligKonto5="Depot",$A25=Param.SonstigEinmaligJahr5),Param.SonstigEinmaligBetrag5,0) -> 0 | AA25: =IF(AND(Param.SonstigEinmaligKonto6="Depot",$A25=Param.SonstigEinmaligJahr6),Param.SonstigEinmaligBetrag6,0) -> 0 | AB25: =IF(AND(Param.SonstigEinmaligKonto7="Depot",$A25=Param.SonstigEinmaligJahr7),Param.SonstigEinmaligBetrag7,0) -> 0 | AC25: =IF(AND(Param.SonstigEinmaligKonto8="Depot",$A25=Param.SonstigEinmaligJahr8),Param.SonstigEinmaligBetrag8,0) -> 0 | AD25: =IF(AND(Param.SonstigEinmaligKonto9="Depot",$A25=Param.SonstigEinmaligJahr9),Param.SonstigEinmaligBetrag9,0) -> 0 | AE25: =IF(AND(Param.SonstigEinmaligKonto10="Depot",$A25=Param.SonstigEinmaligJahr10),Param.SonstigEinmaligBetrag10,0) -> 0 | AF25: =Param.SparerPauschbetrag-BF25 -> 0 | AG25: =IF(AND(A25>=Param.FireStartjahr,S25>0),MIN(N25*Q25,S25),0) -> 43317.215 | AH25: =IF(AG25<=0,0,IF(S25<=0,0,AG25/(1-MAX(0,((T25/S25)*(1-Param.Teilfreistellung)-MIN(AF25,AG25)/AG25)*Param.KapSt)))) -> 49903.171 | AI25: =AH25-AG25 -> 6585.9565 | AJ25: =T25-AH25*(T25/S25) -> 658303.45 | AK25: =S25-AH25 -> 920928.52 | AL25: =FV(AO25,12,-(U25/12),-AK25,0) -> 985393.52 | AM25: =AJ25+AL25-AK25-U25 -> 722768.44 | AN25: =AM25/AL25 -> 0.73348204 | AO25: =(1+IF(AND(A25>=Param.DepotRenditeSpezBeginn1,A25<=Param.DepotRenditeSpezEnde1),Param.DepotRenditeSpezProz1,IF(AND(A25>=Param.DepotRenditeSpezBeginn2,A25<=Param.DepotRenditeSpezEnde2),Param.DepotRenditeSpezProz2,IF(AND(A25>=Param.DepotRenditeSpezBeginn3,A25<=Param.DepotRenditeSpezEnde3),Param.DepotRenditeSpezProz3,IF(AND(A25>=Param.DepotRenditeSpezBeginn4,A25<=Param.DepotRenditeSpezEnde4),Param.DepotRenditeSpezProz4,IF(AND(A25>=Param.DepotRenditeSpezBeginn5,A25<=Param.DepotRenditeSpezEnde5),Param.DepotRenditeSpezProz5,Param.DepotRenditeDefault))))))^(1/12)-1 -> 0.0056541454 | AP25: =BJ24 -> 295510.37 | AQ25: =IF(A25<Param.FireStartjahr,Param.SparrateFestgeldMonatl*12*(1+Param.SparrateDynamikJaehrl)^($A25-Param.Startjahr),0) -> 0 | AR25: =O25 -> 0 | AS25: =IF(AND(Param.SonstigEinmaligKonto1="Festgeld",$A25=Param.SonstigEinmaligJahr1),Param.SonstigEinmaligBetrag1,0) -> 0 | AT25: =IF(AND(Param.SonstigEinmaligKonto2="Festgeld",$A25=Param.SonstigEinmaligJahr2),Param.SonstigEinmaligBetrag2,0) -> 0 | AU25: =IF(AND(Param.SonstigEinmaligKonto3="Festgeld",$A25=Param.SonstigEinmaligJahr3),Param.SonstigEinmaligBetrag3,0) -> 0 | AV25: =IF(AND(Param.SonstigEinmaligKonto4="Festgeld",$A25=Param.SonstigEinmaligJahr4),Param.SonstigEinmaligBetrag4,0) -> 0 | AW25: =IF(AND(Param.SonstigEinmaligKonto5="Festgeld",$A25=Param.SonstigEinmaligJahr5),Param.SonstigEinmaligBetrag5,0) -> 0 | AX25: =IF(AND(Param.SonstigEinmaligKonto6="Festgeld",$A25=Param.SonstigEinmaligJahr6),Param.SonstigEinmaligBetrag6,0) -> 0 | AY25: =IF(AND(Param.SonstigEinmaligKonto7="Festgeld",$A25=Param.SonstigEinmaligJahr7),Param.SonstigEinmaligBetrag7,0) -> 0 | AZ25: =IF(AND(Param.SonstigEinmaligKonto8="Festgeld",$A25=Param.SonstigEinmaligJahr8),Param.SonstigEinmaligBetrag8,0) -> 0 | BA25: =IF(AND(Param.SonstigEinmaligKonto9="Festgeld",$A25=Param.SonstigEinmaligJahr9),Param.SonstigEinmaligBetrag9,0) -> 0 | BB25: =IF(AND(Param.SonstigEinmaligKonto10="Festgeld",$A25=Param.SonstigEinmaligJahr10),Param.SonstigEinmaligBetrag10,0) -> 0 | BC25: =IF(AND(A25>=Param.FireStartjahr,AP25>0),MIN(N25*R25,AP25),0) -> 13185.279 | BD25: =Param.FestgeldZinssatz -> 0.02 | BE25: =(AP25+AQ25-BC25)*BD25 -> 5646.5019 | BF25: =IF(BE25>Param.SparerPauschbetrag,Param.SparerPauschbetrag,BE25) -> 1000 | BG25: =BE25-BF25 -> 4646.5019 | BH25: =BG25*Param.KapSt -> 1225.5149 | BI25: =BE25-BH25 -> 4420.987 | BJ25: =AP25+SUM(AQ25:BB25)-BC25+BI25 -> 286746.08 | BK25: =AL25+BJ25 -> 1272139.6 | BL25: =BK25/(1+Param.Inflationsrate)^(A25-Param.Startjahr) -> 776349.83 | BM25: =IF(BK25<N25,A25,"") | BN25: =AH25+BC25 -> 63088.45 | BO25: =SUM(AR25:BB25) -> 0 | BP25: =BN25+(-1*BO25) -> 63088.45 | BQ25: =AI25+BH25 -> 7811.4714 | BR25: =IF(BK25>0,BP25/BK25,0) -> 0.049592395
A26: =A25+1 -> 2047 | B26: =B5+(22-1) -> 51 | C26: =IF(A26<Param.FireStartjahr,0,Param.EntnahmeBetragStart*(1+Param.Inflationsrate)^(A26-Param.Startjahr)) -> 50387.456 | D26: =IF(OR($A26<Param.SonstigRegelmJahrBeginn1,$A26>Param.SonstigRegelmJahrEnd1),0,Param.SonstigRegelmBetragJaehrl1*(1+Param.SonstigRegelmSteig1)^(A26-Param.SonstigRegelmJahrBeginn1)) -> 0 | E26: =IF(OR($A26<Param.SonstigRegelmJahrBeginn2,$A26>Param.SonstigRegelmJahrEnd2),0,Param.SonstigRegelmBetragJaehrl2*(1+Param.SonstigRegelmSteig2)^($A26-Param.SonstigRegelmJahrBeginn2)) -> -7490.88 | F26: =IF(OR($A26<Param.SonstigRegelmJahrBeginn3,$A26>Param.SonstigRegelmJahrEnd3),0,Param.SonstigRegelmBetragJaehrl3*(1+Param.SonstigRegelmSteig3)^($A26-Param.SonstigRegelmJahrBeginn3)) -> 0 | G26: =IF(OR($A26<Param.SonstigRegelmJahrBeginn4,$A26>Param.SonstigRegelmJahrEnd4),0,Param.SonstigRegelmBetragJaehrl4*(1+Param.SonstigRegelmSteig4)^($A26-Param.SonstigRegelmJahrBeginn4)) -> 0 | H26: =IF(OR($A26<Param.SonstigRegelmJahrBeginn5,$A26>Param.SonstigRegelmJahrEnd5),0,Param.SonstigRegelmBetragJaehrl5*(1+Param.SonstigRegelmSteig5)^($A26-Param.SonstigRegelmJahrBeginn5)) -> 0 | I26: =IF(OR($A26<Param.SonstigRegelmJahrBeginn6,$A26>Param.SonstigRegelmJahrEnd6),0,Param.SonstigRegelmBetragJaehrl6*(1+Param.SonstigRegelmSteig6)^($A26-Param.SonstigRegelmJahrBeginn6)) -> 0 | J26: =IF(OR($A26<Param.SonstigRegelmJahrBeginn7,$A26>Param.SonstigRegelmJahrEnd7),0,Param.SonstigRegelmBetragJaehrl7*(1+Param.SonstigRegelmSteig7)^($A26-Param.SonstigRegelmJahrBeginn7)) -> 0 | K26: =IF(OR($A26<Param.SonstigRegelmJahrBeginn8,$A26>Param.SonstigRegelmJahrEnd8),0,Param.SonstigRegelmBetragJaehrl8*(1+Param.SonstigRegelmSteig8)^($A26-Param.SonstigRegelmJahrBeginn8)) -> 0 | L26: =IF(OR($A26<Param.SonstigRegelmJahrBeginn9,$A26>Param.SonstigRegelmJahrEnd9),0,Param.SonstigRegelmBetragJaehrl9*(1+Param.SonstigRegelmSteig9)^($A26-Param.SonstigRegelmJahrBeginn9)) -> 0 | M26: =IF(OR($A26<Param.SonstigRegelmJahrBeginn10,$A26>Param.SonstigRegelmJahrEnd10),0,Param.SonstigRegelmBetragJaehrl10*(1+Param.SonstigRegelmSteig10)^($A26-Param.SonstigRegelmJahrBeginn10)) -> 0 | N26: =MAX(0,C26-SUM(D26:M26)) -> 57878.336 | O26: =IF(N26<=0,SUM(D26:M26)-C26,0) -> 0 | P26: =S26+AP26 -> 1272139.6 | Q26: =IF(P26>0,S26/P26,0) -> 0.77459543 | R26: =IF(P26>0,AP26/P26,0) -> 0.22540457 | S26: =AL25 -> 985393.52 | T26: =AM25 -> 722768.44 | U26: =IF(A26<Param.FireStartjahr,Param.SparrateDepotMonatl*12*(1+Param.SparrateDynamikJaehrl)^($A26-Param.Startjahr),0) -> 0 | V26: =IF(AND(Param.SonstigEinmaligKonto1="Depot",$A26=Param.SonstigEinmaligJahr1),Param.SonstigEinmaligBetrag1,0) -> 0 | W26: =IF(AND(Param.SonstigEinmaligKonto2="Depot",$A26=Param.SonstigEinmaligJahr2),Param.SonstigEinmaligBetrag2,0) -> 0 | X26: =IF(AND(Param.SonstigEinmaligKonto3="Depot",$A26=Param.SonstigEinmaligJahr3),Param.SonstigEinmaligBetrag3,0) -> 0 | Y26: =IF(AND(Param.SonstigEinmaligKonto4="Depot",$A26=Param.SonstigEinmaligJahr4),Param.SonstigEinmaligBetrag4,0) -> 0 | Z26: =IF(AND(Param.SonstigEinmaligKonto5="Depot",$A26=Param.SonstigEinmaligJahr5),Param.SonstigEinmaligBetrag5,0) -> 0 | AA26: =IF(AND(Param.SonstigEinmaligKonto6="Depot",$A26=Param.SonstigEinmaligJahr6),Param.SonstigEinmaligBetrag6,0) -> 0 | AB26: =IF(AND(Param.SonstigEinmaligKonto7="Depot",$A26=Param.SonstigEinmaligJahr7),Param.SonstigEinmaligBetrag7,0) -> 0 | AC26: =IF(AND(Param.SonstigEinmaligKonto8="Depot",$A26=Param.SonstigEinmaligJahr8),Param.SonstigEinmaligBetrag8,0) -> 0 | AD26: =IF(AND(Param.SonstigEinmaligKonto9="Depot",$A26=Param.SonstigEinmaligJahr9),Param.SonstigEinmaligBetrag9,0) -> 0 | AE26: =IF(AND(Param.SonstigEinmaligKonto10="Depot",$A26=Param.SonstigEinmaligJahr10),Param.SonstigEinmaligBetrag10,0) -> 0 | AF26: =Param.SparerPauschbetrag-BF26 -> 0 | AG26: =IF(AND(A26>=Param.FireStartjahr,S26>0),MIN(N26*Q26,S26),0) -> 44832.294 | AH26: =IF(AG26<=0,0,IF(S26<=0,0,AG26/(1-MAX(0,((T26/S26)*(1-Param.Teilfreistellung)-MIN(AF26,AG26)/AG26)*Param.KapSt)))) -> 51854.367 | AI26: =AH26-AG26 -> 7022.0728 | AJ26: =T26-AH26*(T26/S26) -> 684734.2 | AK26: =S26-AH26 -> 933539.15 | AL26: =FV(AO26,12,-(U26/12),-AK26,0) -> 998886.89 | AM26: =AJ26+AL26-AK26-U26 -> 750081.94 | AN26: =AM26/AL26 -> 0.75091779 | AO26: =(1+IF(AND(A26>=Param.DepotRenditeSpezBeginn1,A26<=Param.DepotRenditeSpezEnde1),Param.DepotRenditeSpezProz1,IF(AND(A26>=Param.DepotRenditeSpezBeginn2,A26<=Param.DepotRenditeSpezEnde2),Param.DepotRenditeSpezProz2,IF(AND(A26>=Param.DepotRenditeSpezBeginn3,A26<=Param.DepotRenditeSpezEnde3),Param.DepotRenditeSpezProz3,IF(AND(A26>=Param.DepotRenditeSpezBeginn4,A26<=Param.DepotRenditeSpezEnde4),Param.DepotRenditeSpezProz4,IF(AND(A26>=Param.DepotRenditeSpezBeginn5,A26<=Param.DepotRenditeSpezEnde5),Param.DepotRenditeSpezProz5,Param.DepotRenditeDefault))))))^(1/12)-1 -> 0.0056541454 | AP26: =BJ25 -> 286746.08 | AQ26: =IF(A26<Param.FireStartjahr,Param.SparrateFestgeldMonatl*12*(1+Param.SparrateDynamikJaehrl)^($A26-Param.Startjahr),0) -> 0 | AR26: =O26 -> 0 | AS26: =IF(AND(Param.SonstigEinmaligKonto1="Festgeld",$A26=Param.SonstigEinmaligJahr1),Param.SonstigEinmaligBetrag1,0) -> 0 | AT26: =IF(AND(Param.SonstigEinmaligKonto2="Festgeld",$A26=Param.SonstigEinmaligJahr2),Param.SonstigEinmaligBetrag2,0) -> 0 | AU26: =IF(AND(Param.SonstigEinmaligKonto3="Festgeld",$A26=Param.SonstigEinmaligJahr3),Param.SonstigEinmaligBetrag3,0) -> 0 | AV26: =IF(AND(Param.SonstigEinmaligKonto4="Festgeld",$A26=Param.SonstigEinmaligJahr4),Param.SonstigEinmaligBetrag4,0) -> 0 | AW26: =IF(AND(Param.SonstigEinmaligKonto5="Festgeld",$A26=Param.SonstigEinmaligJahr5),Param.SonstigEinmaligBetrag5,0) -> 0 | AX26: =IF(AND(Param.SonstigEinmaligKonto6="Festgeld",$A26=Param.SonstigEinmaligJahr6),Param.SonstigEinmaligBetrag6,0) -> 0 | AY26: =IF(AND(Param.SonstigEinmaligKonto7="Festgeld",$A26=Param.SonstigEinmaligJahr7),Param.SonstigEinmaligBetrag7,0) -> 0 | AZ26: =IF(AND(Param.SonstigEinmaligKonto8="Festgeld",$A26=Param.SonstigEinmaligJahr8),Param.SonstigEinmaligBetrag8,0) -> 0 | BA26: =IF(AND(Param.SonstigEinmaligKonto9="Festgeld",$A26=Param.SonstigEinmaligJahr9),Param.SonstigEinmaligBetrag9,0) -> 0 | BB26: =IF(AND(Param.SonstigEinmaligKonto10="Festgeld",$A26=Param.SonstigEinmaligJahr10),Param.SonstigEinmaligBetrag10,0) -> 0 | BC26: =IF(AND(A26>=Param.FireStartjahr,AP26>0),MIN(N26*R26,AP26),0) -> 13046.041 | BD26: =Param.FestgeldZinssatz -> 0.02 | BE26: =(AP26+AQ26-BC26)*BD26 -> 5474.0008 | BF26: =IF(BE26>Param.SparerPauschbetrag,Param.SparerPauschbetrag,BE26) -> 1000 | BG26: =BE26-BF26 -> 4474.0008 | BH26: =BG26*Param.KapSt -> 1180.0177 | BI26: =BE26-BH26 -> 4293.9831 | BJ26: =AP26+SUM(AQ26:BB26)-BC26+BI26 -> 277994.02 | BK26: =AL26+BJ26 -> 1276880.9 | BL26: =BK26/(1+Param.Inflationsrate)^(A26-Param.Startjahr) -> 760237.39 | BM26: =IF(BK26<N26,A26,"") | BN26: =AH26+BC26 -> 64900.408 | BO26: =SUM(AR26:BB26) -> 0 | BP26: =BN26+(-1*BO26) -> 64900.408 | BQ26: =AI26+BH26 -> 8202.0905 | BR26: =IF(BK26>0,BP26/BK26,0) -> 0.050827299
A27: =A26+1 -> 2048 | B27: =B5+(23-1) -> 52 | C27: =IF(A27<Param.FireStartjahr,0,Param.EntnahmeBetragStart*(1+Param.Inflationsrate)^(A27-Param.Startjahr)) -> 51647.142 | D27: =IF(OR($A27<Param.SonstigRegelmJahrBeginn1,$A27>Param.SonstigRegelmJahrEnd1),0,Param.SonstigRegelmBetragJaehrl1*(1+Param.SonstigRegelmSteig1)^(A27-Param.SonstigRegelmJahrBeginn1)) -> 0 | E27: =IF(OR($A27<Param.SonstigRegelmJahrBeginn2,$A27>Param.SonstigRegelmJahrEnd2),0,Param.SonstigRegelmBetragJaehrl2*(1+Param.SonstigRegelmSteig2)^($A27-Param.SonstigRegelmJahrBeginn2)) -> -7640.6976 | F27: =IF(OR($A27<Param.SonstigRegelmJahrBeginn3,$A27>Param.SonstigRegelmJahrEnd3),0,Param.SonstigRegelmBetragJaehrl3*(1+Param.SonstigRegelmSteig3)^($A27-Param.SonstigRegelmJahrBeginn3)) -> 0 | G27: =IF(OR($A27<Param.SonstigRegelmJahrBeginn4,$A27>Param.SonstigRegelmJahrEnd4),0,Param.SonstigRegelmBetragJaehrl4*(1+Param.SonstigRegelmSteig4)^($A27-Param.SonstigRegelmJahrBeginn4)) -> 0 | H27: =IF(OR($A27<Param.SonstigRegelmJahrBeginn5,$A27>Param.SonstigRegelmJahrEnd5),0,Param.SonstigRegelmBetragJaehrl5*(1+Param.SonstigRegelmSteig5)^($A27-Param.SonstigRegelmJahrBeginn5)) -> 0 | I27: =IF(OR($A27<Param.SonstigRegelmJahrBeginn6,$A27>Param.SonstigRegelmJahrEnd6),0,Param.SonstigRegelmBetragJaehrl6*(1+Param.SonstigRegelmSteig6)^($A27-Param.SonstigRegelmJahrBeginn6)) -> 0 | J27: =IF(OR($A27<Param.SonstigRegelmJahrBeginn7,$A27>Param.SonstigRegelmJahrEnd7),0,Param.SonstigRegelmBetragJaehrl7*(1+Param.SonstigRegelmSteig7)^($A27-Param.SonstigRegelmJahrBeginn7)) -> 0 | K27: =IF(OR($A27<Param.SonstigRegelmJahrBeginn8,$A27>Param.SonstigRegelmJahrEnd8),0,Param.SonstigRegelmBetragJaehrl8*(1+Param.SonstigRegelmSteig8)^($A27-Param.SonstigRegelmJahrBeginn8)) -> 0 | L27: =IF(OR($A27<Param.SonstigRegelmJahrBeginn9,$A27>Param.SonstigRegelmJahrEnd9),0,Param.SonstigRegelmBetragJaehrl9*(1+Param.SonstigRegelmSteig9)^($A27-Param.SonstigRegelmJahrBeginn9)) -> 0 | M27: =IF(OR($A27<Param.SonstigRegelmJahrBeginn10,$A27>Param.SonstigRegelmJahrEnd10),0,Param.SonstigRegelmBetragJaehrl10*(1+Param.SonstigRegelmSteig10)^($A27-Param.SonstigRegelmJahrBeginn10)) -> 0 | N27: =MAX(0,C27-SUM(D27:M27)) -> 59287.84 | O27: =IF(N27<=0,SUM(D27:M27)-C27,0) -> 0 | P27: =S27+AP27 -> 1276880.9 | Q27: =IF(P27>0,S27/P27,0) -> 0.78228665 | R27: =IF(P27>0,AP27/P27,0) -> 0.21771335 | S27: =AL26 -> 998886.89 | T27: =AM26 -> 750081.94 | U27: =IF(A27<Param.FireStartjahr,Param.SparrateDepotMonatl*12*(1+Param.SparrateDynamikJaehrl)^($A27-Param.Startjahr),0) -> 0 | V27: =IF(AND(Param.SonstigEinmaligKonto1="Depot",$A27=Param.SonstigEinmaligJahr1),Param.SonstigEinmaligBetrag1,0) -> 0 | W27: =IF(AND(Param.SonstigEinmaligKonto2="Depot",$A27=Param.SonstigEinmaligJahr2),Param.SonstigEinmaligBetrag2,0) -> 0 | X27: =IF(AND(Param.SonstigEinmaligKonto3="Depot",$A27=Param.SonstigEinmaligJahr3),Param.SonstigEinmaligBetrag3,0) -> 0 | Y27: =IF(AND(Param.SonstigEinmaligKonto4="Depot",$A27=Param.SonstigEinmaligJahr4),Param.SonstigEinmaligBetrag4,0) -> 0 | Z27: =IF(AND(Param.SonstigEinmaligKonto5="Depot",$A27=Param.SonstigEinmaligJahr5),Param.SonstigEinmaligBetrag5,0) -> 0 | AA27: =IF(AND(Param.SonstigEinmaligKonto6="Depot",$A27=Param.SonstigEinmaligJahr6),Param.SonstigEinmaligBetrag6,0) -> 0 | AB27: =IF(AND(Param.SonstigEinmaligKonto7="Depot",$A27=Param.SonstigEinmaligJahr7),Param.SonstigEinmaligBetrag7,0) -> 0 | AC27: =IF(AND(Param.SonstigEinmaligKonto8="Depot",$A27=Param.SonstigEinmaligJahr8),Param.SonstigEinmaligBetrag8,0) -> 0 | AD27: =IF(AND(Param.SonstigEinmaligKonto9="Depot",$A27=Param.SonstigEinmaligJahr9),Param.SonstigEinmaligBetrag9,0) -> 0 | AE27: =IF(AND(Param.SonstigEinmaligKonto10="Depot",$A27=Param.SonstigEinmaligJahr10),Param.SonstigEinmaligBetrag10,0) -> 0 | AF27: =Param.SparerPauschbetrag-BF27 -> 0 | AG27: =IF(AND(A27>=Param.FireStartjahr,S27>0),MIN(N27*Q27,S27),0) -> 46380.085 | AH27: =IF(AG27<=0,0,IF(S27<=0,0,AG27/(1-MAX(0,((T27/S27)*(1-Param.Teilfreistellung)-MIN(AF27,AG27)/AG27)*Param.KapSt)))) -> 53845.068 | AI27: =AH27-AG27 -> 7464.9832 | AJ27: =T27-AH27*(T27/S27) -> 709648.72 | AK27: =S27-AH27 -> 945041.82 | AL27: =FV(AO27,12,-(U27/12),-AK27,0) -> 1001744.3 | AM27: =AJ27+AL27-AK27-U27 -> 766351.23 | AN27: =AM27/AL27 -> 0.76501678 | AO27: =(1+IF(AND(A27>=Param.DepotRenditeSpezBeginn1,A27<=Param.DepotRenditeSpezEnde1),Param.DepotRenditeSpezProz1,IF(AND(A27>=Param.DepotRenditeSpezBeginn2,A27<=Param.DepotRenditeSpezEnde2),Param.DepotRenditeSpezProz2,IF(AND(A27>=Param.DepotRenditeSpezBeginn3,A27<=Param.DepotRenditeSpezEnde3),Param.DepotRenditeSpezProz3,IF(AND(A27>=Param.DepotRenditeSpezBeginn4,A27<=Param.DepotRenditeSpezEnde4),Param.DepotRenditeSpezProz4,IF(AND(A27>=Param.DepotRenditeSpezBeginn5,A27<=Param.DepotRenditeSpezEnde5),Param.DepotRenditeSpezProz5,Param.DepotRenditeDefault))))))^(1/12)-1 -> 0.0048675506 | AP27: =BJ26 -> 277994.02 | AQ27: =IF(A27<Param.FireStartjahr,Param.SparrateFestgeldMonatl*12*(1+Param.SparrateDynamikJaehrl)^($A27-Param.Startjahr),0) -> 0 | AR27: =O27 -> 0 | AS27: =IF(AND(Param.SonstigEinmaligKonto1="Festgeld",$A27=Param.SonstigEinmaligJahr1),Param.SonstigEinmaligBetrag1,0) -> 0 | AT27: =IF(AND(Param.SonstigEinmaligKonto2="Festgeld",$A27=Param.SonstigEinmaligJahr2),Param.SonstigEinmaligBetrag2,0) -> 0 | AU27: =IF(AND(Param.SonstigEinmaligKonto3="Festgeld",$A27=Param.SonstigEinmaligJahr3),Param.SonstigEinmaligBetrag3,0) -> 0 | AV27: =IF(AND(Param.SonstigEinmaligKonto4="Festgeld",$A27=Param.SonstigEinmaligJahr4),Param.SonstigEinmaligBetrag4,0) -> 0 | AW27: =IF(AND(Param.SonstigEinmaligKonto5="Festgeld",$A27=Param.SonstigEinmaligJahr5),Param.SonstigEinmaligBetrag5,0) -> 0 | AX27: =IF(AND(Param.SonstigEinmaligKonto6="Festgeld",$A27=Param.SonstigEinmaligJahr6),Param.SonstigEinmaligBetrag6,0) -> 0 | AY27: =IF(AND(Param.SonstigEinmaligKonto7="Festgeld",$A27=Param.SonstigEinmaligJahr7),Param.SonstigEinmaligBetrag7,0) -> 0 | AZ27: =IF(AND(Param.SonstigEinmaligKonto8="Festgeld",$A27=Param.SonstigEinmaligJahr8),Param.SonstigEinmaligBetrag8,0) -> 0 | BA27: =IF(AND(Param.SonstigEinmaligKonto9="Festgeld",$A27=Param.SonstigEinmaligJahr9),Param.SonstigEinmaligBetrag9,0) -> 0 | BB27: =IF(AND(Param.SonstigEinmaligKonto10="Festgeld",$A27=Param.SonstigEinmaligJahr10),Param.SonstigEinmaligBetrag10,0) -> 0 | BC27: =IF(AND(A27>=Param.FireStartjahr,AP27>0),MIN(N27*R27,AP27),0) -> 12907.754 | BD27: =Param.FestgeldZinssatz -> 0.02 | BE27: =(AP27+AQ27-BC27)*BD27 -> 5301.7254 | BF27: =IF(BE27>Param.SparerPauschbetrag,Param.SparerPauschbetrag,BE27) -> 1000 | BG27: =BE27-BF27 -> 4301.7254 | BH27: =BG27*Param.KapSt -> 1134.5801 | BI27: =BE27-BH27 -> 4167.1453 | BJ27: =AP27+SUM(AQ27:BB27)-BC27+BI27 -> 269253.41 | BK27: =AL27+BJ27 -> 1270997.7 | BL27: =BK27/(1+Param.Inflationsrate)^(A27-Param.Startjahr) -> 738277.69 | BM27: =IF(BK27<N27,A27,"") | BN27: =AH27+BC27 -> 66752.823 | BO27: =SUM(AR27:BB27) -> 0 | BP27: =BN27+(-1*BO27) -> 66752.823 | BQ27: =AI27+BH27 -> 8599.5633 | BR27: =IF(BK27>0,BP27/BK27,0) -> 0.052520017
A28: =A27+1 -> 2049 | B28: =B5+(24-1) -> 53 | C28: =IF(A28<Param.FireStartjahr,0,Param.EntnahmeBetragStart*(1+Param.Inflationsrate)^(A28-Param.Startjahr)) -> 52938.32 | D28: =IF(OR($A28<Param.SonstigRegelmJahrBeginn1,$A28>Param.SonstigRegelmJahrEnd1),0,Param.SonstigRegelmBetragJaehrl1*(1+Param.SonstigRegelmSteig1)^(A28-Param.SonstigRegelmJahrBeginn1)) -> 0 | E28: =IF(OR($A28<Param.SonstigRegelmJahrBeginn2,$A28>Param.SonstigRegelmJahrEnd2),0,Param.SonstigRegelmBetragJaehrl2*(1+Param.SonstigRegelmSteig2)^($A28-Param.SonstigRegelmJahrBeginn2)) -> -7793.5116 | F28: =IF(OR($A28<Param.SonstigRegelmJahrBeginn3,$A28>Param.SonstigRegelmJahrEnd3),0,Param.SonstigRegelmBetragJaehrl3*(1+Param.SonstigRegelmSteig3)^($A28-Param.SonstigRegelmJahrBeginn3)) -> 0 | G28: =IF(OR($A28<Param.SonstigRegelmJahrBeginn4,$A28>Param.SonstigRegelmJahrEnd4),0,Param.SonstigRegelmBetragJaehrl4*(1+Param.SonstigRegelmSteig4)^($A28-Param.SonstigRegelmJahrBeginn4)) -> 0 | H28: =IF(OR($A28<Param.SonstigRegelmJahrBeginn5,$A28>Param.SonstigRegelmJahrEnd5),0,Param.SonstigRegelmBetragJaehrl5*(1+Param.SonstigRegelmSteig5)^($A28-Param.SonstigRegelmJahrBeginn5)) -> 0 | I28: =IF(OR($A28<Param.SonstigRegelmJahrBeginn6,$A28>Param.SonstigRegelmJahrEnd6),0,Param.SonstigRegelmBetragJaehrl6*(1+Param.SonstigRegelmSteig6)^($A28-Param.SonstigRegelmJahrBeginn6)) -> 0 | J28: =IF(OR($A28<Param.SonstigRegelmJahrBeginn7,$A28>Param.SonstigRegelmJahrEnd7),0,Param.SonstigRegelmBetragJaehrl7*(1+Param.SonstigRegelmSteig7)^($A28-Param.SonstigRegelmJahrBeginn7)) -> 0 | K28: =IF(OR($A28<Param.SonstigRegelmJahrBeginn8,$A28>Param.SonstigRegelmJahrEnd8),0,Param.SonstigRegelmBetragJaehrl8*(1+Param.SonstigRegelmSteig8)^($A28-Param.SonstigRegelmJahrBeginn8)) -> 0 | L28: =IF(OR($A28<Param.SonstigRegelmJahrBeginn9,$A28>Param.SonstigRegelmJahrEnd9),0,Param.SonstigRegelmBetragJaehrl9*(1+Param.SonstigRegelmSteig9)^($A28-Param.SonstigRegelmJahrBeginn9)) -> 0 | M28: =IF(OR($A28<Param.SonstigRegelmJahrBeginn10,$A28>Param.SonstigRegelmJahrEnd10),0,Param.SonstigRegelmBetragJaehrl10*(1+Param.SonstigRegelmSteig10)^($A28-Param.SonstigRegelmJahrBeginn10)) -> 0 | N28: =MAX(0,C28-SUM(D28:M28)) -> 60731.832 | O28: =IF(N28<=0,SUM(D28:M28)-C28,0) -> 0 | P28: =S28+AP28 -> 1270997.7 | Q28: =IF(P28>0,S28/P28,0) -> 0.78815587 | R28: =IF(P28>0,AP28/P28,0) -> 0.21184413 | S28: =AL27 -> 1001744.3 | T28: =AM27 -> 766351.23 | U28: =IF(A28<Param.FireStartjahr,Param.SparrateDepotMonatl*12*(1+Param.SparrateDynamikJaehrl)^($A28-Param.Startjahr),0) -> 0 | V28: =IF(AND(Param.SonstigEinmaligKonto1="Depot",$A28=Param.SonstigEinmaligJahr1),Param.SonstigEinmaligBetrag1,0) -> 0 | W28: =IF(AND(Param.SonstigEinmaligKonto2="Depot",$A28=Param.SonstigEinmaligJahr2),Param.SonstigEinmaligBetrag2,0) -> 0 | X28: =IF(AND(Param.SonstigEinmaligKonto3="Depot",$A28=Param.SonstigEinmaligJahr3),Param.SonstigEinmaligBetrag3,0) -> 0 | Y28: =IF(AND(Param.SonstigEinmaligKonto4="Depot",$A28=Param.SonstigEinmaligJahr4),Param.SonstigEinmaligBetrag4,0) -> 0 | Z28: =IF(AND(Param.SonstigEinmaligKonto5="Depot",$A28=Param.SonstigEinmaligJahr5),Param.SonstigEinmaligBetrag5,0) -> 0 | AA28: =IF(AND(Param.SonstigEinmaligKonto6="Depot",$A28=Param.SonstigEinmaligJahr6),Param.SonstigEinmaligBetrag6,0) -> 0 | AB28: =IF(AND(Param.SonstigEinmaligKonto7="Depot",$A28=Param.SonstigEinmaligJahr7),Param.SonstigEinmaligBetrag7,0) -> 0 | AC28: =IF(AND(Param.SonstigEinmaligKonto8="Depot",$A28=Param.SonstigEinmaligJahr8),Param.SonstigEinmaligBetrag8,0) -> 0 | AD28: =IF(AND(Param.SonstigEinmaligKonto9="Depot",$A28=Param.SonstigEinmaligJahr9),Param.SonstigEinmaligBetrag9,0) -> 0 | AE28: =IF(AND(Param.SonstigEinmaligKonto10="Depot",$A28=Param.SonstigEinmaligJahr10),Param.SonstigEinmaligBetrag10,0) -> 0 | AF28: =Param.SparerPauschbetrag-BF28 -> 0 | AG28: =IF(AND(A28>=Param.FireStartjahr,S28>0),MIN(N28*Q28,S28),0) -> 47866.15 | AH28: =IF(AG28<=0,0,IF(S28<=0,0,AG28/(1-MAX(0,((T28/S28)*(1-Param.Teilfreistellung)-MIN(AF28,AG28)/AG28)*Param.KapSt)))) -> 55738.761 | AI28: =AH28-AG28 -> 7872.6107 | AJ28: =T28-AH28*(T28/S28) -> 723710.14 | AK28: =S28-AH28 -> 946005.57 | AL28: =FV(AO28,12,-(U28/12),-AK28,0) -> 1002765.9 | AM28: =AJ28+AL28-AK28-U28 -> 780470.47 | AN28: =AM28/AL28 -> 0.77831772 | AO28: =(1+IF(AND(A28>=Param.DepotRenditeSpezBeginn1,A28<=Param.DepotRenditeSpezEnde1),Param.DepotRenditeSpezProz1,IF(AND(A28>=Param.DepotRenditeSpezBeginn2,A28<=Param.DepotRenditeSpezEnde2),Param.DepotRenditeSpezProz2,IF(AND(A28>=Param.DepotRenditeSpezBeginn3,A28<=Param.DepotRenditeSpezEnde3),Param.DepotRenditeSpezProz3,IF(AND(A28>=Param.DepotRenditeSpezBeginn4,A28<=Param.DepotRenditeSpezEnde4),Param.DepotRenditeSpezProz4,IF(AND(A28>=Param.DepotRenditeSpezBeginn5,A28<=Param.DepotRenditeSpezEnde5),Param.DepotRenditeSpezProz5,Param.DepotRenditeDefault))))))^(1/12)-1 -> 0.0048675506 | AP28: =BJ27 -> 269253.41 | AQ28: =IF(A28<Param.FireStartjahr,Param.SparrateFestgeldMonatl*12*(1+Param.SparrateDynamikJaehrl)^($A28-Param.Startjahr),0) -> 0 | AR28: =O28 -> 0 | AS28: =IF(AND(Param.SonstigEinmaligKonto1="Festgeld",$A28=Param.SonstigEinmaligJahr1),Param.SonstigEinmaligBetrag1,0) -> 0 | AT28: =IF(AND(Param.SonstigEinmaligKonto2="Festgeld",$A28=Param.SonstigEinmaligJahr2),Param.SonstigEinmaligBetrag2,0) -> 0 | AU28: =IF(AND(Param.SonstigEinmaligKonto3="Festgeld",$A28=Param.SonstigEinmaligJahr3),Param.SonstigEinmaligBetrag3,0) -> 0 | AV28: =IF(AND(Param.SonstigEinmaligKonto4="Festgeld",$A28=Param.SonstigEinmaligJahr4),Param.SonstigEinmaligBetrag4,0) -> 0 | AW28: =IF(AND(Param.SonstigEinmaligKonto5="Festgeld",$A28=Param.SonstigEinmaligJahr5),Param.SonstigEinmaligBetrag5,0) -> 0 | AX28: =IF(AND(Param.SonstigEinmaligKonto6="Festgeld",$A28=Param.SonstigEinmaligJahr6),Param.SonstigEinmaligBetrag6,0) -> 0 | AY28: =IF(AND(Param.SonstigEinmaligKonto7="Festgeld",$A28=Param.SonstigEinmaligJahr7),Param.SonstigEinmaligBetrag7,0) -> 0 | AZ28: =IF(AND(Param.SonstigEinmaligKonto8="Festgeld",$A28=Param.SonstigEinmaligJahr8),Param.SonstigEinmaligBetrag8,0) -> 0 | BA28: =IF(AND(Param.SonstigEinmaligKonto9="Festgeld",$A28=Param.SonstigEinmaligJahr9),Param.SonstigEinmaligBetrag9,0) -> 0 | BB28: =IF(AND(Param.SonstigEinmaligKonto10="Festgeld",$A28=Param.SonstigEinmaligJahr10),Param.SonstigEinmaligBetrag10,0) -> 0 | BC28: =IF(AND(A28>=Param.FireStartjahr,AP28>0),MIN(N28*R28,AP28),0) -> 12865.682 | BD28: =Param.FestgeldZinssatz -> 0.02 | BE28: =(AP28+AQ28-BC28)*BD28 -> 5127.7547 | BF28: =IF(BE28>Param.SparerPauschbetrag,Param.SparerPauschbetrag,BE28) -> 1000 | BG28: =BE28-BF28 -> 4127.7547 | BH28: =BG28*Param.KapSt -> 1088.6953 | BI28: =BE28-BH28 -> 4039.0594 | BJ28: =AP28+SUM(AQ28:BB28)-BC28+BI28 -> 260426.79 | BK28: =AL28+BJ28 -> 1263192.7 | BL28: =BK28/(1+Param.Inflationsrate)^(A28-Param.Startjahr) -> 715847.81 | BM28: =IF(BK28<N28,A28,"") | BN28: =AH28+BC28 -> 68604.443 | BO28: =SUM(AR28:BB28) -> 0 | BP28: =BN28+(-1*BO28) -> 68604.443 | BQ28: =AI28+BH28 -> 8961.306 | BR28: =IF(BK28>0,BP28/BK28,0) -> 0.054310354
A29: =A28+1 -> 2050 | B29: =B5+(25-1) -> 54 | C29: =IF(A29<Param.FireStartjahr,0,Param.EntnahmeBetragStart*(1+Param.Inflationsrate)^(A29-Param.Startjahr)) -> 54261.778 | D29: =IF(OR($A29<Param.SonstigRegelmJahrBeginn1,$A29>Param.SonstigRegelmJahrEnd1),0,Param.SonstigRegelmBetragJaehrl1*(1+Param.SonstigRegelmSteig1)^(A29-Param.SonstigRegelmJahrBeginn1)) -> 0 | E29: =IF(OR($A29<Param.SonstigRegelmJahrBeginn2,$A29>Param.SonstigRegelmJahrEnd2),0,Param.SonstigRegelmBetragJaehrl2*(1+Param.SonstigRegelmSteig2)^($A29-Param.SonstigRegelmJahrBeginn2)) -> -7949.3818 | F29: =IF(OR($A29<Param.SonstigRegelmJahrBeginn3,$A29>Param.SonstigRegelmJahrEnd3),0,Param.SonstigRegelmBetragJaehrl3*(1+Param.SonstigRegelmSteig3)^($A29-Param.SonstigRegelmJahrBeginn3)) -> 0 | G29: =IF(OR($A29<Param.SonstigRegelmJahrBeginn4,$A29>Param.SonstigRegelmJahrEnd4),0,Param.SonstigRegelmBetragJaehrl4*(1+Param.SonstigRegelmSteig4)^($A29-Param.SonstigRegelmJahrBeginn4)) -> 0 | H29: =IF(OR($A29<Param.SonstigRegelmJahrBeginn5,$A29>Param.SonstigRegelmJahrEnd5),0,Param.SonstigRegelmBetragJaehrl5*(1+Param.SonstigRegelmSteig5)^($A29-Param.SonstigRegelmJahrBeginn5)) -> 0 | I29: =IF(OR($A29<Param.SonstigRegelmJahrBeginn6,$A29>Param.SonstigRegelmJahrEnd6),0,Param.SonstigRegelmBetragJaehrl6*(1+Param.SonstigRegelmSteig6)^($A29-Param.SonstigRegelmJahrBeginn6)) -> 0 | J29: =IF(OR($A29<Param.SonstigRegelmJahrBeginn7,$A29>Param.SonstigRegelmJahrEnd7),0,Param.SonstigRegelmBetragJaehrl7*(1+Param.SonstigRegelmSteig7)^($A29-Param.SonstigRegelmJahrBeginn7)) -> 0 | K29: =IF(OR($A29<Param.SonstigRegelmJahrBeginn8,$A29>Param.SonstigRegelmJahrEnd8),0,Param.SonstigRegelmBetragJaehrl8*(1+Param.SonstigRegelmSteig8)^($A29-Param.SonstigRegelmJahrBeginn8)) -> 0 | L29: =IF(OR($A29<Param.SonstigRegelmJahrBeginn9,$A29>Param.SonstigRegelmJahrEnd9),0,Param.SonstigRegelmBetragJaehrl9*(1+Param.SonstigRegelmSteig9)^($A29-Param.SonstigRegelmJahrBeginn9)) -> 0 | M29: =IF(OR($A29<Param.SonstigRegelmJahrBeginn10,$A29>Param.SonstigRegelmJahrEnd10),0,Param.SonstigRegelmBetragJaehrl10*(1+Param.SonstigRegelmSteig10)^($A29-Param.SonstigRegelmJahrBeginn10)) -> 0 | N29: =MAX(0,C29-SUM(D29:M29)) -> 62211.16 | O29: =IF(N29<=0,SUM(D29:M29)-C29,0) -> 0 | P29: =S29+AP29 -> 1263192.7 | Q29: =IF(P29>0,S29/P29,0) -> 0.79383447 | R29: =IF(P29>0,AP29/P29,0) -> 0.20616553 | S29: =AL28 -> 1002765.9 | T29: =AM28 -> 780470.47 | U29: =IF(A29<Param.FireStartjahr,Param.SparrateDepotMonatl*12*(1+Param.SparrateDynamikJaehrl)^($A29-Param.Startjahr),0) -> 0 | V29: =IF(AND(Param.SonstigEinmaligKonto1="Depot",$A29=Param.SonstigEinmaligJahr1),Param.SonstigEinmaligBetrag1,0) -> 0 | W29: =IF(AND(Param.SonstigEinmaligKonto2="Depot",$A29=Param.SonstigEinmaligJahr2),Param.SonstigEinmaligBetrag2,0) -> 0 | X29: =IF(AND(Param.SonstigEinmaligKonto3="Depot",$A29=Param.SonstigEinmaligJahr3),Param.SonstigEinmaligBetrag3,0) -> 0 | Y29: =IF(AND(Param.SonstigEinmaligKonto4="Depot",$A29=Param.SonstigEinmaligJahr4),Param.SonstigEinmaligBetrag4,0) -> 0 | Z29: =IF(AND(Param.SonstigEinmaligKonto5="Depot",$A29=Param.SonstigEinmaligJahr5),Param.SonstigEinmaligBetrag5,0) -> 0 | AA29: =IF(AND(Param.SonstigEinmaligKonto6="Depot",$A29=Param.SonstigEinmaligJahr6),Param.SonstigEinmaligBetrag6,0) -> 0 | AB29: =IF(AND(Param.SonstigEinmaligKonto7="Depot",$A29=Param.SonstigEinmaligJahr7),Param.SonstigEinmaligBetrag7,0) -> 0 | AC29: =IF(AND(Param.SonstigEinmaligKonto8="Depot",$A29=Param.SonstigEinmaligJahr8),Param.SonstigEinmaligBetrag8,0) -> 0 | AD29: =IF(AND(Param.SonstigEinmaligKonto9="Depot",$A29=Param.SonstigEinmaligJahr9),Param.SonstigEinmaligBetrag9,0) -> 0 | AE29: =IF(AND(Param.SonstigEinmaligKonto10="Depot",$A29=Param.SonstigEinmaligJahr10),Param.SonstigEinmaligBetrag10,0) -> 0 | AF29: =Param.SparerPauschbetrag-BF29 -> 0 | AG29: =IF(AND(A29>=Param.FireStartjahr,S29>0),MIN(N29*Q29,S29),0) -> 49385.363 | AH29: =IF(AG29<=0,0,IF(S29<=0,0,AG29/(1-MAX(0,((T29/S29)*(1-Param.Teilfreistellung)-MIN(AF29,AG29)/AG29)*Param.KapSt)))) -> 57672.761 | AI29: =AH29-AG29 -> 8287.3975 | AJ29: =T29-AH29*(T29/S29) -> 735582.74 | AK29: =S29-AH29 -> 945093.15 | AL29: =FV(AO29,12,-(U29/12),-AK29,0) -> 1001798.7 | AM29: =AJ29+AL29-AK29-U29 -> 792288.33 | AN29: =AM29/AL29 -> 0.79086577 | AO29: =(1+IF(AND(A29>=Param.DepotRenditeSpezBeginn1,A29<=Param.DepotRenditeSpezEnde1),Param.DepotRenditeSpezProz1,IF(AND(A29>=Param.DepotRenditeSpezBeginn2,A29<=Param.DepotRenditeSpezEnde2),Param.DepotRenditeSpezProz2,IF(AND(A29>=Param.DepotRenditeSpezBeginn3,A29<=Param.DepotRenditeSpezEnde3),Param.DepotRenditeSpezProz3,IF(AND(A29>=Param.DepotRenditeSpezBeginn4,A29<=Param.DepotRenditeSpezEnde4),Param.DepotRenditeSpezProz4,IF(AND(A29>=Param.DepotRenditeSpezBeginn5,A29<=Param.DepotRenditeSpezEnde5),Param.DepotRenditeSpezProz5,Param.DepotRenditeDefault))))))^(1/12)-1 -> 0.0048675506 | AP29: =BJ28 -> 260426.79 | AQ29: =IF(A29<Param.FireStartjahr,Param.SparrateFestgeldMonatl*12*(1+Param.SparrateDynamikJaehrl)^($A29-Param.Startjahr),0) -> 0 | AR29: =O29 -> 0 | AS29: =IF(AND(Param.SonstigEinmaligKonto1="Festgeld",$A29=Param.SonstigEinmaligJahr1),Param.SonstigEinmaligBetrag1,0) -> 0 | AT29: =IF(AND(Param.SonstigEinmaligKonto2="Festgeld",$A29=Param.SonstigEinmaligJahr2),Param.SonstigEinmaligBetrag2,0) -> 0 | AU29: =IF(AND(Param.SonstigEinmaligKonto3="Festgeld",$A29=Param.SonstigEinmaligJahr3),Param.SonstigEinmaligBetrag3,0) -> 0 | AV29: =IF(AND(Param.SonstigEinmaligKonto4="Festgeld",$A29=Param.SonstigEinmaligJahr4),Param.SonstigEinmaligBetrag4,0) -> 0 | AW29: =IF(AND(Param.SonstigEinmaligKonto5="Festgeld",$A29=Param.SonstigEinmaligJahr5),Param.SonstigEinmaligBetrag5,0) -> 0 | AX29: =IF(AND(Param.SonstigEinmaligKonto6="Festgeld",$A29=Param.SonstigEinmaligJahr6),Param.SonstigEinmaligBetrag6,0) -> 0 | AY29: =IF(AND(Param.SonstigEinmaligKonto7="Festgeld",$A29=Param.SonstigEinmaligJahr7),Param.SonstigEinmaligBetrag7,0) -> 0 | AZ29: =IF(AND(Param.SonstigEinmaligKonto8="Festgeld",$A29=Param.SonstigEinmaligJahr8),Param.SonstigEinmaligBetrag8,0) -> 0 | BA29: =IF(AND(Param.SonstigEinmaligKonto9="Festgeld",$A29=Param.SonstigEinmaligJahr9),Param.SonstigEinmaligBetrag9,0) -> 0 | BB29: =IF(AND(Param.SonstigEinmaligKonto10="Festgeld",$A29=Param.SonstigEinmaligJahr10),Param.SonstigEinmaligBetrag10,0) -> 0 | BC29: =IF(AND(A29>=Param.FireStartjahr,AP29>0),MIN(N29*R29,AP29),0) -> 12825.797 | BD29: =Param.FestgeldZinssatz -> 0.02 | BE29: =(AP29+AQ29-BC29)*BD29 -> 4952.0199 | BF29: =IF(BE29>Param.SparerPauschbetrag,Param.SparerPauschbetrag,BE29) -> 1000 | BG29: =BE29-BF29 -> 3952.0199 | BH29: =BG29*Param.KapSt -> 1042.3452 | BI29: =BE29-BH29 -> 3909.6747 | BJ29: =AP29+SUM(AQ29:BB29)-BC29+BI29 -> 251510.67 | BK29: =AL29+BJ29 -> 1253309.4 | BL29: =BK29/(1+Param.Inflationsrate)^(A29-Param.Startjahr) -> 692923.88 | BM29: =IF(BK29<N29,A29,"") | BN29: =AH29+BC29 -> 70498.558 | BO29: =SUM(AR29:BB29) -> 0 | BP29: =BN29+(-1*BO29) -> 70498.558 | BQ29: =AI29+BH29 -> 9329.7427 | BR29: =IF(BK29>0,BP29/BK29,0) -> 0.056249923
A30: =A29+1 -> 2051 | B30: =B5+(26-1) -> 55 | C30: =IF(A30<Param.FireStartjahr,0,Param.EntnahmeBetragStart*(1+Param.Inflationsrate)^(A30-Param.Startjahr)) -> 55618.323 | D30: =IF(OR($A30<Param.SonstigRegelmJahrBeginn1,$A30>Param.SonstigRegelmJahrEnd1),0,Param.SonstigRegelmBetragJaehrl1*(1+Param.SonstigRegelmSteig1)^(A30-Param.SonstigRegelmJahrBeginn1)) -> 0 | E30: =IF(OR($A30<Param.SonstigRegelmJahrBeginn2,$A30>Param.SonstigRegelmJahrEnd2),0,Param.SonstigRegelmBetragJaehrl2*(1+Param.SonstigRegelmSteig2)^($A30-Param.SonstigRegelmJahrBeginn2)) -> -8108.3694 | F30: =IF(OR($A30<Param.SonstigRegelmJahrBeginn3,$A30>Param.SonstigRegelmJahrEnd3),0,Param.SonstigRegelmBetragJaehrl3*(1+Param.SonstigRegelmSteig3)^($A30-Param.SonstigRegelmJahrBeginn3)) -> 0 | G30: =IF(OR($A30<Param.SonstigRegelmJahrBeginn4,$A30>Param.SonstigRegelmJahrEnd4),0,Param.SonstigRegelmBetragJaehrl4*(1+Param.SonstigRegelmSteig4)^($A30-Param.SonstigRegelmJahrBeginn4)) -> 0 | H30: =IF(OR($A30<Param.SonstigRegelmJahrBeginn5,$A30>Param.SonstigRegelmJahrEnd5),0,Param.SonstigRegelmBetragJaehrl5*(1+Param.SonstigRegelmSteig5)^($A30-Param.SonstigRegelmJahrBeginn5)) -> 0 | I30: =IF(OR($A30<Param.SonstigRegelmJahrBeginn6,$A30>Param.SonstigRegelmJahrEnd6),0,Param.SonstigRegelmBetragJaehrl6*(1+Param.SonstigRegelmSteig6)^($A30-Param.SonstigRegelmJahrBeginn6)) -> 0 | J30: =IF(OR($A30<Param.SonstigRegelmJahrBeginn7,$A30>Param.SonstigRegelmJahrEnd7),0,Param.SonstigRegelmBetragJaehrl7*(1+Param.SonstigRegelmSteig7)^($A30-Param.SonstigRegelmJahrBeginn7)) -> 0 | K30: =IF(OR($A30<Param.SonstigRegelmJahrBeginn8,$A30>Param.SonstigRegelmJahrEnd8),0,Param.SonstigRegelmBetragJaehrl8*(1+Param.SonstigRegelmSteig8)^($A30-Param.SonstigRegelmJahrBeginn8)) -> 0 | L30: =IF(OR($A30<Param.SonstigRegelmJahrBeginn9,$A30>Param.SonstigRegelmJahrEnd9),0,Param.SonstigRegelmBetragJaehrl9*(1+Param.SonstigRegelmSteig9)^($A30-Param.SonstigRegelmJahrBeginn9)) -> 0 | M30: =IF(OR($A30<Param.SonstigRegelmJahrBeginn10,$A30>Param.SonstigRegelmJahrEnd10),0,Param.SonstigRegelmBetragJaehrl10*(1+Param.SonstigRegelmSteig10)^($A30-Param.SonstigRegelmJahrBeginn10)) -> 0 | N30: =MAX(0,C30-SUM(D30:M30)) -> 63726.692 | O30: =IF(N30<=0,SUM(D30:M30)-C30,0) -> 0 | P30: =S30+AP30 -> 1253309.4 | Q30: =IF(P30>0,S30/P30,0) -> 0.79932276 | R30: =IF(P30>0,AP30/P30,0) -> 0.20067724 | S30: =AL29 -> 1001798.7 | T30: =AM29 -> 792288.33 | U30: =IF(A30<Param.FireStartjahr,Param.SparrateDepotMonatl*12*(1+Param.SparrateDynamikJaehrl)^($A30-Param.Startjahr),0) -> 0 | V30: =IF(AND(Param.SonstigEinmaligKonto1="Depot",$A30=Param.SonstigEinmaligJahr1),Param.SonstigEinmaligBetrag1,0) -> 0 | W30: =IF(AND(Param.SonstigEinmaligKonto2="Depot",$A30=Param.SonstigEinmaligJahr2),Param.SonstigEinmaligBetrag2,0) -> 0 | X30: =IF(AND(Param.SonstigEinmaligKonto3="Depot",$A30=Param.SonstigEinmaligJahr3),Param.SonstigEinmaligBetrag3,0) -> 0 | Y30: =IF(AND(Param.SonstigEinmaligKonto4="Depot",$A30=Param.SonstigEinmaligJahr4),Param.SonstigEinmaligBetrag4,0) -> 0 | Z30: =IF(AND(Param.SonstigEinmaligKonto5="Depot",$A30=Param.SonstigEinmaligJahr5),Param.SonstigEinmaligBetrag5,0) -> 0 | AA30: =IF(AND(Param.SonstigEinmaligKonto6="Depot",$A30=Param.SonstigEinmaligJahr6),Param.SonstigEinmaligBetrag6,0) -> 0 | AB30: =IF(AND(Param.SonstigEinmaligKonto7="Depot",$A30=Param.SonstigEinmaligJahr7),Param.SonstigEinmaligBetrag7,0) -> 0 | AC30: =IF(AND(Param.SonstigEinmaligKonto8="Depot",$A30=Param.SonstigEinmaligJahr8),Param.SonstigEinmaligBetrag8,0) -> 0 | AD30: =IF(AND(Param.SonstigEinmaligKonto9="Depot",$A30=Param.SonstigEinmaligJahr9),Param.SonstigEinmaligBetrag9,0) -> 0 | AE30: =IF(AND(Param.SonstigEinmaligKonto10="Depot",$A30=Param.SonstigEinmaligJahr10),Param.SonstigEinmaligBetrag10,0) -> 0 | AF30: =Param.SparerPauschbetrag-BF30 -> 0 | AG30: =IF(AND(A30>=Param.FireStartjahr,S30>0),MIN(N30*Q30,S30),0) -> 50938.196 | AH30: =IF(AG30<=0,0,IF(S30<=0,0,AG30/(1-MAX(0,((T30/S30)*(1-Param.Teilfreistellung)-MIN(AF30,AG30)/AG30)*Param.KapSt)))) -> 59647.549 | AI30: =AH30-AG30 -> 8709.3529 | AJ30: =T30-AH30*(T30/S30) -> 745115.13 | AK30: =S30-AH30 -> 942151.19 | AL30: =FV(AO30,12,-(U30/12),-AK30,0) -> 998680.26 | AM30: =AJ30+AL30-AK30-U30 -> 801644.2 | AN30: =AM30/AL30 -> 0.80270356 | AO30: =(1+IF(AND(A30>=Param.DepotRenditeSpezBeginn1,A30<=Param.DepotRenditeSpezEnde1),Param.DepotRenditeSpezProz1,IF(AND(A30>=Param.DepotRenditeSpezBeginn2,A30<=Param.DepotRenditeSpezEnde2),Param.DepotRenditeSpezProz2,IF(AND(A30>=Param.DepotRenditeSpezBeginn3,A30<=Param.DepotRenditeSpezEnde3),Param.DepotRenditeSpezProz3,IF(AND(A30>=Param.DepotRenditeSpezBeginn4,A30<=Param.DepotRenditeSpezEnde4),Param.DepotRenditeSpezProz4,IF(AND(A30>=Param.DepotRenditeSpezBeginn5,A30<=Param.DepotRenditeSpezEnde5),Param.DepotRenditeSpezProz5,Param.DepotRenditeDefault))))))^(1/12)-1 -> 0.0048675506 | AP30: =BJ29 -> 251510.67 | AQ30: =IF(A30<Param.FireStartjahr,Param.SparrateFestgeldMonatl*12*(1+Param.SparrateDynamikJaehrl)^($A30-Param.Startjahr),0) -> 0 | AR30: =O30 -> 0 | AS30: =IF(AND(Param.SonstigEinmaligKonto1="Festgeld",$A30=Param.SonstigEinmaligJahr1),Param.SonstigEinmaligBetrag1,0) -> 0 | AT30: =IF(AND(Param.SonstigEinmaligKonto2="Festgeld",$A30=Param.SonstigEinmaligJahr2),Param.SonstigEinmaligBetrag2,0) -> 0 | AU30: =IF(AND(Param.SonstigEinmaligKonto3="Festgeld",$A30=Param.SonstigEinmaligJahr3),Param.SonstigEinmaligBetrag3,0) -> 0 | AV30: =IF(AND(Param.SonstigEinmaligKonto4="Festgeld",$A30=Param.SonstigEinmaligJahr4),Param.SonstigEinmaligBetrag4,0) -> 0 | AW30: =IF(AND(Param.SonstigEinmaligKonto5="Festgeld",$A30=Param.SonstigEinmaligJahr5),Param.SonstigEinmaligBetrag5,0) -> 0 | AX30: =IF(AND(Param.SonstigEinmaligKonto6="Festgeld",$A30=Param.SonstigEinmaligJahr6),Param.SonstigEinmaligBetrag6,0) -> 0 | AY30: =IF(AND(Param.SonstigEinmaligKonto7="Festgeld",$A30=Param.SonstigEinmaligJahr7),Param.SonstigEinmaligBetrag7,0) -> 0 | AZ30: =IF(AND(Param.SonstigEinmaligKonto8="Festgeld",$A30=Param.SonstigEinmaligJahr8),Param.SonstigEinmaligBetrag8,0) -> 0 | BA30: =IF(AND(Param.SonstigEinmaligKonto9="Festgeld",$A30=Param.SonstigEinmaligJahr9),Param.SonstigEinmaligBetrag9,0) -> 0 | BB30: =IF(AND(Param.SonstigEinmaligKonto10="Festgeld",$A30=Param.SonstigEinmaligJahr10),Param.SonstigEinmaligBetrag10,0) -> 0 | BC30: =IF(AND(A30>=Param.FireStartjahr,AP30>0),MIN(N30*R30,AP30),0) -> 12788.497 | BD30: =Param.FestgeldZinssatz -> 0.02 | BE30: =(AP30+AQ30-BC30)*BD30 -> 4774.4435 | BF30: =IF(BE30>Param.SparerPauschbetrag,Param.SparerPauschbetrag,BE30) -> 1000 | BG30: =BE30-BF30 -> 3774.4435 | BH30: =BG30*Param.KapSt -> 995.50946 | BI30: =BE30-BH30 -> 3778.934 | BJ30: =AP30+SUM(AQ30:BB30)-BC30+BI30 -> 242501.11 | BK30: =AL30+BJ30 -> 1241181.4 | BL30: =BK30/(1+Param.Inflationsrate)^(A30-Param.Startjahr) -> 669481.55 | BM30: =IF(BK30<N30,A30,"") | BN30: =AH30+BC30 -> 72436.045 | BO30: =SUM(AR30:BB30) -> 0 | BP30: =BN30+(-1*BO30) -> 72436.045 | BQ30: =AI30+BH30 -> 9704.8624 | BR30: =IF(BK30>0,BP30/BK30,0) -> 0.058360565
